Workbook

Sheet Титул
B2: Финансовая модель продукта «ИНГОССЕМЬЯ»
B3: Кейс IngoSight 2026. Все суммы в рублях; выручка и затраты без НДС, если не указано иное.
B5: Лист | C5: Содержание
B6: Допущения | C6: Все исходные параметры по четырем сценариям, расчетные параметры, команда, инвестиции
B7: Льготы ветеранам | C7: Особые условия для ветеранов СВО и ветеранов: скидки, неценовые условия, стоимость программы
B8: Время координатора | C8: Бюджет минут координатора на семью и итог по тарифам
B9: Бюджет MVP | C9: Смета MVP на 3 месяца, проверка лимита 5 млн руб., итоги по категориям
B10: Сводка | C10: NPV, окупаемость, пиковая потребность, выручка и результат по годам для всех сценариев
B11: Юнит-экономика | C11: Маржинальный доход, LTV, CAC и окупаемость CAC на одну семью
B12: Рынок | C12: TAM, SAM и SOM
B13: Пессимистичный | C13: Помесячный расчет на 60 месяцев и налог по годам
B14: Базовый | C14: Помесячный расчет на 60 месяцев и налог по годам
B15: Оптимистичный | C15: Помесячный расчет на 60 месяцев и налог по годам
B16: Версия 1 | C16: Первая версия продукта без голосового робота: показывает, почему продукт пересобран
... B19: Риски модели | C19: Подводные камни и как они учтены
B21: Обозначения
B22: Синий шрифт: исходные данные и допущения, их можно менять
B23: Черный шрифт: формулы
B24: Зеленый шрифт: ссылка на другой лист
B25: Отрицательные значения показаны в скобках, нулевые прочерком
B26: Метки у чисел: факт (из источника), расчет (на основе фактов), допущение (команды)

Sheet Допущения
A1: Исходные данные и допущения модели
A2: Синий шрифт: исходное значение, его можно менять. Черный шрифт: формула. Столбцы сценариев без собственного значения ссылаются на базовый сценарий.
A4: Параметр | B4: Единица | C4: Пессими-стичный | D4: Базовый | E4: Оптими-стичный | F4: Версия 1 без триажа | G4: Метка | H4: Источник или обоснование
A5: 1. Общие параметры
A6: НДС | B6: доля | C6: =$D6 -> 0.22 | D6: 0.22 | E6: =$D6 -> 0.22 | F6: =$D6 -> 0.22 | G6: факт | H6: НДС 22% с 01.01.2026, НК РФ ст. 164
A7: Налог на прибыль | B7: доля | C7: =$D7 -> 0.25 | D7: 0.25 | E7: =$D7 -> 0.25 | F7: =$D7 -> 0.25 | G7: факт | H7: Налог на прибыль 25% с 2025, НК РФ ст. 284
A8: Лимит переноса убытков от налоговой базы года | B8: доля | C8: =$D8 -> 0.5 | D8: 0.5 | E8: =$D8 -> 0.5 | F8: =$D8 -> 0.5 | G8: факт | H8: Перенос убытков не более 50% базы в год, НК РФ ст. 283
A9: Коэффициент страховых взносов к ФОТ | B9: коэф. | C9: =$D9 -> 1.302 | D9: 1.302 | E9: =$D9 -> 1.302 | F9: =$D9 -> 1.302 | G9: допущение | H9: Страховые взносы 30% + 0,2% травматизм, без учета снижения выше предельной базы
A10: Ставка дисконтирования, годовая | B10: доля | C10: =$D10 -> 0.22 | D10: 0.22 | E10: =$D10 -> 0.22 | F10: =$D10 -> 0.22 | G10: допущение | H10: Ставка дисконтирования для венчурного проекта внутри страховщика
A11: Индексация зарплат в год | B11: доля | C11: =$D11 -> 0.08 | D11: 0.08 | E11: =$D11 -> 0.08 | F11: =$D11 -> 0.08 | G11: допущение | H11: Индексация зарплат в год
A12: Индексация цен подписки в год, со 2-го года | B12: доля | C12: =$D12 -> 0.07 | D12: 0.07 | E12: =$D12 -> 0.07 | F12: =$D12 -> 0.07 | G12: допущение | H12: Индексация цен подписки со 2-го года
A13: Эквайринг от суммы оплаты | B13: доля | C13: =$D13 -> 0.018 | D13: 0.018 | E13: =$D13 -> 0.018 | F13: =$D13 -> 0.018 | G13: допущение | H13: Эквайринг 1,8% от оплаты
A14: Накладные расходы от ФОТ | B14: доля | C14: =$D14 -> 0.1 | D14: 0.1 | E14: =$D14 -> 0.1 | F14: =$D14 -> 0.1 | G14: допущение | H14: Накладные (офис, HR, бухгалтерия) 10% от ФОТ
A15: Рабочих часов координатора в месяц | B15: ч | C15: =$D15 -> 165 | D15: 165 | E15: =$D15 -> 165 | F15: =$D15 -> 165 | G15: допущение | H15: Производственный календарь
A16: Доля времени на работу с семьями | B16: доля | C16: =$D16 -> 0.75 | D16: 0.75 | E16: =$D16 -> 0.75 | F16: =$D16 -> 0.75 | G16: допущение | H16: Остальное: обучение, планерки, документы
A17: Множитель покрытия смен | B17: коэф. | C17: =$D17 -> 1.2 | D17: 1.2 | E17: =$D17 -> 1.2 | F17: =$D17 -> 1.2 | G17: допущение | H17: Отпуска, больничные и смены 8-22 без выходных
... A21: Резерв на непредвиденные расходы MVP | B21: доля | C21: =$D21 -> 0.1 | D21: 0.1 | E21: =$D21 -> 0.1 | F21: =$D21 -> 0.1 | G21: допущение | H21: Резерв на непредвиденные расходы
A22: 2. Параметры сценариев
A23: Цена тарифа «Базовый» с НДС | B23: руб./мес. | C23: =$D23 -> 2490 | D23: 2490 | E23: =$D23 -> 2490 | F23: 1990 | G23: допущение | H23: Базовый: робот каждый день, координатор раз в месяц и по флагу; руб в месяц с НДС
A24: Цена тарифа «Расширенный» с НДС | B24: руб./мес. | C24: =$D24 -> 4990 | D24: 4990 | E24: =$D24 -> 4990 | F24: 3990 | G24: допущение | H24: Расширенный: координатор каждую неделю; руб в месяц с НДС
A25: Доля тарифа «Расширенный» в B2C | B25: доля | C25: 0.15 | D25: 0.25 | E25: 0.3 | F25: 0.3 | G25: допущение | H25: Доля Расширенного тарифа
A26: Покупки услуг партнеров через координатора | B26: руб./семью в мес. | C26: =$D26 -> 1500 | D26: 1500 | E26: =$D26 -> 1500 | F26: =$D26 -> 1500 | G26: допущение | H26: Услуги партнеров через координатора, руб на семью в месяц
A27: Агентская комиссия с услуг партнеров | B27: доля | C27: =$D27 -> 0.1 | D27: 0.1 | E27: =$D27 -> 0.1 | F27: =$D27 -> 0.1 | G27: допущение | H27: Агентская комиссия сервисной компании с услуг партнеров
A28: Цена опции к корпоративному ДМС с НДС | B28: руб./мес. | C28: =$D28 -> 1990 | D28: 1990 | E28: =$D28 -> 1990 | F28: 1500 | G28: допущение | H28: Опция к корпоративному ДМС, руб в месяц за активную семью, Базовый уровень
A29: CAC во внутренних каналах | B29: руб. | C29: =$D29 -> 1500 | D29: 1500 | E29: =$D29 -> 1500 | F29: =$D29 -> 1500 | G29: допущение | H29: CAC во внутренних каналах: IngoMobile, рассылки клиентам ДМС, агенты
A30: Емкость внутренних каналов | B30: семей/мес. | C30: 200 | D30: 300 | E30: 400 | F30: =$D30 -> 300 | G30: допущение | H30: Сколько новых семей в месяц могут дать внутренние каналы
A31: CAC во внешних каналах | B31: руб. | C31: 7500 | D31: 6000 | E31: 4500 | F31: =$D31 -> 6000 | G31: допущение | H31: CAC во внешних каналах: клик 50-100 руб., конверсия в оплату 1-2%
A32: Маркетинговый бюджет в 4-м месяце | B32: руб. | C32: =$D32 -> 400000 | D32: 400000 | E32: =$D32 -> 400000 | F32: =$D32 -> 400000 | G32: допущение | H32: Маркетинг в 4-м месяце, руб
A33: Рост маркетингового бюджета в месяц | B33: доля | C33: =$D33 -> 0.08 | D33: 0.08 | E33: =$D33 -> 0.08 | F33: =$D33 -> 0.08 | G33: допущение | H33: Рост маркетингового бюджета в месяц до потолка
A34: Потолок маркетингового бюджета | B34: руб./мес. | C34: =$D34 -> 2500000 | D34: 2500000 | E34: =$D34 -> 2500000 | F34: =$D34 -> 2500000 | G34: допущение | H34: Потолок маркетинга в месяц
A35: Месяц запуска партнерского канала с фондом «Защитники Отечества» | B35: месяц | C35: =$D35 -> 6 | D35: 6 | E35: =$D35 -> 6 | F35: =$D35 -> 6 | G35: допущение | H35: Начало партнерского канала с фондом «Защитники Отечества» после пилота в MVP
A36: Новых семей в месяц через партнерский канал фонда | B36: семей/мес. | C36: 20 | D36: 40 | E36: 60 | F36: =$D36 -> 40 | G36: допущение | H36: Новых семей в месяц по рекомендациям социальных координаторов фонда и ветеранских организаций
A37: Затраты на привлечение в партнерском канале | B37: руб. | C37: =$D37 -> 500 | D37: 500 | E37: =$D37 -> 500 | F37: =$D37 -> 500 | G37: допущение | H37: Затраты на привлечение в партнерском канале: материалы и обучение координаторов фонда
A38: Месяц первого корпоративного клиента | B38: месяц | C38: =$D38 -> 7 | D38: 7 | E38: =$D38 -> 7 | F38: =$D38 -> 7 | G38: допущение | H38: Первый корпоративный клиент; переговоры с месяца 3
A39: Новых корпоративных клиентов в месяц | B39: клиентов | C39: 0.5 | D39: 1 | E39: 1.5 | F39: =$D39 -> 1 | G39: допущение | H39: Новых корпоративных клиентов в месяц
A40: Сотрудников у корпоративного клиента | B40: чел. | C40: =$D40 -> 2000 | D40: 2000 | E40: =$D40 -> 2000 | F40: =$D40 -> 2000 | G40: допущение | H40: Сотрудников у корпоративного клиента
A41: Доля сотрудников, подключивших родителя | B41: доля | C41: 0.02 | D41: 0.03 | E41: 0.04 | F41: =$D41 -> 0.03 | G41: допущение | H41: Доля сотрудников, которые подключают родителя
A42: Срок разгона активации у клиента | B42: мес. | C42: =$D42 -> 3 | D42: 3 | E42: =$D42 -> 3 | F42: =$D42 -> 3 | G42: допущение | H42: Месяцев до полной активации внутри клиента
A43: Отток после первого месяца | B43: доля | C43: 0.35 | D43: 0.25 | E43: 0.18 | F43: =$D43 -> 0.25 | G43: допущение | H43: Отток после первого месяца, порог H5
A44: Отток B2C в месяц со второго месяца | B44: доля | C44: 0.08 | D44: 0.06 | E44: 0.045 | F44: =$D44 -> 0.06 | G44: допущение | H44: Отток B2C в месяц со второго месяца
A45: Отток B2B2C в месяц | B45: доля | C45: =$D45 -> 0.02 | D45: 0.02 | E45: =$D45 -> 0.02 | F45: =$D45 -> 0.02 | G45: допущение | H45: Отток B2B2C в месяц
A46: Множитель к бюджету минут координатора | B46: коэф. | C46: 1.3 | D46: 1 | E46: 0.85 | F46: =$D46 -> 1 | G46: допущение | H46: Множитель к бюджету минут (сценарии)
A47: Зарплата координатора | B47: руб./мес. | C47: 80000 | D47: 70000 | E47: 65000 | F47: 85000 | G47: допущение | H47: Зарплата координатора в региональном контакт-центре, руб
A48: Координаторов на одного супервизора | B48: чел. | C48: =$D48 -> 12 | D48: 12 | E48: =$D48 -> 12 | F48: 10 | G48: допущение | H48: Координаторов на одного супервизора
A49: Зарплата супервизора | B49: руб./мес. | C49: =$D49 -> 110000 | D49: 110000 | E49: =$D49 -> 110000 | F49: 130000 | G49: допущение | H49: Зарплата супервизора
A50: Текучесть координаторов в год | B50: доля | C50: =$D50 -> 0.3 | D50: 0.3 | E50: =$D50 -> 0.3 | F50: =$D50 -> 0.3 | G50: допущение | H50: Текучесть координаторов в год
A51: Стоимость обучения нового координатора | B51: руб. | C51: =$D51 -> 70000 | D51: 70000 | E51: =$D51 -> 70000 | F51: 77500 | G51: расчет | H51: Курс 35 тыс. + полмесяца зарплаты на обучение
A52: CRM и телефония на рабочее место | B52: руб./мес. | C52: =$D52 -> 2700 | D52: 2700 | E52: =$D52 -> 2700 | F52: =$D52 -> 2700 | G52: допущение | H52: CRM и телефония на рабочее место в месяц
A53: Телемедицина на семью | B53: руб./мес. | C53: =$D53 -> 200 | D53: 200 | E53: =$D53 -> 200 | F53: 280 | G53: допущение | H53: 0,25 консультации x 800 руб
A54: Связь на семью (робот, звонки, СМС) | B54: руб./мес. | C54: =$D54 -> 165 | D54: 165 | E54: =$D54 -> 165 | F54: =$D54 -> 165 | G54: расчет | H54: Робот 30 мин + координатор до 30 мин + 10 СМС
A55: Размещение в контуре ИСПДн группы | B55: руб./мес. | C55: =$D55 -> 40000 | D55: 40000 | E55: =$D55 -> 40000 | F55: =$D55 -> 40000 | G55: допущение | H55: Размещение в контуре ИСПДн группы после MVP, в месяц
A56: Доплата за размещение на 1000 семей | B56: руб./мес. | C56: =$D56 -> 8000 | D56: 8000 | E56: =$D56 -> 8000 | F56: =$D56 -> 8000 | G56: допущение | H56: Доплата за каждую 1000 семей
A57: Сопровождение сервисной компании | B57: руб./мес. | C57: =$D57 -> 100000 | D57: 100000 | E57: =$D57 -> 100000 | F57: =$D57 -> 100000 | G57: допущение | H57: Сопровождение договоров и отчетности сервисной компании, в месяц
A58: Доля семей, покупающих ДМС или полис ухода в месяц | B58: доля | C58: 0.003 | D58: 0.006 | E58: 0.009 | F58: =$D58 -> 0.006 | G58: допущение | H58: Доля активных семей, покупающих ДМС родителю или полис ухода в месяц
A59: Маржинальный доход группы с кросс-продажи | B59: руб. | C59: =$D59 -> 5500 | D59: 5500 | E59: =$D59 -> 5500 | F59: =$D59 -> 5500 | G59: допущение | H59: Маржинальный доход страховщика с одной кросс-продажи
A60: Доля платящих семей в MVP | B60: доля | C60: =$D60 -> 0.6 | D60: 0.6 | E60: =$D60 -> 0.6 | F60: =$D60 -> 0.6 | G60: допущение | H60: Доля платящих в MVP, остальные на пробном периоде
A61: 3. Нагрузка координатора в версии 1 (без голосового робота)
A62: Фиксированная нагрузка, семей «Базовый» | B62: семей | F62: 100 | G62: допущение | H62: Координатор звонит каждой семье раз в неделю; в сценариях 1-3 нагрузка считается от минут
A63: Вес семьи «Расширенный» к «Базовому» | B63: коэф. | F63: 1.8 | G63: допущение | H63: Координатор звонит каждой семье раз в неделю; в сценариях 1-3 нагрузка считается от минут
A64: 4. Расчетные параметры
A65: Минут координатора на семью «Базовый» с множителем | B65: мин./мес. | C65: ='Время координатора'!$E$11*C46 -> 62.79 | D65: ='Время координатора'!$E$11*D46 -> 48.3 | E65: ='Время координатора'!$E$11*E46 -> 41.055 | F65: ='Время координатора'!$E$11*F46 -> 48.3 | G65: расчет | H65: Лист «Время координатора»
A66: Минут координатора на семью «Расширенный» с множителем | B66: мин./мес. | C66: ='Время координатора'!$E$18*C46 -> 156.39 | D66: ='Время координатора'!$E$18*D46 -> 120.3 | E66: ='Время координатора'!$E$18*E46 -> 102.255 | F66: ='Время координатора'!$E$18*F46 -> 120.3 | G66: расчет | H66: Лист «Время координатора»
A67: Продуктивных минут координатора с учетом покрытия смен | B67: мин./мес. | C67: =C15*60*C16/C17 -> 6187.5 | D67: =D15*60*D16/D17 -> 6187.5 | E67: =E15*60*E16/E17 -> 6187.5 | F67: =F15*60*F16/F17 -> 6187.5 | G67: расчет | H67: Часы x 60 x доля / множитель покрытия
A68: Семей «Базовый» на координатора | B68: семей | C68: =IF(C62="",C67/C65,C62/C17) -> 98.542762 | D68: =IF(D62="",D67/D65,D62/D17) -> 128.10559 | E68: =IF(E62="",E67/E65,E62/E17) -> 150.71246 | F68: =IF(F62="",F67/F65,F62/F17) -> 83.333333 | G68: расчет | H68: Емкость / минуты на семью
A69: Семей «Расширенный» на координатора | B69: семей | C69: =IF(C62="",C67/C66,C62/C63/C17) -> 39.56455 | D69: =IF(D62="",D67/D66,D62/D63/D17) -> 51.433915 | E69: =IF(E62="",E67/E66,E62/E63/E17) -> 60.510488 | F69: =IF(F62="",F67/F66,F62/F63/F17) -> 46.296296 | G69: расчет | H69: Емкость / минуты на семью
A70: Средний чек B2C с НДС по прейскуранту, 1-й год | B70: руб./мес. | C70: =C23*(1-C25)+C24*C25 -> 2865 | D70: =D23*(1-D25)+D24*D25 -> 3115 | E70: =E23*(1-E25)+E24*E25 -> 3240 | F70: =F23*(1-F25)+F24*F25 -> 2590 | G70: расчет | H70: Взвешенная цена тарифов
A71: Средний чек B2C с НДС с учетом льгот ветеранам, 1-й год | B71: руб./мес. | C71: =C70*(1-'Льготы ветеранам'!$D$9) -> 2727.48 | D71: =D70*(1-'Льготы ветеранам'!$D$9) -> 2965.48 | E71: =E70*(1-'Льготы ветеранам'!$D$9) -> 3084.48 | F71: =F70*(1-'Льготы ветеранам'!$D$9) -> 2465.68 | G71: расчет | H71: Лист «Льготы ветеранам»
A72: Недополученная выручка на 1 руб. оплаченной подписки | B72: коэф. | C72: ='Льготы ветеранам'!$D$9/(1-'Льготы ветеранам'!$D$9) -> 0.050420168 | D72: ='Льготы ветеранам'!$D$9/(1-'Льготы ветеранам'!$D$9) -> 0.050420168 | E72: ='Льготы ветеранам'!$D$9/(1-'Льготы ветеранам'!$D$9) -> 0.050420168 | F72: ='Льготы ветеранам'!$D$9/(1-'Льготы ветеранам'!$D$9) -> 0.050420168 | G72: расчет | H72: Скидка / (1 - скидка)
A73: Семей B2B2C от клиентов одного месяца | B73: семей | C73: =C39*C40*C41 -> 20 | D73: =D39*D40*D41 -> 60 | E73: =E39*E40*E41 -> 120 | F73: =F39*F40*F41 -> 60 | G73: расчет | H73: Клиенты x сотрудники x активация
A74: Ставка дисконтирования, месячная | B74: доля | C74: =(1+C10)^(1/12)-1 -> 0.016708964 | D74: =(1+D10)^(1/12)-1 -> 0.016708964 | E74: =(1+E10)^(1/12)-1 -> 0.016708964 | F74: =(1+F10)^(1/12)-1 -> 0.016708964 | G74: расчет | H74: Эквивалент годовой ставки
A76: 5. Семьи в MVP
A77: Месяц MVP | B77: Семей
A78: 1 | B78: 0
A79: 2 | B79: 50
A80: 3 | B80: 150
A82: 6. Постоянная команда после MVP
A83: Роль | B83: Ставка, FTE | C83: Зарплата, руб./мес. | D83: Месяц выхода | E83: Комментарий
A84: Руководитель продукта | B84: 1 | C84: 230000 | D84: 4
A85: Разработчик 1 | B85: 1 | C85: 260000 | D85: 4
A86: Разработчик 2 | B86: 1 | C86: 260000 | D86: 10 | E86: Второй разработчик под интеграции
A87: Аналитик | B87: 1 | C87: 170000 | D87: 4
A88: Врач-методист | B88: 0.5 | C88: 220000 | D88: 4
A89: Дизайнер | B89: 0.5 | C89: 200000 | D89: 4
A90: Маркетолог | B90: 1 | C90: 180000 | D90: 6
A91: Менеджер B2B | B91: 1 | C91: 200000 | D91: 6
A93: 7. Инвестиции после MVP
A94: Назначение | B94: Месяц | C94: Сумма, руб.
A95: Интеграция в IngoMobile | B95: 4 | C95: 1000000
A96: Интеграция в IngoMobile | B96: 5 | C96: 1000000
A97: Интеграция в IngoMobile | B97: 6 | C97: 1000000
A98: Интеграция с клиниками через МедРокет | B98: 7 | C98: 500000
A99: Интеграция с клиниками через МедРокет | B99: 8 | C99: 500000
A100: Интеграция с клиниками через МедРокет | B100: 9 | C100: 500000
A101: ИИ-черновики отчетов и доработка робота | B101: 10 | C101: 350000
A102: ИИ-черновики отчетов и доработка робота | B102: 11 | C102: 350000
A103: ИИ-черновики отчетов и доработка робота | B103: 12 | C103: 300000
A104: Итого | C104: =SUM(C95:C103) -> 5500000

Sheet Льготы ветеранам
A1: Особые условия для ветеранов СВО и ветеранов
A2: Льгота действует на подписку B2C. Скидка уменьшает выручку во всех сценариях; ее сумма показана на листе «Сводка».
A4: Категория | B4: Доля семей B2C | C4: Скидка с подписки | D4: Вклад в среднюю скидку | E4: Условие и обоснование
A5: Родители погибших участников СВО | B5: 0.01 | C5: 1 | D5: =B5*C5 -> 0.01 | E5: Подписка «Базовый» бесплатно: у родителя нет ребенка, который организовал бы помощь [допущение]
A6: Участники СВО на службе (оплачивают сервис для родителя) | B6: 0.03 | C6: 0.5 | D6: =B6*C6 -> 0.015 | E6: На время службы и 6 месяцев после возвращения: сами не могут звонить и ездить к родителю [допущение]
A7: Ветераны боевых действий, включая ветеранов СВО, и инвалиды войны | B7: 0.05 | C7: 0.3 | D7: =B7*C7 -> 0.015 | E7: Плательщик или родитель со статусом по 5-ФЗ «О ветеранах» (с изменениями 83-ФЗ от 21.04.2025) [допущение]
A8: Ветераны ВОВ и ветераны труда (родитель) | B8: 0.08 | C8: 0.1 | D8: =B8*C8 -> 0.008 | E8: Родитель 70+ со статусом ветерана; доля уточняется анкетой [допущение]
A9: Итого: доля семей с льготой и средняя скидка | B9: =SUM(B5:B8) -> 0.17 | D9: =SUM(D5:D8) -> 0.048 | E9: Средняя скидка применяется к чеку B2C во всех сценариях
A10: Минут координатора в месяц на семью с льготой | B10: 10 | E10: Минут координатора в месяц на семью с льготой: внеочередная запись, льготные лекарства, санаторий [допущение]
A12: Неценовые условия
A13: Условие | B13: Содержание
A14: Цена | B14: Скидки по категориям из таблицы выше; для родителей погибших участников СВО тариф «Базовый» бесплатно
A15: Навигатор льгот | B15: Координатор помогает получить положенное по закону: внеочередную медпомощь, льготные лекарства, санаторно-курортное лечение, меры региональной поддержки
A16: Приоритет | B16: Отдельная линия координаторов, прошедших курс по льготам ветеранов и работе с семьями участников СВО
A17: Психологическая поддержка | B17: Консультация психолога через телемедицину Ингосстраха для семей участников СВО
A18: Партнерство | B18: Обмен обращениями с фондом «Защитники Отечества»: социальный координатор фонда передает задачи по медпомощи родителю, ИНГОССЕМЬЯ сообщает фонду о социальных вопросах семьи
A19: Работа для ветеранов | B19: Ветераны СВО и члены семей участников СВО в приоритете при найме координаторов
A20: Проверка статуса | B20: Удостоверение проверяется при подключении; в CRM хранится только категория льготы и дата проверки
A22: Стоимость льгот для сервиса (недополученная выручка без НДС)
A23: Сценарий | B23: За 60 мес., руб. | C23: Доля выручки за 60 мес.
A24: Пессимистичный | B24: =Сводка!$B$28 -> 23946264 | C24: =B24/(SUM(Пессимистичный!$W$6:$W$65)+B24) -> 0.0424244
A25: Базовый | B25: =Сводка!$C$28 -> 46773207 | C25: =B25/(SUM(Базовый!$W$6:$W$65)+B25) -> 0.040856096
A26: Оптимистичный | B26: =Сводка!$D$28 -> 77956259 | C26: =B26/(SUM(Оптимистичный!$W$6:$W$65)+B26) -> 0.039996813
A27: Версия 1 | B27: =Сводка!$E$28 -> 38890082 | C27: =B27/(SUM('Версия 1'!$W$6:$W$65)+B27) -> 0.040932126

Sheet Время координатора
A1: Бюджет живого времени координатора на одну семью в месяц
A2: Нагрузка на координатора рассчитывается от минут, а не задается числом
A4: Тариф | B4: Операция | C4: Раз в месяц | D4: Минут на операцию | E4: Минут в месяц
A5: Базовый | B5: Плановый звонок родителю | C5: 1 | D5: 12 | E5: =C5*D5 -> 12
A6: Базовый | B6: Перезвон по флагу голосового робота | C6: 0.8 | D6: 10 | E6: =C6*D6 -> 8
A7: Базовый | B7: Организация услуги (запись, анализы, доставка) | C7: 1.2 | D7: 15 | E7: =C7*D7 -> 18
A8: Базовый | B8: Проверка отчета ребенку (черновик готовит ИИ) | C8: 1.2 | D8: 3 | E8: =C8*D8 -> 3.6
A9: Базовый | B9: Ответы ребенку в чате | C9: 1 | D9: 5 | E9: =C9*D9 -> 5
A10: Базовый | B10: Помощь с льготами ветеранов (доля семей с льготой) | C10: ='Льготы ветеранам'!$B$9 -> 0.17 | D10: ='Льготы ветеранам'!$B$10 -> 10 | E10: =C10*D10 -> 1.7
A11: Итого «Базовый» | E11: =SUM(E5:E10) -> 48.3
A12: Расширенный | B12: Плановые звонки родителю | C12: 4.3 | D12: 12 | E12: =C12*D12 -> 51.6
A13: Расширенный | B13: Перезвон по флагу голосового робота | C13: 1.2 | D13: 10 | E13: =C13*D13 -> 12
A14: Расширенный | B14: Организация услуг | C14: 2.5 | D14: 15 | E14: =C14*D14 -> 37.5
A15: Расширенный | B15: Проверка отчетов ребенку | C15: 2.5 | D15: 3 | E15: =C15*D15 -> 7.5
A16: Расширенный | B16: Ответы ребенку в чате | C16: 1 | D16: 10 | E16: =C16*D16 -> 10
A17: Расширенный | B17: Помощь с льготами ветеранов (доля семей с льготой) | C17: ='Льготы ветеранам'!$B$9 -> 0.17 | D17: ='Льготы ветеранам'!$B$10 -> 10 | E17: =C17*D17 -> 1.7
A18: Итого «Расширенный» | E18: =SUM(E12:E17) -> 120.3

Sheet Бюджет MVP
A1: Бюджет MVP на 3 месяца
A2: Итог по статье = количество x цена x месяцев x коэффициент взносов (для ФОТ)
A4: Категория | B4: Статья | C4: Кол-во | D4: Цена за ед., руб. | E4: Месяцев | F4: Взносы | G4: Итого, руб. | H4: Метка | I4: Комментарий
A5: Команда | B5: Руководитель продукта | C5: 1 | D5: 230000 | E5: 3 | F5: да | G5: =ROUND(C5*D5*E5*IF(F5="да",Допущения!$D$9,1),0) -> 898380 | H5: допущение | I5: Рыночная зарплата Москва, 1 FTE
A6: Команда | B6: Исследователь и аналитик | C6: 0.3 | D6: 170000 | E6: 3 | F6: да | G6: =ROUND(C6*D6*E6*IF(F6="да",Допущения!$D$9,1),0) -> 199206 | H6: допущение | I6: Анкеты, когорты; первые интервью проводит команда до старта
A7: Команда | B7: Разработчик бота и интеграций | C7: 0.4 | D7: 260000 | E7: 3 | F7: да | G7: =ROUND(C7*D7*E7*IF(F7="да",Допущения!$D$9,1),0) -> 406224 | H7: допущение | I7: Бот в MAX на конструкторе, CRM, телефония
A8: Команда | B8: Координаторы (3 человека) | C8: 3 | D8: 70000 | E8: 2.5 | F8: да | G8: =ROUND(C8*D8*E8*IF(F8="да",Допущения!$D$9,1),0) -> 683550 | H8: допущение | I8: Операторы ДМС регионального контакт-центра; 1-й месяц на половину ставки
A9: Команда | B9: Врач-методист (терапевт или гериатр) | C9: 0.25 | D9: 220000 | E9: 3 | F9: да | G9: =ROUND(C9*D9*E9*IF(F9="да",Допущения!$D$9,1),0) -> 214830 | H9: допущение | I9: Протоколы эскалации, супервизия
A10: Команда | B10: Юрист по ПДн и договорам | C10: 0.2 | D10: 240000 | E10: 2 | F10: да | G10: =ROUND(C10*D10*E10*IF(F10="да",Допущения!$D$9,1),0) -> 124992 | H10: допущение | I10: Согласия на медданные, договоры с партнерами
A11: Команда | B11: Дизайнер | C11: 0.2 | D11: 200000 | E11: 2 | F11: да | G11: =ROUND(C11*D11*E11*IF(F11="да",Допущения!$D$9,1),0) -> 104160 | H11: допущение | I11: Бот, лендинг, отчеты
A12: Обучение | B12: Курс по работе с пожилыми и основам гериатрии | C12: 3 | D12: 35000 | E12: 1 | F12: нет | G12: =ROUND(C12*D12*E12*IF(F12="да",Допущения!$D$9,1),0) -> 105000 | H12: допущение | I12: Внешний курс на каждого координатора
A13: Обучение | B13: Скрипты звонков и супервизия психолога | C13: 1 | D13: 60000 | E13: 1 | F13: нет | G13: =ROUND(C13*D13*E13*IF(F13="да",Допущения!$D$9,1),0) -> 60000 | H13: допущение | I13: Профилактика выгорания
A14: Обучение | B14: Обучение операторов ДМС для резерва | C14: 4 | D14: 8000 | E14: 1 | F14: нет | G14: =ROUND(C14*D14*E14*IF(F14="да",Допущения!$D$9,1),0) -> 32000 | H14: допущение | I14: Внутренний тренинг, 1 день
A15: Обучение | B15: Курс: льготы ветеранов и работа с семьями участников СВО | C15: 3 | D15: 15000 | E15: 1 | F15: нет | G15: =ROUND(C15*D15*E15*IF(F15="да",Допущения!$D$9,1),0) -> 45000 | H15: допущение | I15: 5-ФЗ «О ветеранах», региональные меры, психологические аспекты; программа с фондом «Защитники Отечества»
A16: Юридическая схема | B16: Оформление сервиса через сервисную компанию группы | C16: 1 | D16: 200000 | E16: 1 | F16: нет | G16: =ROUND(C16*D16*E16*IF(F16="да",Допущения!$D$9,1),0) -> 200000 | H16: допущение | I16: Ст. 6 закона 4015-1 ограничивает страховщика страховой деятельностью; заключение юриста, оферта, агентские договоры
... A30: Маркетинг и исследования | B30: Вознаграждение респондентам | C30: 20 | D30: 1500 | E30: 1 | F30: нет | G30: =ROUND(C30*D30*E30*IF(F30="да",Допущения!$D$9,1),0) -> 30000 | H30: допущение | I30: 20 глубинных интервью
A31: Накладные | B31: Накладные от ФОТ команды MVP | G31: =ROUND(SUMIF(F5:F30,"да",G5:G30)*Допущения!$D$14,0) -> 263134 | H31: допущение | I31: Рабочие места, HR, бухгалтерия
A32: Резерв | B32: Резерв на непредвиденные расходы | G32: =ROUND((SUM(G5:G30)+G31)*Допущения!$D$21,0) -> 443088 | H32: допущение | I32: Резерв на непредвиденные расходы
A33: Итого бюджет MVP | G33: =SUM(G5:G32) -> 4873964
A34: Лимит бюджета | G34: =Допущения!$D$20 -> 5000000 | I34: Условие кейса
A35: Запас до лимита | G35: =G34-G33 -> 126036 | I35: =IF(G35>=0,"Бюджет в пределах лимита","Превышение лимита") -> Бюджет в пределах лимита
A37: Бюджет по категориям
A38: Категория | B38: Сумма, руб. | C38: Доля
A39: Команда | B39: =SUMIF($A$5:$A$32,A39,$G$5:$G$32) -> 2631342 | C39: =B39/$G$33 -> 0.53987719
A40: Обучение | B40: =SUMIF($A$5:$A$32,A40,$G$5:$G$32) -> 242000 | C40: =B40/$G$33 -> 0.049651577
A41: Юридическая схема | B41: =SUMIF($A$5:$A$32,A41,$G$5:$G$32) -> 200000 | C41: =B41/$G$33 -> 0.041034361
A42: Лицензии и ИТ | B42: =SUMIF($A$5:$A$32,A42,$G$5:$G$32) -> 667400 | C42: =B42/$G$33 -> 0.13693166
A43: Операции | B43: =SUMIF($A$5:$A$32,A43,$G$5:$G$32) -> 97000 | C43: =B43/$G$33 -> 0.019901665
A44: Маркетинг и исследования | B44: =SUMIF($A$5:$A$32,A44,$G$5:$G$32) -> 330000 | C44: =B44/$G$33 -> 0.067706696
A45: Накладные | B45: =SUMIF($A$5:$A$32,A45,$G$5:$G$32) -> 263134 | C45: =B45/$G$33 -> 0.053987678
A46: Резерв | B46: =SUMIF($A$5:$A$32,A46,$G$5:$G$32) -> 443088 | C46: =B46/$G$33 -> 0.090909166
A47: Итого | B47: =SUM(B39:B46) -> 4873964 | C47: =SUM(C39:C46) -> 1

Sheet Сводка
A1: Сводные результаты по сценариям
A2: Горизонт 60 месяцев, NPV по месячной ставке дисконтирования
A4: Показатель | B4: Пессимистичный | C4: Базовый | D4: Оптимистичный | E4: Версия 1 без триажа
A5: NPV до налога за 36 мес., руб. | B5: =SUMPRODUCT(Пессимистичный!$AI$6:$AI$41,Пессимистичный!$AO$6:$AO$41) -> -89328769 | C5: =SUMPRODUCT(Базовый!$AI$6:$AI$41,Базовый!$AO$6:$AO$41) -> -21114552 | D5: =SUMPRODUCT(Оптимистичный!$AI$6:$AI$41,Оптимистичный!$AO$6:$AO$41) -> 66276520 | E5: =SUMPRODUCT('Версия 1'!$AI$6:$AI$41,'Версия 1'!$AO$6:$AO$41) -> -1.6994413e+08
A6: NPV после налога за 36 мес., руб. | B6: =SUMPRODUCT(Пессимистичный!$AN$6:$AN$41,Пессимистичный!$AO$6:$AO$41) -> -89328769 | C6: =SUMPRODUCT(Базовый!$AN$6:$AN$41,Базовый!$AO$6:$AO$41) -> -21953294 | D6: =SUMPRODUCT(Оптимистичный!$AN$6:$AN$41,Оптимистичный!$AO$6:$AO$41) -> 50060163 | E6: =SUMPRODUCT('Версия 1'!$AN$6:$AN$41,'Версия 1'!$AO$6:$AO$41) -> -1.6994413e+08
A7: NPV до налога за 60 мес., руб. | B7: =SUMPRODUCT(Пессимистичный!$AI$6:$AI$65,Пессимистичный!$AO$6:$AO$65) -> -1.3308264e+08 | C7: =SUMPRODUCT(Базовый!$AI$6:$AI$65,Базовый!$AO$6:$AO$65) -> 23483259 | D7: =SUMPRODUCT(Оптимистичный!$AI$6:$AI$65,Оптимистичный!$AO$6:$AO$65) -> 2.4774695e+08 | E7: =SUMPRODUCT('Версия 1'!$AI$6:$AI$65,'Версия 1'!$AO$6:$AO$65) -> -3.0781391e+08
A8: NPV после налога за 60 мес., руб. | B8: =SUMPRODUCT(Пессимистичный!$AN$6:$AN$65,Пессимистичный!$AO$6:$AO$65) -> -1.3308264e+08 | C8: =SUMPRODUCT(Базовый!$AN$6:$AN$65,Базовый!$AO$6:$AO$65) -> 15293260 | D8: =SUMPRODUCT(Оптимистичный!$AN$6:$AN$65,Оптимистичный!$AO$6:$AO$65) -> 1.9004086e+08 | E8: =SUMPRODUCT('Версия 1'!$AN$6:$AN$65,'Версия 1'!$AO$6:$AO$65) -> -3.0781391e+08
A9: NPV до налога за 60 мес. с кросс-продажами группы, руб. | B9: =SUMPRODUCT(Пессимистичный!$AI$6:$AI$65+Пессимистичный!$AK$6:$AK$65,Пессимистичный!$AO$6:$AO$65) -> -1.3133325e+08 | C9: =SUMPRODUCT(Базовый!$AI$6:$AI$65+Базовый!$AK$6:$AK$65,Базовый!$AO$6:$AO$65) -> 30113192 | D9: =SUMPRODUCT(Оптимистичный!$AI$6:$AI$65+Оптимистичный!$AK$6:$AK$65,Оптимистичный!$AO$6:$AO$65) -> 2.6402013e+08 | E9: =SUMPRODUCT('Версия 1'!$AI$6:$AI$65+'Версия 1'!$AK$6:$AK$65,'Версия 1'!$AO$6:$AO$65) -> -3.0118398e+08
A10: Пиковая потребность в деньгах, руб. | B10: =MAX(0,-MIN(Пессимистичный!$AJ$6:$AJ$65)) -> 2.2083319e+08 | C10: =MAX(0,-MIN(Базовый!$AJ$6:$AJ$65)) -> 32533857 | D10: =MAX(0,-MIN(Оптимистичный!$AJ$6:$AJ$65)) -> 18255992 | E10: =MAX(0,-MIN('Версия 1'!$AJ$6:$AJ$65)) -> 5.5299689e+08
A11: Месяц операционной безубыточности | B11: =IF(COUNT(Пессимистичный!$AP$6:$AP$65)=0,"не достигается",MIN(Пессимистичный!$AP$6:$AP$65)) -> не достигается | C11: =IF(COUNT(Базовый!$AP$6:$AP$65)=0,"не достигается",MIN(Базовый!$AP$6:$AP$65)) -> 24 | D11: =IF(COUNT(Оптимистичный!$AP$6:$AP$65)=0,"не достигается",MIN(Оптимистичный!$AP$6:$AP$65)) -> 13 | E11: =IF(COUNT('Версия 1'!$AP$6:$AP$65)=0,"не достигается",MIN('Версия 1'!$AP$6:$AP$65)) -> не достигается
A12: Месяц окупаемости (накопленный результат > 0) | B12: =IF(COUNT(Пессимистичный!$AQ$6:$AQ$65)=0,"не достигается",MIN(Пессимистичный!$AQ$6:$AQ$65)) -> не достигается | C12: =IF(COUNT(Базовый!$AQ$6:$AQ$65)=0,"не достигается",MIN(Базовый!$AQ$6:$AQ$65)) -> 43 | D12: =IF(COUNT(Оптимистичный!$AQ$6:$AQ$65)=0,"не достигается",MIN(Оптимистичный!$AQ$6:$AQ$65)) -> 21 | E12: =IF(COUNT('Версия 1'!$AQ$6:$AQ$65)=0,"не достигается",MIN('Версия 1'!$AQ$6:$AQ$65)) -> не достигается
A13: Семей на конец 36 мес. | B13: =Пессимистичный!$O$41 -> 4331.7901 | C13: =Базовый!$O$41 -> 8235.3631 | D13: =Оптимистичный!$O$41 -> 13617.66 | E13: ='Версия 1'!$O$41 -> 8235.3631
A14: Семей на конец 60 мес. | B14: =Пессимистичный!$O$65 -> 5233.807 | C14: =Базовый!$O$65 -> 10653.815 | D14: =Оптимистичный!$O$65 -> 18914.162 | E14: ='Версия 1'!$O$65 -> 10653.815
A15: Координаторов на конец 60 мес. | B15: =Пессимистичный!$R$65 -> 64 | C15: =Базовый!$R$65 -> 109 | D15: =Оптимистичный!$R$65 -> 170 | E15: ='Версия 1'!$R$65 -> 153
A16: Выручка за MVP, руб. | B16: =SUM(Пессимистичный!$W$6:$W$8) -> 292866.89 | C16: =SUM(Базовый!$W$6:$W$8) -> 316276.72 | D16: =SUM(Оптимистичный!$W$6:$W$8) -> 327981.64 | E16: =SUM('Версия 1'!$W$6:$W$8) -> 267116.07
A17: Выручка, год 1, руб. | B17: =Пессимистичный!$B$70 -> 18779931 | C17: =Базовый!$B$70 -> 31496602 | D17: =Оптимистичный!$B$70 -> 41038866 | E17: ='Версия 1'!$B$70 -> 26337800
A18: Выручка, год 2, руб. | B18: =Пессимистичный!$B$71 -> 64939175 | C18: =Базовый!$B$71 -> 1.2489503e+08 | D18: =Оптимистичный!$B$71 -> 1.9322244e+08 | E18: ='Версия 1'!$B$71 -> 1.038415e+08
A19: Выручка, год 3, руб. | B19: =Пессимистичный!$B$72 -> 1.1763414e+08 | C19: =Базовый!$B$72 -> 2.3287691e+08 | D19: =Оптимистичный!$B$72 -> 3.8485219e+08 | E19: ='Версия 1'!$B$72 -> 1.9341124e+08
A20: Выручка, год 4, руб. | B20: =Пессимистичный!$B$73 -> 1.5729593e+08 | C20: =Базовый!$B$73 -> 3.2292213e+08 | D20: =Оптимистичный!$B$73 -> 5.5921336e+08 | E20: ='Версия 1'!$B$73 -> 2.6792167e+08
A21: Выручка, год 5, руб. | B21: =Пессимистичный!$B$74 -> 1.8185011e+08 | C21: =Базовый!$B$74 -> 3.8586421e+08 | D21: =Оптимистичный!$B$74 -> 6.9277866e+08 | E21: ='Версия 1'!$B$74 -> 3.1970916e+08
A22: Операционный результат, год 1, руб. | B22: =Пессимистичный!$C$70 -> -32670499 | C22: =Базовый!$C$70 -> -24976439 | D22: =Оптимистичный!$C$70 -> -18255992 | E22: ='Версия 1'!$C$70 -> -43302772
A23: Операционный результат, год 2, руб. | B23: =Пессимистичный!$C$71 -> -40397407 | C23: =Базовый!$C$71 -> -7556528.9 | D23: =Оптимистичный!$C$71 -> 32437821 | E23: ='Версия 1'!$C$71 -> -79712783
A24: Операционный результат, год 3, руб. | B24: =Пессимистичный!$C$72 -> -50659679 | C24: =Базовый!$C$72 -> 12184223 | D24: =Оптимистичный!$C$72 -> 1.0003577e+08 | E24: ='Версия 1'!$C$72 -> -1.2193943e+08
A25: Операционный результат, год 4, руб. | B25: =Пессимистичный!$C$73 -> -48137365 | C25: =Базовый!$C$73 -> 40463904 | D25: =Оптимистичный!$C$73 -> 1.7557154e+08 | E25: ='Версия 1'!$C$73 -> -1.4498746e+08
A26: Операционный результат, год 5, руб. | B26: =Пессимистичный!$C$74 -> -48968239 | C26: =Базовый!$C$74 -> 60999135 | D26: =Оптимистичный!$C$74 -> 2.3434135e+08 | E26: ='Версия 1'!$C$74 -> -1.6305444e+08
A27: Кросс-продажи за 60 мес. (эффект группы), руб. | B27: =Пессимистичный!$H$75 -> 3257280 | C27: =Базовый!$H$75 -> 12495581 | D27: =Оптимистичный!$H$75 -> 31135755 | E27: ='Версия 1'!$H$75 -> 12495581
A28: Льготы ветеранам за 60 мес. (недополученная выручка), руб. | B28: =SUM(Пессимистичный!$AL$6:$AL$65) -> 23946264 | C28: =SUM(Базовый!$AL$6:$AL$65) -> 46773207 | D28: =SUM(Оптимистичный!$AL$6:$AL$65) -> 77956259 | E28: =SUM('Версия 1'!$AL$6:$AL$65) -> 38890082

Sheet Юнит-экономика
A1: Юнит-экономика одной семьи B2C
A2: Устоявшаяся семья, первый год, без индексации цен и зарплат
A4: Показатель | B4: Пессимистичный | C4: Базовый | D4: Оптимистичный | E4: Версия 1 без триажа
A5: Средний чек по прейскуранту с НДС, руб./мес. | B5: =Допущения!$C$70 -> 2865 | C5: =Допущения!$D$70 -> 3115 | D5: =Допущения!$E$70 -> 3240 | E5: =Допущения!$F$70 -> 2590
A6: Средняя скидка по льготам ветеранам | B6: ='Льготы ветеранам'!$D$9 -> 0.048 | C6: ='Льготы ветеранам'!$D$9 -> 0.048 | D6: ='Льготы ветеранам'!$D$9 -> 0.048 | E6: ='Льготы ветеранам'!$D$9 -> 0.048
A7: Средний чек с НДС с учетом льгот, руб./мес. | B7: =B5*(1-B6) -> 2727.48 | C7: =C5*(1-C6) -> 2965.48 | D7: =D5*(1-D6) -> 3084.48 | E7: =E5*(1-E6) -> 2465.68
A8: Средний чек без НДС, руб./мес. | B8: =B7/(1+Допущения!$C$6) -> 2235.6393 | C8: =C7/(1+Допущения!$D$6) -> 2430.7213 | D8: =D7/(1+Допущения!$E$6) -> 2528.2623 | E8: =E7/(1+Допущения!$F$6) -> 2021.0492
A9: Комиссия партнеров без НДС, руб./мес. | B9: =Допущения!$C$26*Допущения!$C$27/(1+Допущения!$C$6) -> 122.95082 | C9: =Допущения!$D$26*Допущения!$D$27/(1+Допущения!$D$6) -> 122.95082 | D9: =Допущения!$E$26*Допущения!$E$27/(1+Допущения!$E$6) -> 122.95082 | E9: =Допущения!$F$26*Допущения!$F$27/(1+Допущения!$F$6) -> 122.95082
A10: Семей «Базовый» на координатора | B10: =Допущения!$C$68 -> 98.542762 | C10: =Допущения!$D$68 -> 128.10559 | D10: =Допущения!$E$68 -> 150.71246 | E10: =Допущения!$F$68 -> 83.333333
A11: Семей «Расширенный» на координатора | B11: =Допущения!$C$69 -> 39.56455 | C11: =Допущения!$D$69 -> 51.433915 | D11: =Допущения!$E$69 -> 60.510488 | E11: =Допущения!$F$69 -> 46.296296
A12: Доля ставки координатора на семью | B12: =(1-Допущения!$C$25)/B10+Допущения!$C$25/B11 -> 0.01241697 | C12: =(1-Допущения!$D$25)/C10+Допущения!$D$25/C11 -> 0.010715152 | D12: =(1-Допущения!$E$25)/D10+Допущения!$E$25/D11 -> 0.0096024242 | E12: =(1-Допущения!$F$25)/E10+Допущения!$F$25/E11 -> 0.01488
A13: Полная стоимость координатора с супервизией, руб./мес. | B13: =Допущения!$C$47*Допущения!$C$9*(1+Допущения!$C$14)+Допущения!$C$49*Допущения!$C$9*(1+Допущения!$C$14)/Допущения!$C$48+Допущения!$C$52*(1+1/Допущения!$C$48)+Допущения!$C$51*Допущения!$C$50/12 -> 132379.5 | C13: =Допущения!$D$47*Допущения!$D$9*(1+Допущения!$D$14)+Допущения!$D$49*Допущения!$D$9*(1+Допущения!$D$14)/Допущения!$D$48+Допущения!$D$52*(1+1/Допущения!$D$48)+Допущения!$D$51*Допущения!$D$50/12 -> 118057.5 | D13: =Допущения!$E$47*Допущения!$E$9*(1+Допущения!$E$14)+Допущения!$E$49*Допущения!$E$9*(1+Допущения!$E$14)/Допущения!$E$48+Допущения!$E$52*(1+1/Допущения!$E$48)+Допущения!$E$51*Допущения!$E$50/12 -> 110896.5 | E13: =Допущения!$F$47*Допущения!$F$9*(1+Допущения!$F$14)+Допущения!$F$49*Допущения!$F$9*(1+Допущения!$F$14)/Допущения!$F$48+Допущения!$F$52*(1+1/Допущения!$F$48)+Допущения!$F$51*Допущения!$F$50/12 -> 145263.1
A14: Координатор, супервизия, накладные на семью, руб./мес. | B14: =B13*B12 -> 1643.7522 | C14: =C13*C12 -> 1265.004 | D14: =D13*D12 -> 1064.8752 | E14: =E13*E12 -> 2161.5149
A15: Прочие переменные на семью, руб./мес. | B15: =Допущения!$C$53+Допущения!$C$54+B7*Допущения!$C$13+Допущения!$C$56/1000 -> 422.09464 | C15: =Допущения!$D$53+Допущения!$D$54+C7*Допущения!$D$13+Допущения!$D$56/1000 -> 426.37864 | D15: =Допущения!$E$53+Допущения!$E$54+D7*Допущения!$E$13+Допущения!$E$56/1000 -> 428.52064 | E15: =Допущения!$F$53+Допущения!$F$54+E7*Допущения!$F$13+Допущения!$F$56/1000 -> 497.38224
A16: Маржинальный доход на семью, руб./мес. | B16: =B8+B9-B14-B15 -> 292.74328 | C16: =C8+C9-C14-C15 -> 862.28949 | D16: =D8+D9-D14-D15 -> 1157.8172 | E16: =E8+E9-E14-E15 -> -514.89717
A17: Маржинальность | B17: =B16/(B8+B9) -> 0.12411791 | C17: =C16/(C8+C9) -> 0.33766648 | D17: =D16/(D8+D9) -> 0.43671225 | E17: =E16/(E8+E9) -> -0.24015726
A18: Средний срок жизни, мес. | B18: =1+(1-Допущения!$C$43)/Допущения!$C$44 -> 9.125 | C18: =1+(1-Допущения!$D$43)/Допущения!$D$44 -> 13.5 | D18: =1+(1-Допущения!$E$43)/Допущения!$E$44 -> 19.222222 | E18: =1+(1-Допущения!$F$43)/Допущения!$F$44 -> 13.5
A19: LTV, руб. | B19: =B16*B18 -> 2671.2825 | C19: =C16*C18 -> 11640.908 | D19: =D16*D18 -> 22255.82 | E19: =E16*E18 -> -6951.1118
A20: CAC при полном бюджете (смесь каналов), руб. | B20: =Допущения!$C$34/(Допущения!$C$30+(Допущения!$C$34-Допущения!$C$30*Допущения!$C$29)/Допущения!$C$31) -> 5067.5676 | C20: =Допущения!$D$34/(Допущения!$D$30+(Допущения!$D$34-Допущения!$D$30*Допущения!$D$29)/Допущения!$D$31) -> 3896.1039 | D20: =Допущения!$E$34/(Допущения!$E$30+(Допущения!$E$34-Допущения!$E$30*Допущения!$E$29)/Допущения!$E$31) -> 3040.5405 | E20: =Допущения!$F$34/(Допущения!$F$30+(Допущения!$F$34-Допущения!$F$30*Допущения!$F$29)/Допущения!$F$31) -> 3896.1039
A21: LTV/CAC | B21: =B19/B20 -> 0.52713307 | C21: =C19/C20 -> 2.9878331 | D21: =D19/D20 -> 7.319692 | E21: =E19/E20 -> -1.7841187
A22: Окупаемость CAC, мес. | B22: =IF(B16>0,B20/B16,"не окупается") -> 17.310619 | C22: =IF(C16>0,C20/C16,"не окупается") -> 4.5183247 | D22: =IF(D16>0,D20/D16,"не окупается") -> 2.6260972 | E22: =IF(E16>0,E20/E16,"не окупается") -> не окупается

Sheet Рынок
A1: Оценка размера рынка (порядок величины)
A2: Базовый сценарий
A4: Показатель | B4: Значение | C4: Метка | D4: Источник или обоснование
A5: Люди 65+ в РФ | B5: 25800000 | C5: факт | D5: Росстат через Демоскоп, 01.01.2025
A6: Доля с хроническими заболеваниями | B6: 0.54 | C6: факт | D6: Минздрав (Мурашко), 07.2026, для старше трудоспособного возраста, используем как приближение
A7: Доля живущих отдельно от взрослых детей | B7: 0.6 | C7: допущение | D7: Проверяется анкетой (вопрос 3)
A8: Доля, где ребенок работает и сам координирует медпомощь | B8: 0.7 | C8: допущение | D8: Проверяется анкетой (вопросы 4-5)
A9: Доля в городах 250 тыс.+ с доходом, позволяющим платить 2,5 тыс. в месяц | B9: 0.35 | C9: допущение | D9: Оценка команды, проверяется тестом цены
A10: TAM, семей | B10: =B5*B6*B7*B8 -> 5851440 | C10: расчет | D10: Произведение долей
A11: TAM, руб. в год | B11: =B10*Допущения!$D$71*12 -> 2.0822794e+11 | C11: расчет | D11: TAM x средний чек с НДС x 12
A12: SAM, семей | B12: =B10*B9 -> 2048004 | C12: расчет | D12: TAM x доля платежеспособных в городах 250 тыс.+
A13: SAM, руб. в год | B13: =B12*Допущения!$D$71*12 -> 7.2879779e+10 | C13: расчет | D13: SAM x средний чек с НДС x 12
A14: SOM на 60 мес., семей (базовый сценарий) | B14: =Сводка!$C$14 -> 10653.815 | C14: расчет | D14: Лист «Сводка»
A15: Доля SOM от SAM | B15: =B14/B12 -> 0.0052020479 | C15: расчет | D15: SOM / SAM

Sheet Пессимистичный
A1: Помесячный расчет: сценарий «Пессимистичный»
A2: Суммы в рублях без НДС. Месяцы 1-3: MVP. Налог на прибыль начисляется в последнем месяце года.
A5: Месяц | B5: Год | C5: Фаза | D5: Индекс зарплат | E5: Индекс цен | F5: Средний чек B2C с НДС, руб. | G5: Маркетинг, руб. | H5: Новые семьи: внутренние каналы | I5: Новые семьи: внешние каналы | J5: Новые семьи: канал фонда «Защитники Отечества» | K5: Новые семьи B2C | L5: Семьи B2C | M5: Приток B2B2C | N5: Семьи B2B2C | O5: Всего семей | P5: Семьи «Расши-ренный» | Q5: Семьи «Базовый» и B2B2C | R5: Координа-торы, чел. | S5: Супер-визоры, чел. | T5: Выручка: подписка B2C, руб. | U5: Выручка: B2B2C, руб. | V5: Выручка: комиссия партнеров, руб. | W5: Выручка всего, руб. | X5: Партнерский канал фонда, руб. | Y5: ФОТ координаторов и супервизоров, руб. | Z5: Обучение новых координаторов, руб. | AA5: Переменные расходы на семьи, руб. | AB5: Рабочие места, руб. | AC5: Постоянная команда, руб. | AD5: Накладные, руб. | AE5: Размещение и юрлицо, руб. | AF5: Инвестиции, руб. | AG5: Бюджет MVP, руб. | AH5: Расходы всего, руб. | AI5: Операционный результат, руб. | AJ5: Накопленный результат, руб. | AK5: Кросс-продажи (эффект группы), руб. | AL5: Льготы ветеранам: недополученная выручка, руб. | AM5: Налог на прибыль, руб. | AN5: Денежный поток после налога, руб. | AO5: Коэффициент дисконтирования | AP5: Признак безубыточности (месяц) | AQ5: Признак окупаемости (месяц)
A6: 1 | B6: =INT((A6-1)/12)+1 -> 1 | C6: MVP | D6: =(1+Допущения!$C$11)^(B6-1) -> 1 | E6: =(1+Допущения!$C$12)^(B6-1) -> 1 | F6: =Допущения!$C$71*E6 -> 2727.48 | G6: 0 | H6: 0 | I6: 0 | J6: 0 | K6: =Допущения!$B$78-0 -> 0 | L6: =Допущения!$B$78 -> 0 | M6: 0 | N6: 0 | O6: =L6+N6 -> 0 | P6: =L6*Допущения!$C$25 -> 0 | Q6: =L6*(1-Допущения!$C$25)+N6 -> 0 | R6: =IF(A6>1,Допущения!$C$18,0) -> 0 | S6: 0 | T6: =L6*Допущения!$C$60*F6/(1+Допущения!$C$6) -> 0 | U6: =N6*Допущения!$C$28*E6/(1+Допущения!$C$6) -> 0 | V6: =O6*Допущения!$C$26*Допущения!$C$27/(1+Допущения!$C$6) -> 0 | W6: =T6+U6+V6 -> 0 | X6: 0 | Y6: 0 | Z6: 0 | AA6: 0 | AB6: 0 | AC6: 0 | AD6: 0 | AE6: 0 | AF6: 0 | AG6: ='Бюджет MVP'!$G$33/Допущения!$C$19 -> 1624654.7 | AH6: =G6+SUM(X6:AG6) -> 1624654.7 | AI6: =W6-AH6 -> -1624654.7 | AJ6: =AI6 -> -1624654.7 | AK6: 0 | AL6: =T6*Допущения!$C$72 -> 0 | AM6: =IF(MOD(A6,12)=0,INDEX($F$70:$F$74,B6),0) -> 0 | AN6: =AI6-AM6 -> -1624654.7 | AO6: =1/(1+Допущения!$C$74)^A6 -> 0.98356564 | AP6: =IF(AND(A6>Допущения!$C$19,MIN(AI6:AI$65)>0),A6,"") | AQ6: =IF(MIN(AJ6:AJ$65)>0,A6,"")
A7: 2 | B7: =INT((A7-1)/12)+1 -> 1 | C7: MVP | D7: =(1+Допущения!$C$11)^(B7-1) -> 1 | E7: =(1+Допущения!$C$12)^(B7-1) -> 1 | F7: =Допущения!$C$71*E7 -> 2727.48 | G7: 0 | H7: 0 | I7: 0 | J7: 0 | K7: =Допущения!$B$79-Допущения!$B$78 -> 50 | L7: =Допущения!$B$79 -> 50 | M7: 0 | N7: 0 | O7: =L7+N7 -> 50 | P7: =L7*Допущения!$C$25 -> 7.5 | Q7: =L7*(1-Допущения!$C$25)+N7 -> 42.5 | R7: =IF(A7>1,Допущения!$C$18,0) -> 3 | S7: 0 | T7: =L7*Допущения!$C$60*F7/(1+Допущения!$C$6) -> 67069.18 | U7: =N7*Допущения!$C$28*E7/(1+Допущения!$C$6) -> 0 | V7: =O7*Допущения!$C$26*Допущения!$C$27/(1+Допущения!$C$6) -> 6147.541 | W7: =T7+U7+V7 -> 73216.721 | X7: 0 | Y7: 0 | Z7: 0 | AA7: 0 | AB7: 0 | AC7: 0 | AD7: 0 | AE7: 0 | AF7: 0 | AG7: ='Бюджет MVP'!$G$33/Допущения!$C$19 -> 1624654.7 | AH7: =G7+SUM(X7:AG7) -> 1624654.7 | AI7: =W7-AH7 -> -1551437.9 | AJ7: =AJ6+AI7 -> -3176092.6 | AK7: 0 | AL7: =T7*Допущения!$C$72 -> 3381.6393 | AM7: =IF(MOD(A7,12)=0,INDEX($F$70:$F$74,B7),0) -> 0 | AN7: =AI7-AM7 -> -1551437.9 | AO7: =1/(1+Допущения!$C$74)^A7 -> 0.96740136 | AP7: =IF(AND(A7>Допущения!$C$19,MIN(AI7:AI$65)>0),A7,"") | AQ7: =IF(MIN(AJ7:AJ$65)>0,A7,"")
A8: 3 | B8: =INT((A8-1)/12)+1 -> 1 | C8: MVP | D8: =(1+Допущения!$C$11)^(B8-1) -> 1 | E8: =(1+Допущения!$C$12)^(B8-1) -> 1 | F8: =Допущения!$C$71*E8 -> 2727.48 | G8: 0 | H8: 0 | I8: 0 | J8: 0 | K8: =Допущения!$B$80-Допущения!$B$79 -> 100 | L8: =Допущения!$B$80 -> 150 | M8: 0 | N8: 0 | O8: =L8+N8 -> 150 | P8: =L8*Допущения!$C$25 -> 22.5 | Q8: =L8*(1-Допущения!$C$25)+N8 -> 127.5 | R8: =IF(A8>1,Допущения!$C$18,0) -> 3 | S8: 0 | T8: =L8*Допущения!$C$60*F8/(1+Допущения!$C$6) -> 201207.54 | U8: =N8*Допущения!$C$28*E8/(1+Допущения!$C$6) -> 0 | V8: =O8*Допущения!$C$26*Допущения!$C$27/(1+Допущения!$C$6) -> 18442.623 | W8: =T8+U8+V8 -> 219650.16 | X8: 0 | Y8: 0 | Z8: 0 | AA8: 0 | AB8: 0 | AC8: 0 | AD8: 0 | AE8: 0 | AF8: 0 | AG8: ='Бюджет MVP'!$G$33/Допущения!$C$19 -> 1624654.7 | AH8: =G8+SUM(X8:AG8) -> 1624654.7 | AI8: =W8-AH8 -> -1405004.5 | AJ8: =AJ7+AI8 -> -4581097.1 | AK8: 0 | AL8: =T8*Допущения!$C$72 -> 10144.918 | AM8: =IF(MOD(A8,12)=0,INDEX($F$70:$F$74,B8),0) -> 0 | AN8: =AI8-AM8 -> -1405004.5 | AO8: =1/(1+Допущения!$C$74)^A8 -> 0.95150274 | AP8: =IF(AND(A8>Допущения!$C$19,MIN(AI8:AI$65)>0),A8,"") | AQ8: =IF(MIN(AJ8:AJ$65)>0,A8,"")
A9: 4 | B9: =INT((A9-1)/12)+1 -> 1 | C9: Масштабирование | D9: =(1+Допущения!$C$11)^(B9-1) -> 1 | E9: =(1+Допущения!$C$12)^(B9-1) -> 1 | F9: =Допущения!$C$71*E9 -> 2727.48 | G9: =Допущения!$C$32 -> 400000 | H9: =MIN(Допущения!$C$30,G9/Допущения!$C$29) -> 200 | I9: =MAX(0,G9-H9*Допущения!$C$29)/Допущения!$C$31 -> 13.333333 | J9: =IF(A9>=Допущения!$C$35,Допущения!$C$36,0) -> 0 | K9: =H9+I9+J9 -> 213.33333 | L9: =(L8-K8)*(1-Допущения!$C$44)+K8*(1-Допущения!$C$43)+K9 -> 324.33333 | M9: =IF(A9>=Допущения!$C$38,Допущения!$C$73/Допущения!$C$42*MIN(Допущения!$C$42,A9-Допущения!$C$38+1),0) -> 0 | N9: =N8*(1-Допущения!$C$45)+M9 -> 0 | O9: =L9+N9 -> 324.33333 | P9: =L9*Допущения!$C$25 -> 48.65 | Q9: =L9*(1-Допущения!$C$25)+N9 -> 275.68333 | R9: =MAX(Допущения!$C$18,ROUNDUP(Q9/Допущения!$C$68+P9/Допущения!$C$69,0)) -> 5 | S9: =ROUNDUP(R9/Допущения!$C$48,0) -> 1 | T9: =L9*F9/(1+Допущения!$C$6) -> 725092.36 | U9: =N9*Допущения!$C$28*E9/(1+Допущения!$C$6) -> 0 | V9: =O9*Допущения!$C$26*Допущения!$C$27/(1+Допущения!$C$6) -> 39877.049 | W9: =T9+U9+V9 -> 764969.41 | X9: =J9*Допущения!$C$37 -> 0 | Y9: =(R9*Допущения!$C$47+S9*Допущения!$C$49)*D9*Допущения!$C$9 -> 664020 | Z9: =(MAX(0,R9-R8)+R9*Допущения!$C$50/12)*Допущения!$C$51*D9 -> 148750 | AA9: =O9*(Допущения!$C$53+Допущения!$C$54)+(L9*F9+N9*Допущения!$C$28*E9)*Допущения!$C$13 -> 134304.69 | AB9: =(R9+S9)*Допущения!$C$52 -> 16200 | AC9: =SUMPRODUCT(Допущения!$B$84:$B$91,Допущения!$C$84:$C$91,--(Допущения!$D$84:$D$91<=A9))*D9*Допущения!$C$9 -> 1132740 | AD9: =(AC9+Y9)*Допущения!$C$14 -> 179676 | AE9: =Допущения!$C$55+Допущения!$C$56*O9/1000+Допущения!$C$57 -> 142594.67 | AF9: =SUMIF(Допущения!$B$95:$B$103,A9,Допущения!$C$95:$C$103) -> 1000000 | AG9: 0 | AH9: =G9+SUM(X9:AG9) -> 3818285.4 | AI9: =W9-AH9 -> -3053316 | AJ9: =AJ8+AI9 -> -7634413.1 | AK9: =O9*Допущения!$C$58*Допущения!$C$59 -> 5351.5 | AL9: =T9*Допущения!$C$72 -> 36559.279 | AM9: =IF(MOD(A9,12)=0,INDEX($F$70:$F$74,B9),0) -> 0 | AN9: =AI9-AM9 -> -3053316 | AO9: =1/(1+Допущения!$C$74)^A9 -> 0.9358654 | AP9: =IF(AND(A9>Допущения!$C$19,MIN(AI9:AI$65)>0),A9,"") | AQ9: =IF(MIN(AJ9:AJ$65)>0,A9,"")
A10: 5 | B10: =INT((A10-1)/12)+1 -> 1 | C10: Масштабирование | D10: =(1+Допущения!$C$11)^(B10-1) -> 1 | E10: =(1+Допущения!$C$12)^(B10-1) -> 1 | F10: =Допущения!$C$71*E10 -> 2727.48 | G10: =MIN(G9*(1+Допущения!$C$33),Допущения!$C$34) -> 432000 | H10: =MIN(Допущения!$C$30,G10/Допущения!$C$29) -> 200 | I10: =MAX(0,G10-H10*Допущения!$C$29)/Допущения!$C$31 -> 17.6 | J10: =IF(A10>=Допущения!$C$35,Допущения!$C$36,0) -> 0 | K10: =H10+I10+J10 -> 217.6 | L10: =(L9-K9)*(1-Допущения!$C$44)+K9*(1-Допущения!$C$43)+K10 -> 458.38667 | M10: =IF(A10>=Допущения!$C$38,Допущения!$C$73/Допущения!$C$42*MIN(Допущения!$C$42,A10-Допущения!$C$38+1),0) -> 0 | N10: =N9*(1-Допущения!$C$45)+M10 -> 0 | O10: =L10+N10 -> 458.38667 | P10: =L10*Допущения!$C$25 -> 68.758 | Q10: =L10*(1-Допущения!$C$25)+N10 -> 389.62867 | R10: =MAX(Допущения!$C$18,ROUNDUP(Q10/Допущения!$C$68+P10/Допущения!$C$69,0)) -> 6 | S10: =ROUNDUP(R10/Допущения!$C$48,0) -> 1 | T10: =L10*F10/(1+Допущения!$C$6) -> 1024787.3 | U10: =N10*Допущения!$C$28*E10/(1+Допущения!$C$6) -> 0 | V10: =O10*Допущения!$C$26*Допущения!$C$27/(1+Допущения!$C$6) -> 56359.016 | W10: =T10+U10+V10 -> 1081146.3 | X10: =J10*Допущения!$C$37 -> 0 | Y10: =(R10*Допущения!$C$47+S10*Допущения!$C$49)*D10*Допущения!$C$9 -> 768180 | Z10: =(MAX(0,R10-R9)+R10*Допущения!$C$50/12)*Допущения!$C$51*D10 -> 80500 | AA10: =O10*(Допущения!$C$53+Допущения!$C$54)+(L10*F10+N10*Допущения!$C$28*E10)*Допущения!$C$13 -> 189815.46 | AB10: =(R10+S10)*Допущения!$C$52 -> 18900 | AC10: =SUMPRODUCT(Допущения!$B$84:$B$91,Допущения!$C$84:$C$91,--(Допущения!$D$84:$D$91<=A10))*D10*Допущения!$C$9 -> 1132740 | AD10: =(AC10+Y10)*Допущения!$C$14 -> 190092 | AE10: =Допущения!$C$55+Допущения!$C$56*O10/1000+Допущения!$C$57 -> 143667.09 | AF10: =SUMIF(Допущения!$B$95:$B$103,A10,Допущения!$C$95:$C$103) -> 1000000 | AG10: 0 | AH10: =G10+SUM(X10:AG10) -> 3955894.6 | AI10: =W10-AH10 -> -2874748.3 | AJ10: =AJ9+AI10 -> -10509161 | AK10: =O10*Допущения!$C$58*Допущения!$C$59 -> 7563.38 | AL10: =T10*Допущения!$C$72 -> 51669.946 | AM10: =IF(MOD(A10,12)=0,INDEX($F$70:$F$74,B10),0) -> 0 | AN10: =AI10-AM10 -> -2874748.3 | AO10: =1/(1+Допущения!$C$74)^A10 -> 0.92048505 | AP10: =IF(AND(A10>Допущения!$C$19,MIN(AI10:AI$65)>0),A10,"") | AQ10: =IF(MIN(AJ10:AJ$65)>0,A10,"")
A11: 6 | B11: =INT((A11-1)/12)+1 -> 1 | C11: Масштабирование | D11: =(1+Допущения!$C$11)^(B11-1) -> 1 | E11: =(1+Допущения!$C$12)^(B11-1) -> 1 | F11: =Допущения!$C$71*E11 -> 2727.48 | G11: =MIN(G10*(1+Допущения!$C$33),Допущения!$C$34) -> 466560 | H11: =MIN(Допущения!$C$30,G11/Допущения!$C$29) -> 200 | I11: =MAX(0,G11-H11*Допущения!$C$29)/Допущения!$C$31 -> 22.208 | J11: =IF(A11>=Допущения!$C$35,Допущения!$C$36,0) -> 20 | K11: =H11+I11+J11 -> 242.208 | L11: =(L10-K10)*(1-Допущения!$C$44)+K10*(1-Допущения!$C$43)+K11 -> 605.17173 | M11: =IF(A11>=Допущения!$C$38,Допущения!$C$73/Допущения!$C$42*MIN(Допущения!$C$42,A11-Допущения!$C$38+1),0) -> 0 | N11: =N10*(1-Допущения!$C$45)+M11 -> 0 | O11: =L11+N11 -> 605.17173 | P11: =L11*Допущения!$C$25 -> 90.77576 | Q11: =L11*(1-Допущения!$C$25)+N11 -> 514.39597 | R11: =MAX(Допущения!$C$18,ROUNDUP(Q11/Допущения!$C$68+P11/Допущения!$C$69,0)) -> 8 | S11: =ROUNDUP(R11/Допущения!$C$48,0) -> 1 | T11: =L11*F11/(1+Допущения!$C$6) -> 1352945.7 | U11: =N11*Допущения!$C$28*E11/(1+Допущения!$C$6) -> 0 | V11: =O11*Допущения!$C$26*Допущения!$C$27/(1+Допущения!$C$6) -> 74406.361 | W11: =T11+U11+V11 -> 1427352.1 | X11: =J11*Допущения!$C$37 -> 10000 | Y11: =(R11*Допущения!$C$47+S11*Допущения!$C$49)*D11*Допущения!$C$9 -> 976500 | Z11: =(MAX(0,R11-R10)+R11*Допущения!$C$50/12)*Допущения!$C$51*D11 -> 154000 | AA11: =O11*(Допущения!$C$53+Допущения!$C$54)+(L11*F11+N11*Допущения!$C$28*E11)*Допущения!$C$13 -> 250598.37 | AB11: =(R11+S11)*Допущения!$C$52 -> 24300 | AC11: =SUMPRODUCT(Допущения!$B$84:$B$91,Допущения!$C$84:$C$91,--(Допущения!$D$84:$D$91<=A11))*D11*Допущения!$C$9 -> 1627500 | AD11: =(AC11+Y11)*Допущения!$C$14 -> 260400 | AE11: =Допущения!$C$55+Допущения!$C$56*O11/1000+Допущения!$C$57 -> 144841.37 | AF11: =SUMIF(Допущения!$B$95:$B$103,A11,Допущения!$C$95:$C$103) -> 1000000 | AG11: 0 | AH11: =G11+SUM(X11:AG11) -> 4914699.7 | AI11: =W11-AH11 -> -3487347.6 | AJ11: =AJ10+AI11 -> -13996509 | AK11: =O11*Допущения!$C$58*Допущения!$C$59 -> 9985.3336 | AL11: =T11*Допущения!$C$72 -> 68215.751 | AM11: =IF(MOD(A11,12)=0,INDEX($F$70:$F$74,B11),0) -> 0 | AN11: =AI11-AM11 -> -3487347.6 | AO11: =1/(1+Допущения!$C$74)^A11 -> 0.90535746 | AP11: =IF(AND(A11>Допущения!$C$19,MIN(AI11:AI$65)>0),A11,"") | AQ11: =IF(MIN(AJ11:AJ$65)>0,A11,"")
A12: 7 | B12: =INT((A12-1)/12)+1 -> 1 | C12: Масштабирование | D12: =(1+Допущения!$C$11)^(B12-1) -> 1 | E12: =(1+Допущения!$C$12)^(B12-1) -> 1 | F12: =Допущения!$C$71*E12 -> 2727.48 | G12: =MIN(G11*(1+Допущения!$C$33),Допущения!$C$34) -> 503884.8 | H12: =MIN(Допущения!$C$30,G12/Допущения!$C$29) -> 200 | I12: =MAX(0,G12-H12*Допущения!$C$29)/Допущения!$C$31 -> 27.18464 | J12: =IF(A12>=Допущения!$C$35,Допущения!$C$36,0) -> 20 | K12: =H12+I12+J12 -> 247.18464 | L12: =(L11-K11)*(1-Допущения!$C$44)+K11*(1-Допущения!$C$43)+K12 -> 738.54647 | M12: =IF(A12>=Допущения!$C$38,Допущения!$C$73/Допущения!$C$42*MIN(Допущения!$C$42,A12-Допущения!$C$38+1),0) -> 6.6666667 | N12: =N11*(1-Допущения!$C$45)+M12 -> 6.6666667 | O12: =L12+N12 -> 745.21314 | P12: =L12*Допущения!$C$25 -> 110.78197 | Q12: =L12*(1-Допущения!$C$25)+N12 -> 634.43117 | R12: =MAX(Допущения!$C$18,ROUNDUP(Q12/Допущения!$C$68+P12/Допущения!$C$69,0)) -> 10 | S12: =ROUNDUP(R12/Допущения!$C$48,0) -> 1 | T12: =L12*F12/(1+Допущения!$C$6) -> 1651123.6 | U12: =N12*Допущения!$C$28*E12/(1+Допущения!$C$6) -> 10874.317 | V12: =O12*Допущения!$C$26*Допущения!$C$27/(1+Допущения!$C$6) -> 91624.567 | W12: =T12+U12+V12 -> 1753622.4 | X12: =J12*Допущения!$C$37 -> 10000 | Y12: =(R12*Допущения!$C$47+S12*Допущения!$C$49)*D12*Допущения!$C$9 -> 1184820 | Z12: =(MAX(0,R12-R11)+R12*Допущения!$C$50/12)*Допущения!$C$51*D12 -> 157500 | AA12: =O12*(Допущения!$C$53+Допущения!$C$54)+(L12*F12+N12*Допущения!$C$28*E12)*Допущения!$C$13 -> 308500.27 | AB12: =(R12+S12)*Допущения!$C$52 -> 29700 | AC12: =SUMPRODUCT(Допущения!$B$84:$B$91,Допущения!$C$84:$C$91,--(Допущения!$D$84:$D$91<=A12))*D12*Допущения!$C$9 -> 1627500 | AD12: =(AC12+Y12)*Допущения!$C$14 -> 281232 | AE12: =Допущения!$C$55+Допущения!$C$56*O12/1000+Допущения!$C$57 -> 145961.71 | AF12: =SUMIF(Допущения!$B$95:$B$103,A12,Допущения!$C$95:$C$103) -> 500000 | AG12: 0 | AH12: =G12+SUM(X12:AG12) -> 4749098.8 | AI12: =W12-AH12 -> -2995476.3 | AJ12: =AJ11+AI12 -> -16991985 | AK12: =O12*Допущения!$C$58*Допущения!$C$59 -> 12296.017 | AL12: =T12*Допущения!$C$72 -> 83249.927 | AM12: =IF(MOD(A12,12)=0,INDEX($F$70:$F$74,B12),0) -> 0 | AN12: =AI12-AM12 -> -2995476.3 | AO12: =1/(1+Допущения!$C$74)^A12 -> 0.89047849 | AP12: =IF(AND(A12>Допущения!$C$19,MIN(AI12:AI$65)>0),A12,"") | AQ12: =IF(MIN(AJ12:AJ$65)>0,A12,"")
A13: 8 | B13: =INT((A13-1)/12)+1 -> 1 | C13: Масштабирование | D13: =(1+Допущения!$C$11)^(B13-1) -> 1 | E13: =(1+Допущения!$C$12)^(B13-1) -> 1 | F13: =Допущения!$C$71*E13 -> 2727.48 | G13: =MIN(G12*(1+Допущения!$C$33),Допущения!$C$34) -> 544195.58 | H13: =MIN(Допущения!$C$30,G13/Допущения!$C$29) -> 200 | I13: =MAX(0,G13-H13*Допущения!$C$29)/Допущения!$C$31 -> 32.559411 | J13: =IF(A13>=Допущения!$C$35,Допущения!$C$36,0) -> 20 | K13: =H13+I13+J13 -> 252.55941 | L13: =(L12-K12)*(1-Допущения!$C$44)+K12*(1-Допущения!$C$43)+K13 -> 865.28232 | M13: =IF(A13>=Допущения!$C$38,Допущения!$C$73/Допущения!$C$42*MIN(Допущения!$C$42,A13-Допущения!$C$38+1),0) -> 13.333333 | N13: =N12*(1-Допущения!$C$45)+M13 -> 19.866667 | O13: =L13+N13 -> 885.14898 | P13: =L13*Допущения!$C$25 -> 129.79235 | Q13: =L13*(1-Допущения!$C$25)+N13 -> 755.35663 | R13: =MAX(Допущения!$C$18,ROUNDUP(Q13/Допущения!$C$68+P13/Допущения!$C$69,0)) -> 11 | S13: =ROUNDUP(R13/Допущения!$C$48,0) -> 1 | T13: =L13*F13/(1+Допущения!$C$6) -> 1934459.2 | U13: =N13*Допущения!$C$28*E13/(1+Допущения!$C$6) -> 32405.464 | V13: =O13*Допущения!$C$26*Допущения!$C$27/(1+Допущения!$C$6) -> 108829.79 | W13: =T13+U13+V13 -> 2075694.4 | X13: =J13*Допущения!$C$37 -> 10000 | Y13: =(R13*Допущения!$C$47+S13*Допущения!$C$49)*D13*Допущения!$C$9 -> 1288980 | Z13: =(MAX(0,R13-R12)+R13*Допущения!$C$50/12)*Допущения!$C$51*D13 -> 89250 | AA13: =O13*(Допущения!$C$53+Допущения!$C$54)+(L13*F13+N13*Допущения!$C$28*E13)*Допущения!$C$13 -> 366271.73 | AB13: =(R13+S13)*Допущения!$C$52 -> 32400 | AC13: =SUMPRODUCT(Допущения!$B$84:$B$91,Допущения!$C$84:$C$91,--(Допущения!$D$84:$D$91<=A13))*D13*Допущения!$C$9 -> 1627500 | AD13: =(AC13+Y13)*Допущения!$C$14 -> 291648 | AE13: =Допущения!$C$55+Допущения!$C$56*O13/1000+Допущения!$C$57 -> 147081.19 | AF13: =SUMIF(Допущения!$B$95:$B$103,A13,Допущения!$C$95:$C$103) -> 500000 | AG13: 0 | AH13: =G13+SUM(X13:AG13) -> 4897326.5 | AI13: =W13-AH13 -> -2821632.1 | AJ13: =AJ12+AI13 -> -19813617 | AK13: =O13*Допущения!$C$58*Допущения!$C$59 -> 14604.958 | AL13: =T13*Допущения!$C$72 -> 97535.757 | AM13: =IF(MOD(A13,12)=0,INDEX($F$70:$F$74,B13),0) -> 0 | AN13: =AI13-AM13 -> -2821632.1 | AO13: =1/(1+Допущения!$C$74)^A13 -> 0.87584404 | AP13: =IF(AND(A13>Допущения!$C$19,MIN(AI13:AI$65)>0),A13,"") | AQ13: =IF(MIN(AJ13:AJ$65)>0,A13,"")
A14: 9 | B14: =INT((A14-1)/12)+1 -> 1 | C14: Масштабирование | D14: =(1+Допущения!$C$11)^(B14-1) -> 1 | E14: =(1+Допущения!$C$12)^(B14-1) -> 1 | F14: =Допущения!$C$71*E14 -> 2727.48 | G14: =MIN(G13*(1+Допущения!$C$33),Допущения!$C$34) -> 587731.23 | H14: =MIN(Допущения!$C$30,G14/Допущения!$C$29) -> 200 | I14: =MAX(0,G14-H14*Допущения!$C$29)/Допущения!$C$31 -> 38.364164 | J14: =IF(A14>=Допущения!$C$35,Допущения!$C$36,0) -> 20 | K14: =H14+I14+J14 -> 258.36416 | L14: =(L13-K13)*(1-Допущения!$C$44)+K13*(1-Допущения!$C$43)+K14 -> 986.23285 | M14: =IF(A14>=Допущения!$C$38,Допущения!$C$73/Допущения!$C$42*MIN(Допущения!$C$42,A14-Допущения!$C$38+1),0) -> 20 | N14: =N13*(1-Допущения!$C$45)+M14 -> 39.469333 | O14: =L14+N14 -> 1025.7022 | P14: =L14*Допущения!$C$25 -> 147.93493 | Q14: =L14*(1-Допущения!$C$25)+N14 -> 877.76726 | R14: =MAX(Допущения!$C$18,ROUNDUP(Q14/Допущения!$C$68+P14/Допущения!$C$69,0)) -> 13 | S14: =ROUNDUP(R14/Допущения!$C$48,0) -> 2 | T14: =L14*F14/(1+Допущения!$C$6) -> 2204861 | U14: =N14*Допущения!$C$28*E14/(1+Допущения!$C$6) -> 64380.306 | V14: =O14*Допущения!$C$26*Допущения!$C$27/(1+Допущения!$C$6) -> 126110.92 | W14: =T14+U14+V14 -> 2395352.2 | X14: =J14*Допущения!$C$37 -> 10000 | Y14: =(R14*Допущения!$C$47+S14*Допущения!$C$49)*D14*Допущения!$C$9 -> 1640520 | Z14: =(MAX(0,R14-R13)+R14*Допущения!$C$50/12)*Допущения!$C$51*D14 -> 162750 | AA14: =O14*(Допущения!$C$53+Допущения!$C$54)+(L14*F14+N14*Допущения!$C$28*E14)*Допущения!$C$13 -> 424213.84 | AB14: =(R14+S14)*Допущения!$C$52 -> 40500 | AC14: =SUMPRODUCT(Допущения!$B$84:$B$91,Допущения!$C$84:$C$91,--(Допущения!$D$84:$D$91<=A14))*D14*Допущения!$C$9 -> 1627500 | AD14: =(AC14+Y14)*Допущения!$C$14 -> 326802 | AE14: =Допущения!$C$55+Допущения!$C$56*O14/1000+Допущения!$C$57 -> 148205.62 | AF14: =SUMIF(Допущения!$B$95:$B$103,A14,Допущения!$C$95:$C$103) -> 500000 | AG14: 0 | AH14: =G14+SUM(X14:AG14) -> 5468222.7 | AI14: =W14-AH14 -> -3072870.5 | AJ14: =AJ13+AI14 -> -22886488 | AK14: =O14*Допущения!$C$58*Допущения!$C$59 -> 16924.086 | AL14: =T14*Допущения!$C$72 -> 111169.46 | AM14: =IF(MOD(A14,12)=0,INDEX($F$70:$F$74,B14),0) -> 0 | AN14: =AI14-AM14 -> -3072870.5 | AO14: =1/(1+Допущения!$C$74)^A14 -> 0.8614501 | AP14: =IF(AND(A14>Допущения!$C$19,MIN(AI14:AI$65)>0),A14,"") | AQ14: =IF(MIN(AJ14:AJ$65)>0,A14,"")
A15: 10 | B15: =INT((A15-1)/12)+1 -> 1 | C15: Масштабирование | D15: =(1+Допущения!$C$11)^(B15-1) -> 1 | E15: =(1+Допущения!$C$12)^(B15-1) -> 1 | F15: =Допущения!$C$71*E15 -> 2727.48 | G15: =MIN(G14*(1+Допущения!$C$33),Допущения!$C$34) -> 634749.73 | H15: =MIN(Допущения!$C$30,G15/Допущения!$C$29) -> 200 | I15: =MAX(0,G15-H15*Допущения!$C$29)/Допущения!$C$31 -> 44.633297 | J15: =IF(A15>=Допущения!$C$35,Допущения!$C$36,0) -> 20 | K15: =H15+I15+J15 -> 264.6333 | L15: =(L14-K14)*(1-Допущения!$C$44)+K14*(1-Допущения!$C$43)+K15 -> 1102.2092 | M15: =IF(A15>=Допущения!$C$38,Допущения!$C$73/Допущения!$C$42*MIN(Допущения!$C$42,A15-Допущения!$C$38+1),0) -> 20 | N15: =N14*(1-Допущения!$C$45)+M15 -> 58.679947 | O15: =L15+N15 -> 1160.8891 | P15: =L15*Допущения!$C$25 -> 165.33138 | Q15: =L15*(1-Допущения!$C$25)+N15 -> 995.55776 | R15: =MAX(Допущения!$C$18,ROUNDUP(Q15/Допущения!$C$68+P15/Допущения!$C$69,0)) -> 15 | S15: =ROUNDUP(R15/Допущения!$C$48,0) -> 2 | T15: =L15*F15/(1+Допущения!$C$6) -> 2464142.2 | U15: =N15*Допущения!$C$28*E15/(1+Допущения!$C$6) -> 95715.651 | V15: =O15*Допущения!$C$26*Допущения!$C$27/(1+Допущения!$C$6) -> 142732.27 | W15: =T15+U15+V15 -> 2702590.2 | X15: =J15*Допущения!$C$37 -> 10000 | Y15: =(R15*Допущения!$C$47+S15*Допущения!$C$49)*D15*Допущения!$C$9 -> 1848840 | Z15: =(MAX(0,R15-R14)+R15*Допущения!$C$50/12)*Допущения!$C$51*D15 -> 166250 | AA15: =O15*(Допущения!$C$53+Допущения!$C$54)+(L15*F15+N15*Допущения!$C$28*E15)*Допущения!$C$13 -> 479939.02 | AB15: =(R15+S15)*Допущения!$C$52 -> 45900 | AC15: =SUMPRODUCT(Допущения!$B$84:$B$91,Допущения!$C$84:$C$91,--(Допущения!$D$84:$D$91<=A15))*D15*Допущения!$C$9 -> 1966020 | AD15: =(AC15+Y15)*Допущения!$C$14 -> 381486 | AE15: =Допущения!$C$55+Допущения!$C$56*O15/1000+Допущения!$C$57 -> 149287.11 | AF15: =SUMIF(Допущения!$B$95:$B$103,A15,Допущения!$C$95:$C$103) -> 350000 | AG15: 0 | AH15: =G15+SUM(X15:AG15) -> 6032471.9 | AI15: =W15-AH15 -> -3329881.7 | AJ15: =AJ14+AI15 -> -26216370 | AK15: =O15*Допущения!$C$58*Допущения!$C$59 -> 19154.671 | AL15: =T15*Допущения!$C$72 -> 124242.47 | AM15: =IF(MOD(A15,12)=0,INDEX($F$70:$F$74,B15),0) -> 0 | AN15: =AI15-AM15 -> -3329881.7 | AO15: =1/(1+Допущения!$C$74)^A15 -> 0.84729272 | AP15: =IF(AND(A15>Допущения!$C$19,MIN(AI15:AI$65)>0),A15,"") | AQ15: =IF(MIN(AJ15:AJ$65)>0,A15,"")
A16: 11 | B16: =INT((A16-1)/12)+1 -> 1 | C16: Масштабирование | D16: =(1+Допущения!$C$11)^(B16-1) -> 1 | E16: =(1+Допущения!$C$12)^(B16-1) -> 1 | F16: =Допущения!$C$71*E16 -> 2727.48 | G16: =MIN(G15*(1+Допущения!$C$33),Допущения!$C$34) -> 685529.71 | H16: =MIN(Допущения!$C$30,G16/Допущения!$C$29) -> 200 | I16: =MAX(0,G16-H16*Допущения!$C$29)/Допущения!$C$31 -> 51.403961 | J16: =IF(A16>=Допущения!$C$35,Допущения!$C$36,0) -> 20 | K16: =H16+I16+J16 -> 271.40396 | L16: =(L15-K15)*(1-Допущения!$C$44)+K15*(1-Допущения!$C$43)+K16 -> 1213.9854 | M16: =IF(A16>=Допущения!$C$38,Допущения!$C$73/Допущения!$C$42*MIN(Допущения!$C$42,A16-Допущения!$C$38+1),0) -> 20 | N16: =N15*(1-Допущения!$C$45)+M16 -> 77.506348 | O16: =L16+N16 -> 1291.4918 | P16: =L16*Допущения!$C$25 -> 182.09781 | Q16: =L16*(1-Допущения!$C$25)+N16 -> 1109.394 | R16: =MAX(Допущения!$C$18,ROUNDUP(Q16/Допущения!$C$68+P16/Допущения!$C$69,0)) -> 16 | S16: =ROUNDUP(R16/Допущения!$C$48,0) -> 2 | T16: =L16*F16/(1+Допущения!$C$6) -> 2714033.6 | U16: =N16*Допущения!$C$28*E16/(1+Допущения!$C$6) -> 126424.29 | V16: =O16*Допущения!$C$26*Допущения!$C$27/(1+Допущения!$C$6) -> 158789.97 | W16: =T16+U16+V16 -> 2999247.9 | X16: =J16*Допущения!$C$37 -> 10000 | Y16: =(R16*Допущения!$C$47+S16*Допущения!$C$49)*D16*Допущения!$C$9 -> 1953000 | Z16: =(MAX(0,R16-R15)+R16*Допущения!$C$50/12)*Допущения!$C$51*D16 -> 98000 | AA16: =O16*(Допущения!$C$53+Допущения!$C$54)+(L16*F16+N16*Допущения!$C$28*E16)*Допущения!$C$13 -> 533770.95 | AB16: =(R16+S16)*Допущения!$C$52 -> 48600 | AC16: =SUMPRODUCT(Допущения!$B$84:$B$91,Допущения!$C$84:$C$91,--(Допущения!$D$84:$D$91<=A16))*D16*Допущения!$C$9 -> 1966020 | AD16: =(AC16+Y16)*Допущения!$C$14 -> 391902 | AE16: =Допущения!$C$55+Допущения!$C$56*O16/1000+Допущения!$C$57 -> 150331.93 | AF16: =SUMIF(Допущения!$B$95:$B$103,A16,Допущения!$C$95:$C$103) -> 350000 | AG16: 0 | AH16: =G16+SUM(X16:AG16) -> 6187154.6 | AI16: =W16-AH16 -> -3187906.7 | AJ16: =AJ15+AI16 -> -29404276 | AK16: =O16*Допущения!$C$58*Допущения!$C$59 -> 21309.614 | AL16: =T16*Допущения!$C$72 -> 136842.03 | AM16: =IF(MOD(A16,12)=0,INDEX($F$70:$F$74,B16),0) -> 0 | AN16: =AI16-AM16 -> -3187906.7 | AO16: =1/(1+Допущения!$C$74)^A16 -> 0.833368 | AP16: =IF(AND(A16>Допущения!$C$19,MIN(AI16:AI$65)>0),A16,"") | AQ16: =IF(MIN(AJ16:AJ$65)>0,A16,"")
A17: 12 | B17: =INT((A17-1)/12)+1 -> 1 | C17: Масштабирование | D17: =(1+Допущения!$C$11)^(B17-1) -> 1 | E17: =(1+Допущения!$C$12)^(B17-1) -> 1 | F17: =Допущения!$C$71*E17 -> 2727.48 | G17: =MIN(G16*(1+Допущения!$C$33),Допущения!$C$34) -> 740372.08 | H17: =MIN(Допущения!$C$30,G17/Допущения!$C$29) -> 200 | I17: =MAX(0,G17-H17*Допущения!$C$29)/Допущения!$C$31 -> 58.716278 | J17: =IF(A17>=Допущения!$C$35,Допущения!$C$36,0) -> 20 | K17: =H17+I17+J17 -> 278.71628 | L17: =(L16-K16)*(1-Допущения!$C$44)+K16*(1-Допущения!$C$43)+K17 -> 1322.3038 | M17: =IF(A17>=Допущения!$C$38,Допущения!$C$73/Допущения!$C$42*MIN(Допущения!$C$42,A17-Допущения!$C$38+1),0) -> 20 | N17: =N16*(1-Допущения!$C$45)+M17 -> 95.956221 | O17: =L17+N17 -> 1418.26 | P17: =L17*Допущения!$C$25 -> 198.34557 | Q17: =L17*(1-Допущения!$C$25)+N17 -> 1219.9145 | R17: =MAX(Допущения!$C$18,ROUNDUP(Q17/Допущения!$C$68+P17/Допущения!$C$69,0)) -> 18 | S17: =ROUNDUP(R17/Допущения!$C$48,0) -> 2 | T17: =L17*F17/(1+Допущения!$C$6) -> 2956194.4 | U17: =N17*Допущения!$C$28*E17/(1+Допущения!$C$6) -> 156518.75 | V17: =O17*Допущения!$C$26*Допущения!$C$27/(1+Допущения!$C$6) -> 174376.23 | W17: =T17+U17+V17 -> 3287089.4 | X17: =J17*Допущения!$C$37 -> 10000 | Y17: =(R17*Допущения!$C$47+S17*Допущения!$C$49)*D17*Допущения!$C$9 -> 2161320 | Z17: =(MAX(0,R17-R16)+R17*Допущения!$C$50/12)*Допущения!$C$51*D17 -> 171500 | AA17: =O17*(Допущения!$C$53+Допущения!$C$54)+(L17*F17+N17*Допущения!$C$28*E17)*Допущения!$C$13 -> 586020.09 | AB17: =(R17+S17)*Допущения!$C$52 -> 54000 | AC17: =SUMPRODUCT(Допущения!$B$84:$B$91,Допущения!$C$84:$C$91,--(Допущения!$D$84:$D$91<=A17))*D17*Допущения!$C$9 -> 1966020 | AD17: =(AC17+Y17)*Допущения!$C$14 -> 412734 | AE17: =Допущения!$C$55+Допущения!$C$56*O17/1000+Допущения!$C$57 -> 151346.08 | AF17: =SUMIF(Допущения!$B$95:$B$103,A17,Допущения!$C$95:$C$103) -> 300000 | AG17: 0 | AH17: =G17+SUM(X17:AG17) -> 6553312.3 | AI17: =W17-AH17 -> -3266222.9 | AJ17: =AJ16+AI17 -> -32670499 | AK17: =O17*Допущения!$C$58*Допущения!$C$59 -> 23401.29 | AL17: =T17*Допущения!$C$72 -> 149051.82 | AM17: =IF(MOD(A17,12)=0,INDEX($F$70:$F$74,B17),0) -> 0 | AN17: =AI17-AM17 -> -3266222.9 | AO17: =1/(1+Допущения!$C$74)^A17 -> 0.81967213 | AP17: =IF(AND(A17>Допущения!$C$19,MIN(AI17:AI$65)>0),A17,"") | AQ17: =IF(MIN(AJ17:AJ$65)>0,A17,"")
A18: 13 | B18: =INT((A18-1)/12)+1 -> 2 | C18: Масштабирование | D18: =(1+Допущения!$C$11)^(B18-1) -> 1.08 | E18: =(1+Допущения!$C$12)^(B18-1) -> 1.07 | F18: =Допущения!$C$71*E18 -> 2918.4036 | G18: =MIN(G17*(1+Допущения!$C$33),Допущения!$C$34) -> 799601.85 | H18: =MIN(Допущения!$C$30,G18/Допущения!$C$29) -> 200 | I18: =MAX(0,G18-H18*Допущения!$C$29)/Допущения!$C$31 -> 66.61358 | J18: =IF(A18>=Допущения!$C$35,Допущения!$C$36,0) -> 20 | K18: =H18+I18+J18 -> 286.61358 | L18: =(L17-K17)*(1-Допущения!$C$44)+K17*(1-Допущения!$C$43)+K18 -> 1427.8797 | M18: =IF(A18>=Допущения!$C$38,Допущения!$C$73/Допущения!$C$42*MIN(Допущения!$C$42,A18-Допущения!$C$38+1),0) -> 20 | N18: =N17*(1-Допущения!$C$45)+M18 -> 114.0371 | O18: =L18+N18 -> 1541.9168 | P18: =L18*Допущения!$C$25 -> 214.18195 | Q18: =L18*(1-Допущения!$C$25)+N18 -> 1327.7348 | R18: =MAX(Допущения!$C$18,ROUNDUP(Q18/Допущения!$C$68+P18/Допущения!$C$69,0)) -> 19 | S18: =ROUNDUP(R18/Допущения!$C$48,0) -> 2 | T18: =L18*F18/(1+Допущения!$C$6) -> 3415679.7 | U18: =N18*Допущения!$C$28*E18/(1+Допущения!$C$6) -> 199032.12 | V18: =O18*Допущения!$C$26*Допущения!$C$27/(1+Допущения!$C$6) -> 189579.93 | W18: =T18+U18+V18 -> 3804291.7 | X18: =J18*Допущения!$C$37 -> 10000 | Y18: =(R18*Допущения!$C$47+S18*Допущения!$C$49)*D18*Допущения!$C$9 -> 2446718.4 | Z18: =(MAX(0,R18-R17)+R18*Допущения!$C$50/12)*Допущения!$C$51*D18 -> 111510 | AA18: =O18*(Допущения!$C$53+Допущения!$C$54)+(L18*F18+N18*Допущения!$C$28*E18)*Допущения!$C$13 -> 642178.7 | AB18: =(R18+S18)*Допущения!$C$52 -> 56700 | AC18: =SUMPRODUCT(Допущения!$B$84:$B$91,Допущения!$C$84:$C$91,--(Допущения!$D$84:$D$91<=A18))*D18*Допущения!$C$9 -> 2123301.6 | AD18: =(AC18+Y18)*Допущения!$C$14 -> 457002 | AE18: =Допущения!$C$55+Допущения!$C$56*O18/1000+Допущения!$C$57 -> 152335.33 | AF18: =SUMIF(Допущения!$B$95:$B$103,A18,Допущения!$C$95:$C$103) -> 0 | AG18: 0 | AH18: =G18+SUM(X18:AG18) -> 6799347.9 | AI18: =W18-AH18 -> -2995056.1 | AJ18: =AJ17+AI18 -> -35665555 | AK18: =O18*Допущения!$C$58*Допущения!$C$59 -> 25441.627 | AL18: =T18*Допущения!$C$72 -> 172219.14 | AM18: =IF(MOD(A18,12)=0,INDEX($F$70:$F$74,B18),0) -> 0 | AN18: =AI18-AM18 -> -2995056.1 | AO18: =1/(1+Допущения!$C$74)^A18 -> 0.80620134 | AP18: =IF(AND(A18>Допущения!$C$19,MIN(AI18:AI$65)>0),A18,"") | AQ18: =IF(MIN(AJ18:AJ$65)>0,A18,"")
A19: 14 | B19: =INT((A19-1)/12)+1 -> 2 | C19: Масштабирование | D19: =(1+Допущения!$C$11)^(B19-1) -> 1.08 | E19: =(1+Допущения!$C$12)^(B19-1) -> 1.07 | F19: =Допущения!$C$71*E19 -> 2918.4036 | G19: =MIN(G18*(1+Допущения!$C$33),Допущения!$C$34) -> 863570 | H19: =MIN(Допущения!$C$30,G19/Допущения!$C$29) -> 200 | I19: =MAX(0,G19-H19*Допущения!$C$29)/Допущения!$C$31 -> 75.142667 | J19: =IF(A19>=Допущения!$C$35,Допущения!$C$36,0) -> 20 | K19: =H19+I19+J19 -> 295.14267 | L19: =(L18-K18)*(1-Допущения!$C$44)+K18*(1-Допущения!$C$43)+K19 -> 1531.4063 | M19: =IF(A19>=Допущения!$C$38,Допущения!$C$73/Допущения!$C$42*MIN(Допущения!$C$42,A19-Допущения!$C$38+1),0) -> 20 | N19: =N18*(1-Допущения!$C$45)+M19 -> 131.75635 | O19: =L19+N19 -> 1663.1627 | P19: =L19*Допущения!$C$25 -> 229.71095 | Q19: =L19*(1-Допущения!$C$25)+N19 -> 1433.4517 | R19: =MAX(Допущения!$C$18,ROUNDUP(Q19/Допущения!$C$68+P19/Допущения!$C$69,0)) -> 21 | S19: =ROUNDUP(R19/Допущения!$C$48,0) -> 2 | T19: =L19*F19/(1+Допущения!$C$6) -> 3663329.3 | U19: =N19*Допущения!$C$28*E19/(1+Допущения!$C$6) -> 229958.04 | V19: =O19*Допущения!$C$26*Допущения!$C$27/(1+Допущения!$C$6) -> 204487.21 | W19: =T19+U19+V19 -> 4097774.5 | X19: =J19*Допущения!$C$37 -> 10000 | Y19: =(R19*Допущения!$C$47+S19*Допущения!$C$49)*D19*Допущения!$C$9 -> 2671704 | Z19: =(MAX(0,R19-R18)+R19*Допущения!$C$50/12)*Допущения!$C$51*D19 -> 190890 | AA19: =O19*(Допущения!$C$53+Допущения!$C$54)+(L19*F19+N19*Допущения!$C$28*E19)*Допущения!$C$13 -> 692550.96 | AB19: =(R19+S19)*Допущения!$C$52 -> 62100 | AC19: =SUMPRODUCT(Допущения!$B$84:$B$91,Допущения!$C$84:$C$91,--(Допущения!$D$84:$D$91<=A19))*D19*Допущения!$C$9 -> 2123301.6 | AD19: =(AC19+Y19)*Допущения!$C$14 -> 479500.56 | AE19: =Допущения!$C$55+Допущения!$C$56*O19/1000+Допущения!$C$57 -> 153305.3 | AF19: =SUMIF(Допущения!$B$95:$B$103,A19,Допущения!$C$95:$C$103) -> 0 | AG19: 0 | AH19: =G19+SUM(X19:AG19) -> 7246922.4 | AI19: =W19-AH19 -> -3149147.9 | AJ19: =AJ18+AI19 -> -38814703 | AK19: =O19*Допущения!$C$58*Допущения!$C$59 -> 27442.184 | AL19: =T19*Допущения!$C$72 -> 184705.68 | AM19: =IF(MOD(A19,12)=0,INDEX($F$70:$F$74,B19),0) -> 0 | AN19: =AI19-AM19 -> -3149147.9 | AO19: =1/(1+Допущения!$C$74)^A19 -> 0.79295194 | AP19: =IF(AND(A19>Допущения!$C$19,MIN(AI19:AI$65)>0),A19,"") | AQ19: =IF(MIN(AJ19:AJ$65)>0,A19,"")
A20: 15 | B20: =INT((A20-1)/12)+1 -> 2 | C20: Масштабирование | D20: =(1+Допущения!$C$11)^(B20-1) -> 1.08 | E20: =(1+Допущения!$C$12)^(B20-1) -> 1.07 | F20: =Допущения!$C$71*E20 -> 2918.4036 | G20: =MIN(G19*(1+Допущения!$C$33),Допущения!$C$34) -> 932655.6 | H20: =MIN(Допущения!$C$30,G20/Допущения!$C$29) -> 200 | I20: =MAX(0,G20-H20*Допущения!$C$29)/Допущения!$C$31 -> 84.35408 | J20: =IF(A20>=Допущения!$C$35,Допущения!$C$36,0) -> 20 | K20: =H20+I20+J20 -> 304.35408 | L20: =(L19-K19)*(1-Допущения!$C$44)+K19*(1-Допущения!$C$43)+K20 -> 1633.5594 | M20: =IF(A20>=Допущения!$C$38,Допущения!$C$73/Допущения!$C$42*MIN(Допущения!$C$42,A20-Допущения!$C$38+1),0) -> 20 | N20: =N19*(1-Допущения!$C$45)+M20 -> 149.12123 | O20: =L20+N20 -> 1782.6806 | P20: =L20*Допущения!$C$25 -> 245.03391 | Q20: =L20*(1-Допущения!$C$25)+N20 -> 1537.6467 | R20: =MAX(Допущения!$C$18,ROUNDUP(Q20/Допущения!$C$68+P20/Допущения!$C$69,0)) -> 22 | S20: =ROUNDUP(R20/Допущения!$C$48,0) -> 2 | T20: =L20*F20/(1+Допущения!$C$6) -> 3907693.1 | U20: =N20*Допущения!$C$28*E20/(1+Допущения!$C$6) -> 260265.43 | V20: =O20*Допущения!$C$26*Допущения!$C$27/(1+Допущения!$C$6) -> 219182.04 | W20: =T20+U20+V20 -> 4387140.5 | X20: =J20*Допущения!$C$37 -> 10000 | Y20: =(R20*Допущения!$C$47+S20*Допущения!$C$49)*D20*Допущения!$C$9 -> 2784196.8 | Z20: =(MAX(0,R20-R19)+R20*Допущения!$C$50/12)*Допущения!$C$51*D20 -> 117180 | AA20: =O20*(Допущения!$C$53+Допущения!$C$54)+(L20*F20+N20*Допущения!$C$28*E20)*Допущения!$C$13 -> 742206.79 | AB20: =(R20+S20)*Допущения!$C$52 -> 64800 | AC20: =SUMPRODUCT(Допущения!$B$84:$B$91,Допущения!$C$84:$C$91,--(Допущения!$D$84:$D$91<=A20))*D20*Допущения!$C$9 -> 2123301.6 | AD20: =(AC20+Y20)*Допущения!$C$14 -> 490749.84 | AE20: =Допущения!$C$55+Допущения!$C$56*O20/1000+Допущения!$C$57 -> 154261.44 | AF20: =SUMIF(Допущения!$B$95:$B$103,A20,Допущения!$C$95:$C$103) -> 0 | AG20: 0 | AH20: =G20+SUM(X20:AG20) -> 7419352.1 | AI20: =W20-AH20 -> -3032211.5 | AJ20: =AJ19+AI20 -> -41846915 | AK20: =O20*Допущения!$C$58*Допущения!$C$59 -> 29414.23 | AL20: =T20*Допущения!$C$72 -> 197026.54 | AM20: =IF(MOD(A20,12)=0,INDEX($F$70:$F$74,B20),0) -> 0 | AN20: =AI20-AM20 -> -3032211.5 | AO20: =1/(1+Допущения!$C$74)^A20 -> 0.77992028 | AP20: =IF(AND(A20>Допущения!$C$19,MIN(AI20:AI$65)>0),A20,"") | AQ20: =IF(MIN(AJ20:AJ$65)>0,A20,"")
A21: 16 | B21: =INT((A21-1)/12)+1 -> 2 | C21: Масштабирование | D21: =(1+Допущения!$C$11)^(B21-1) -> 1.08 | E21: =(1+Допущения!$C$12)^(B21-1) -> 1.07 | F21: =Допущения!$C$71*E21 -> 2918.4036 | G21: =MIN(G20*(1+Допущения!$C$33),Допущения!$C$34) -> 1007268 | H21: =MIN(Допущения!$C$30,G21/Допущения!$C$29) -> 200 | I21: =MAX(0,G21-H21*Допущения!$C$29)/Допущения!$C$31 -> 94.302406 | J21: =IF(A21>=Допущения!$C$35,Допущения!$C$36,0) -> 20 | K21: =H21+I21+J21 -> 314.30241 | L21: =(L20-K20)*(1-Допущения!$C$44)+K20*(1-Допущения!$C$43)+K21 -> 1735.0014 | M21: =IF(A21>=Допущения!$C$38,Допущения!$C$73/Допущения!$C$42*MIN(Допущения!$C$42,A21-Допущения!$C$38+1),0) -> 20 | N21: =N20*(1-Допущения!$C$45)+M21 -> 166.1388 | O21: =L21+N21 -> 1901.1402 | P21: =L21*Допущения!$C$25 -> 260.25021 | Q21: =L21*(1-Допущения!$C$25)+N21 -> 1640.89 | R21: =MAX(Допущения!$C$18,ROUNDUP(Q21/Допущения!$C$68+P21/Допущения!$C$69,0)) -> 24 | S21: =ROUNDUP(R21/Допущения!$C$48,0) -> 2 | T21: =L21*F21/(1+Допущения!$C$6) -> 4150356.1 | U21: =N21*Допущения!$C$28*E21/(1+Допущения!$C$6) -> 289966.68 | V21: =O21*Допущения!$C$26*Допущения!$C$27/(1+Допущения!$C$6) -> 233746.75 | W21: =T21+U21+V21 -> 4674069.5 | X21: =J21*Допущения!$C$37 -> 10000 | Y21: =(R21*Допущения!$C$47+S21*Допущения!$C$49)*D21*Допущения!$C$9 -> 3009182.4 | Z21: =(MAX(0,R21-R20)+R21*Допущения!$C$50/12)*Допущения!$C$51*D21 -> 196560 | AA21: =O21*(Допущения!$C$53+Допущения!$C$54)+(L21*F21+N21*Допущения!$C$28*E21)*Допущения!$C$13 -> 791425.67 | AB21: =(R21+S21)*Допущения!$C$52 -> 70200 | AC21: =SUMPRODUCT(Допущения!$B$84:$B$91,Допущения!$C$84:$C$91,--(Допущения!$D$84:$D$91<=A21))*D21*Допущения!$C$9 -> 2123301.6 | AD21: =(AC21+Y21)*Допущения!$C$14 -> 513248.4 | AE21: =Допущения!$C$55+Допущения!$C$56*O21/1000+Допущения!$C$57 -> 155209.12 | AF21: =SUMIF(Допущения!$B$95:$B$103,A21,Допущения!$C$95:$C$103) -> 0 | AG21: 0 | AH21: =G21+SUM(X21:AG21) -> 7876395.2 | AI21: =W21-AH21 -> -3202325.7 | AJ21: =AJ20+AI21 -> -45049240 | AK21: =O21*Допущения!$C$58*Допущения!$C$59 -> 31368.814 | AL21: =T21*Допущения!$C$72 -> 209261.65 | AM21: =IF(MOD(A21,12)=0,INDEX($F$70:$F$74,B21),0) -> 0 | AN21: =AI21-AM21 -> -3202325.7 | AO21: =1/(1+Допущения!$C$74)^A21 -> 0.76710278 | AP21: =IF(AND(A21>Допущения!$C$19,MIN(AI21:AI$65)>0),A21,"") | AQ21: =IF(MIN(AJ21:AJ$65)>0,A21,"")
... A65: 60 | B65: =INT((A65-1)/12)+1 -> 5 | C65: Масштабирование | D65: =(1+Допущения!$C$11)^(B65-1) -> 1.360489 | E65: =(1+Допущения!$C$12)^(B65-1) -> 1.310796 | F65: =Допущения!$C$71*E65 -> 3575.1699 | G65: =MIN(G64*(1+Допущения!$C$33),Допущения!$C$34) -> 2500000 | H65: =MIN(Допущения!$C$30,G65/Допущения!$C$29) -> 200 | I65: =MAX(0,G65-H65*Допущения!$C$29)/Допущения!$C$31 -> 293.33333 | J65: =IF(A65>=Допущения!$C$35,Допущения!$C$36,0) -> 20 | K65: =H65+I65+J65 -> 513.33333 | L65: =(L64-K64)*(1-Допущения!$C$44)+K64*(1-Допущения!$C$43)+K65 -> 4576.6072 | M65: =IF(A65>=Допущения!$C$38,Допущения!$C$73/Допущения!$C$42*MIN(Допущения!$C$42,A65-Допущения!$C$38+1),0) -> 20 | N65: =N64*(1-Допущения!$C$45)+M65 -> 657.19978 | O65: =L65+N65 -> 5233.807 | P65: =L65*Допущения!$C$25 -> 686.49108 | Q65: =L65*(1-Допущения!$C$25)+N65 -> 4547.3159 | R65: =MAX(Допущения!$C$18,ROUNDUP(Q65/Допущения!$C$68+P65/Допущения!$C$69,0)) -> 64 | S65: =ROUNDUP(R65/Допущения!$C$48,0) -> 6 | T65: =L65*F65/(1+Допущения!$C$6) -> 13411597 | U65: =N65*Допущения!$C$28*E65/(1+Допущения!$C$6) -> 1405160 | V65: =O65*Допущения!$C$26*Допущения!$C$27/(1+Допущения!$C$6) -> 643500.86 | W65: =T65+U65+V65 -> 15460258 | X65: =J65*Допущения!$C$37 -> 10000 | Y65: =(R65*Допущения!$C$47+S65*Допущения!$C$49)*D65*Допущения!$C$9 -> 10238441 | Z65: =(MAX(0,R65-R64)+R65*Допущения!$C$50/12)*Допущения!$C$51*D65 -> 152374.76 | AA65: =O65*(Допущения!$C$53+Допущения!$C$54)+(L65*F65+N65*Допущения!$C$28*E65)*Допущения!$C$13 -> 2235715.5 | AB65: =(R65+S65)*Допущения!$C$52 -> 189000 | AC65: =SUMPRODUCT(Допущения!$B$84:$B$91,Допущения!$C$84:$C$91,--(Допущения!$D$84:$D$91<=A65))*D65*Допущения!$C$9 -> 2674748.5 | AD65: =(AC65+Y65)*Допущения!$C$14 -> 1291319 | AE65: =Допущения!$C$55+Допущения!$C$56*O65/1000+Допущения!$C$57 -> 181870.46 | AF65: =SUMIF(Допущения!$B$95:$B$103,A65,Допущения!$C$95:$C$103) -> 0 | AG65: 0 | AH65: =G65+SUM(X65:AG65) -> 19473470 | AI65: =W65-AH65 -> -4013211.7 | AJ65: =AJ64+AI65 -> -2.2083319e+08 | AK65: =O65*Допущения!$C$58*Допущения!$C$59 -> 86357.815 | AL65: =T65*Допущения!$C$72 -> 676214.98 | AM65: =IF(MOD(A65,12)=0,INDEX($F$70:$F$74,B65),0) -> 0 | AN65: =AI65-AM65 -> -4013211.7 | AO65: =1/(1+Допущения!$C$74)^A65 -> 0.36999925 | AP65: =IF(AND(A65>Допущения!$C$19,MIN(AI65:AI$65)>0),A65,"") | AQ65: =IF(MIN(AJ65:AJ$65)>0,A65,"")
A68: Годовые итоги и налог на прибыль с переносом убытков
A69: Год | B69: Выручка, руб. | C69: Операционный результат, руб. | D69: Убыток к переносу на начало, руб. | E69: Зачтено убытка, руб. | F69: Налог на прибыль, руб. | G69: Убыток к переносу на конец, руб. | H69: Кросс-продажи, руб.
A70: 1 | B70: =SUMIF($B$6:$B$65,A70,$W$6:$W$65) -> 18779931 | C70: =SUMIF($B$6:$B$65,A70,$AI$6:$AI$65) -> -32670499 | D70: 0 | E70: =IF(C70>0,MIN(D70,C70*Допущения!$C$8),0) -> 0 | F70: =IF(C70>0,(C70-E70)*Допущения!$C$7,0) -> 0 | G70: =D70+IF(C70<0,-C70,0)-E70 -> 32670499 | H70: =SUMIF($B$6:$B$65,A70,$AK$6:$AK$65) -> 130590.85
A71: 2 | B71: =SUMIF($B$6:$B$65,A71,$W$6:$W$65) -> 64939175 | C71: =SUMIF($B$6:$B$65,A71,$AI$6:$AI$65) -> -40397407 | D71: =G70 -> 32670499 | E71: =IF(C71>0,MIN(D71,C71*Допущения!$C$8),0) -> 0 | F71: =IF(C71>0,(C71-E71)*Допущения!$C$7,0) -> 0 | G71: =D71+IF(C71<0,-C71,0)-E71 -> 73067906 | H71: =SUMIF($B$6:$B$65,A71,$AK$6:$AK$65) -> 436480.69
A72: 3 | B72: =SUMIF($B$6:$B$65,A72,$W$6:$W$65) -> 1.1763414e+08 | C72: =SUMIF($B$6:$B$65,A72,$AI$6:$AI$65) -> -50659679 | D72: =G71 -> 73067906 | E72: =IF(C72>0,MIN(D72,C72*Допущения!$C$8),0) -> 0 | F72: =IF(C72>0,(C72-E72)*Допущения!$C$7,0) -> 0 | G72: =D72+IF(C72<0,-C72,0)-E72 -> 1.2372758e+08 | H72: =SUMIF($B$6:$B$65,A72,$AK$6:$AK$65) -> 742781.96
A73: 4 | B73: =SUMIF($B$6:$B$65,A73,$W$6:$W$65) -> 1.5729593e+08 | C73: =SUMIF($B$6:$B$65,A73,$AI$6:$AI$65) -> -48137365 | D73: =G72 -> 1.2372758e+08 | E73: =IF(C73>0,MIN(D73,C73*Допущения!$C$8),0) -> 0 | F73: =IF(C73>0,(C73-E73)*Допущения!$C$7,0) -> 0 | G73: =D73+IF(C73<0,-C73,0)-E73 -> 1.7186495e+08 | H73: =SUMIF($B$6:$B$65,A73,$AK$6:$AK$65) -> 933098.65
A74: 5 | B74: =SUMIF($B$6:$B$65,A74,$W$6:$W$65) -> 1.8185011e+08 | C74: =SUMIF($B$6:$B$65,A74,$AI$6:$AI$65) -> -48968239 | D74: =G73 -> 1.7186495e+08 | E74: =IF(C74>0,MIN(D74,C74*Допущения!$C$8),0) -> 0 | F74: =IF(C74>0,(C74-E74)*Допущения!$C$7,0) -> 0 | G74: =D74+IF(C74<0,-C74,0)-E74 -> 2.2083319e+08 | H74: =SUMIF($B$6:$B$65,A74,$AK$6:$AK$65) -> 1014327.9
A75: Итого | B75: =SUM(B70:B74) -> 5.4049928e+08 | C75: =SUM(C70:C74) -> -2.2083319e+08 | F75: =SUM(F70:F74) -> 0 | H75: =SUM(H70:H74) -> 3257280

Sheet Базовый
A1: Помесячный расчет: сценарий «Базовый»
A2: Суммы в рублях без НДС. Месяцы 1-3: MVP. Налог на прибыль начисляется в последнем месяце года.
A5: Месяц | B5: Год | C5: Фаза | D5: Индекс зарплат | E5: Индекс цен | F5: Средний чек B2C с НДС, руб. | G5: Маркетинг, руб. | H5: Новые семьи: внутренние каналы | I5: Новые семьи: внешние каналы | J5: Новые семьи: канал фонда «Защитники Отечества» | K5: Новые семьи B2C | L5: Семьи B2C | M5: Приток B2B2C | N5: Семьи B2B2C | O5: Всего семей | P5: Семьи «Расши-ренный» | Q5: Семьи «Базовый» и B2B2C | R5: Координа-торы, чел. | S5: Супер-визоры, чел. | T5: Выручка: подписка B2C, руб. | U5: Выручка: B2B2C, руб. | V5: Выручка: комиссия партнеров, руб. | W5: Выручка всего, руб. | X5: Партнерский канал фонда, руб. | Y5: ФОТ координаторов и супервизоров, руб. | Z5: Обучение новых координаторов, руб. | AA5: Переменные расходы на семьи, руб. | AB5: Рабочие места, руб. | AC5: Постоянная команда, руб. | AD5: Накладные, руб. | AE5: Размещение и юрлицо, руб. | AF5: Инвестиции, руб. | AG5: Бюджет MVP, руб. | AH5: Расходы всего, руб. | AI5: Операционный результат, руб. | AJ5: Накопленный результат, руб. | AK5: Кросс-продажи (эффект группы), руб. | AL5: Льготы ветеранам: недополученная выручка, руб. | AM5: Налог на прибыль, руб. | AN5: Денежный поток после налога, руб. | AO5: Коэффициент дисконтирования | AP5: Признак безубыточности (месяц) | AQ5: Признак окупаемости (месяц)
A6: 1 | B6: =INT((A6-1)/12)+1 -> 1 | C6: MVP | D6: =(1+Допущения!$D$11)^(B6-1) -> 1 | E6: =(1+Допущения!$D$12)^(B6-1) -> 1 | F6: =Допущения!$D$71*E6 -> 2965.48 | G6: 0 | H6: 0 | I6: 0 | J6: 0 | K6: =Допущения!$B$78-0 -> 0 | L6: =Допущения!$B$78 -> 0 | M6: 0 | N6: 0 | O6: =L6+N6 -> 0 | P6: =L6*Допущения!$D$25 -> 0 | Q6: =L6*(1-Допущения!$D$25)+N6 -> 0 | R6: =IF(A6>1,Допущения!$D$18,0) -> 0 | S6: 0 | T6: =L6*Допущения!$D$60*F6/(1+Допущения!$D$6) -> 0 | U6: =N6*Допущения!$D$28*E6/(1+Допущения!$D$6) -> 0 | V6: =O6*Допущения!$D$26*Допущения!$D$27/(1+Допущения!$D$6) -> 0 | W6: =T6+U6+V6 -> 0 | X6: 0 | Y6: 0 | Z6: 0 | AA6: 0 | AB6: 0 | AC6: 0 | AD6: 0 | AE6: 0 | AF6: 0 | AG6: ='Бюджет MVP'!$G$33/Допущения!$D$19 -> 1624654.7 | AH6: =G6+SUM(X6:AG6) -> 1624654.7 | AI6: =W6-AH6 -> -1624654.7 | AJ6: =AI6 -> -1624654.7 | AK6: 0 | AL6: =T6*Допущения!$D$72 -> 0 | AM6: =IF(MOD(A6,12)=0,INDEX($F$70:$F$74,B6),0) -> 0 | AN6: =AI6-AM6 -> -1624654.7 | AO6: =1/(1+Допущения!$D$74)^A6 -> 0.98356564 | AP6: =IF(AND(A6>Допущения!$D$19,MIN(AI6:AI$65)>0),A6,"") | AQ6: =IF(MIN(AJ6:AJ$65)>0,A6,"")
A7: 2 | B7: =INT((A7-1)/12)+1 -> 1 | C7: MVP | D7: =(1+Допущения!$D$11)^(B7-1) -> 1 | E7: =(1+Допущения!$D$12)^(B7-1) -> 1 | F7: =Допущения!$D$71*E7 -> 2965.48 | G7: 0 | H7: 0 | I7: 0 | J7: 0 | K7: =Допущения!$B$79-Допущения!$B$78 -> 50 | L7: =Допущения!$B$79 -> 50 | M7: 0 | N7: 0 | O7: =L7+N7 -> 50 | P7: =L7*Допущения!$D$25 -> 12.5 | Q7: =L7*(1-Допущения!$D$25)+N7 -> 37.5 | R7: =IF(A7>1,Допущения!$D$18,0) -> 3 | S7: 0 | T7: =L7*Допущения!$D$60*F7/(1+Допущения!$D$6) -> 72921.639 | U7: =N7*Допущения!$D$28*E7/(1+Допущения!$D$6) -> 0 | V7: =O7*Допущения!$D$26*Допущения!$D$27/(1+Допущения!$D$6) -> 6147.541 | W7: =T7+U7+V7 -> 79069.18 | X7: 0 | Y7: 0 | Z7: 0 | AA7: 0 | AB7: 0 | AC7: 0 | AD7: 0 | AE7: 0 | AF7: 0 | AG7: ='Бюджет MVP'!$G$33/Допущения!$D$19 -> 1624654.7 | AH7: =G7+SUM(X7:AG7) -> 1624654.7 | AI7: =W7-AH7 -> -1545585.5 | AJ7: =AJ6+AI7 -> -3170240.2 | AK7: 0 | AL7: =T7*Допущения!$D$72 -> 3676.7213 | AM7: =IF(MOD(A7,12)=0,INDEX($F$70:$F$74,B7),0) -> 0 | AN7: =AI7-AM7 -> -1545585.5 | AO7: =1/(1+Допущения!$D$74)^A7 -> 0.96740136 | AP7: =IF(AND(A7>Допущения!$D$19,MIN(AI7:AI$65)>0),A7,"") | AQ7: =IF(MIN(AJ7:AJ$65)>0,A7,"")
A8: 3 | B8: =INT((A8-1)/12)+1 -> 1 | C8: MVP | D8: =(1+Допущения!$D$11)^(B8-1) -> 1 | E8: =(1+Допущения!$D$12)^(B8-1) -> 1 | F8: =Допущения!$D$71*E8 -> 2965.48 | G8: 0 | H8: 0 | I8: 0 | J8: 0 | K8: =Допущения!$B$80-Допущения!$B$79 -> 100 | L8: =Допущения!$B$80 -> 150 | M8: 0 | N8: 0 | O8: =L8+N8 -> 150 | P8: =L8*Допущения!$D$25 -> 37.5 | Q8: =L8*(1-Допущения!$D$25)+N8 -> 112.5 | R8: =IF(A8>1,Допущения!$D$18,0) -> 3 | S8: 0 | T8: =L8*Допущения!$D$60*F8/(1+Допущения!$D$6) -> 218764.92 | U8: =N8*Допущения!$D$28*E8/(1+Допущения!$D$6) -> 0 | V8: =O8*Допущения!$D$26*Допущения!$D$27/(1+Допущения!$D$6) -> 18442.623 | W8: =T8+U8+V8 -> 237207.54 | X8: 0 | Y8: 0 | Z8: 0 | AA8: 0 | AB8: 0 | AC8: 0 | AD8: 0 | AE8: 0 | AF8: 0 | AG8: ='Бюджет MVP'!$G$33/Допущения!$D$19 -> 1624654.7 | AH8: =G8+SUM(X8:AG8) -> 1624654.7 | AI8: =W8-AH8 -> -1387447.1 | AJ8: =AJ7+AI8 -> -4557687.3 | AK8: 0 | AL8: =T8*Допущения!$D$72 -> 11030.164 | AM8: =IF(MOD(A8,12)=0,INDEX($F$70:$F$74,B8),0) -> 0 | AN8: =AI8-AM8 -> -1387447.1 | AO8: =1/(1+Допущения!$D$74)^A8 -> 0.95150274 | AP8: =IF(AND(A8>Допущения!$D$19,MIN(AI8:AI$65)>0),A8,"") | AQ8: =IF(MIN(AJ8:AJ$65)>0,A8,"")
A9: 4 | B9: =INT((A9-1)/12)+1 -> 1 | C9: Масштабирование | D9: =(1+Допущения!$D$11)^(B9-1) -> 1 | E9: =(1+Допущения!$D$12)^(B9-1) -> 1 | F9: =Допущения!$D$71*E9 -> 2965.48 | G9: =Допущения!$D$32 -> 400000 | H9: =MIN(Допущения!$D$30,G9/Допущения!$D$29) -> 266.66667 | I9: =MAX(0,G9-H9*Допущения!$D$29)/Допущения!$D$31 -> 0 | J9: =IF(A9>=Допущения!$D$35,Допущения!$D$36,0) -> 0 | K9: =H9+I9+J9 -> 266.66667 | L9: =(L8-K8)*(1-Допущения!$D$44)+K8*(1-Допущения!$D$43)+K9 -> 388.66667 | M9: =IF(A9>=Допущения!$D$38,Допущения!$D$73/Допущения!$D$42*MIN(Допущения!$D$42,A9-Допущения!$D$38+1),0) -> 0 | N9: =N8*(1-Допущения!$D$45)+M9 -> 0 | O9: =L9+N9 -> 388.66667 | P9: =L9*Допущения!$D$25 -> 97.166667 | Q9: =L9*(1-Допущения!$D$25)+N9 -> 291.5 | R9: =MAX(Допущения!$D$18,ROUNDUP(Q9/Допущения!$D$68+P9/Допущения!$D$69,0)) -> 5 | S9: =ROUNDUP(R9/Допущения!$D$48,0) -> 1 | T9: =L9*F9/(1+Допущения!$D$6) -> 944740.35 | U9: =N9*Допущения!$D$28*E9/(1+Допущения!$D$6) -> 0 | V9: =O9*Допущения!$D$26*Допущения!$D$27/(1+Допущения!$D$6) -> 47786.885 | W9: =T9+U9+V9 -> 992527.23 | X9: =J9*Допущения!$D$37 -> 0 | Y9: =(R9*Допущения!$D$47+S9*Допущения!$D$49)*D9*Допущения!$D$9 -> 598920 | Z9: =(MAX(0,R9-R8)+R9*Допущения!$D$50/12)*Допущения!$D$51*D9 -> 148750 | AA9: =O9*(Допущения!$D$53+Допущения!$D$54)+(L9*F9+N9*Допущения!$D$28*E9)*Допущения!$D$13 -> 162609.83 | AB9: =(R9+S9)*Допущения!$D$52 -> 16200 | AC9: =SUMPRODUCT(Допущения!$B$84:$B$91,Допущения!$C$84:$C$91,--(Допущения!$D$84:$D$91<=A9))*D9*Допущения!$D$9 -> 1132740 | AD9: =(AC9+Y9)*Допущения!$D$14 -> 173166 | AE9: =Допущения!$D$55+Допущения!$D$56*O9/1000+Допущения!$D$57 -> 143109.33 | AF9: =SUMIF(Допущения!$B$95:$B$103,A9,Допущения!$C$95:$C$103) -> 1000000 | AG9: 0 | AH9: =G9+SUM(X9:AG9) -> 3775495.2 | AI9: =W9-AH9 -> -2782967.9 | AJ9: =AJ8+AI9 -> -7340655.2 | AK9: =O9*Допущения!$D$58*Допущения!$D$59 -> 12826 | AL9: =T9*Допущения!$D$72 -> 47633.967 | AM9: =IF(MOD(A9,12)=0,INDEX($F$70:$F$74,B9),0) -> 0 | AN9: =AI9-AM9 -> -2782967.9 | AO9: =1/(1+Допущения!$D$74)^A9 -> 0.9358654 | AP9: =IF(AND(A9>Допущения!$D$19,MIN(AI9:AI$65)>0),A9,"") | AQ9: =IF(MIN(AJ9:AJ$65)>0,A9,"")
A10: 5 | B10: =INT((A10-1)/12)+1 -> 1 | C10: Масштабирование | D10: =(1+Допущения!$D$11)^(B10-1) -> 1 | E10: =(1+Допущения!$D$12)^(B10-1) -> 1 | F10: =Допущения!$D$71*E10 -> 2965.48 | G10: =MIN(G9*(1+Допущения!$D$33),Допущения!$D$34) -> 432000 | H10: =MIN(Допущения!$D$30,G10/Допущения!$D$29) -> 288 | I10: =MAX(0,G10-H10*Допущения!$D$29)/Допущения!$D$31 -> 0 | J10: =IF(A10>=Допущения!$D$35,Допущения!$D$36,0) -> 0 | K10: =H10+I10+J10 -> 288 | L10: =(L9-K9)*(1-Допущения!$D$44)+K9*(1-Допущения!$D$43)+K10 -> 602.68 | M10: =IF(A10>=Допущения!$D$38,Допущения!$D$73/Допущения!$D$42*MIN(Допущения!$D$42,A10-Допущения!$D$38+1),0) -> 0 | N10: =N9*(1-Допущения!$D$45)+M10 -> 0 | O10: =L10+N10 -> 602.68 | P10: =L10*Допущения!$D$25 -> 150.67 | Q10: =L10*(1-Допущения!$D$25)+N10 -> 452.01 | R10: =MAX(Допущения!$D$18,ROUNDUP(Q10/Допущения!$D$68+P10/Допущения!$D$69,0)) -> 7 | S10: =ROUNDUP(R10/Допущения!$D$48,0) -> 1 | T10: =L10*F10/(1+Допущения!$D$6) -> 1464947.1 | U10: =N10*Допущения!$D$28*E10/(1+Допущения!$D$6) -> 0 | V10: =O10*Допущения!$D$26*Допущения!$D$27/(1+Допущения!$D$6) -> 74100 | W10: =T10+U10+V10 -> 1539047.1 | X10: =J10*Допущения!$D$37 -> 0 | Y10: =(R10*Допущения!$D$47+S10*Допущения!$D$49)*D10*Допущения!$D$9 -> 781200 | Z10: =(MAX(0,R10-R9)+R10*Допущения!$D$50/12)*Допущения!$D$51*D10 -> 152250 | AA10: =O10*(Допущения!$D$53+Допущения!$D$54)+(L10*F10+N10*Допущения!$D$28*E10)*Допущения!$D$13 -> 252148.44 | AB10: =(R10+S10)*Допущения!$D$52 -> 21600 | AC10: =SUMPRODUCT(Допущения!$B$84:$B$91,Допущения!$C$84:$C$91,--(Допущения!$D$84:$D$91<=A10))*D10*Допущения!$D$9 -> 1132740 | AD10: =(AC10+Y10)*Допущения!$D$14 -> 191394 | AE10: =Допущения!$D$55+Допущения!$D$56*O10/1000+Допущения!$D$57 -> 144821.44 | AF10: =SUMIF(Допущения!$B$95:$B$103,A10,Допущения!$C$95:$C$103) -> 1000000 | AG10: 0 | AH10: =G10+SUM(X10:AG10) -> 4108153.9 | AI10: =W10-AH10 -> -2569106.8 | AJ10: =AJ9+AI10 -> -9909762 | AK10: =O10*Допущения!$D$58*Допущения!$D$59 -> 19888.44 | AL10: =T10*Допущения!$D$72 -> 73862.88 | AM10: =IF(MOD(A10,12)=0,INDEX($F$70:$F$74,B10),0) -> 0 | AN10: =AI10-AM10 -> -2569106.8 | AO10: =1/(1+Допущения!$D$74)^A10 -> 0.92048505 | AP10: =IF(AND(A10>Допущения!$D$19,MIN(AI10:AI$65)>0),A10,"") | AQ10: =IF(MIN(AJ10:AJ$65)>0,A10,"")
A11: 6 | B11: =INT((A11-1)/12)+1 -> 1 | C11: Масштабирование | D11: =(1+Допущения!$D$11)^(B11-1) -> 1 | E11: =(1+Допущения!$D$12)^(B11-1) -> 1 | F11: =Допущения!$D$71*E11 -> 2965.48 | G11: =MIN(G10*(1+Допущения!$D$33),Допущения!$D$34) -> 466560 | H11: =MIN(Допущения!$D$30,G11/Допущения!$D$29) -> 300 | I11: =MAX(0,G11-H11*Допущения!$D$29)/Допущения!$D$31 -> 2.76 | J11: =IF(A11>=Допущения!$D$35,Допущения!$D$36,0) -> 40 | K11: =H11+I11+J11 -> 342.76 | L11: =(L10-K10)*(1-Допущения!$D$44)+K10*(1-Допущения!$D$43)+K11 -> 854.5592 | M11: =IF(A11>=Допущения!$D$38,Допущения!$D$73/Допущения!$D$42*MIN(Допущения!$D$42,A11-Допущения!$D$38+1),0) -> 0 | N11: =N10*(1-Допущения!$D$45)+M11 -> 0 | O11: =L11+N11 -> 854.5592 | P11: =L11*Допущения!$D$25 -> 213.6398 | Q11: =L11*(1-Допущения!$D$25)+N11 -> 640.9194 | R11: =MAX(Допущения!$D$18,ROUNDUP(Q11/Допущения!$D$68+P11/Допущения!$D$69,0)) -> 10 | S11: =ROUNDUP(R11/Допущения!$D$48,0) -> 1 | T11: =L11*F11/(1+Допущения!$D$6) -> 2077195.3 | U11: =N11*Допущения!$D$28*E11/(1+Допущения!$D$6) -> 0 | V11: =O11*Допущения!$D$26*Допущения!$D$27/(1+Допущения!$D$6) -> 105068.75 | W11: =T11+U11+V11 -> 2182264 | X11: =J11*Допущения!$D$37 -> 20000 | Y11: =(R11*Допущения!$D$47+S11*Допущения!$D$49)*D11*Допущения!$D$9 -> 1054620 | Z11: =(MAX(0,R11-R10)+R11*Допущения!$D$50/12)*Допущения!$D$51*D11 -> 227500 | AA11: =O11*(Допущения!$D$53+Допущения!$D$54)+(L11*F11+N11*Допущения!$D$28*E11)*Допущения!$D$13 -> 357529.32 | AB11: =(R11+S11)*Допущения!$D$52 -> 29700 | AC11: =SUMPRODUCT(Допущения!$B$84:$B$91,Допущения!$C$84:$C$91,--(Допущения!$D$84:$D$91<=A11))*D11*Допущения!$D$9 -> 1627500 | AD11: =(AC11+Y11)*Допущения!$D$14 -> 268212 | AE11: =Допущения!$D$55+Допущения!$D$56*O11/1000+Допущения!$D$57 -> 146836.47 | AF11: =SUMIF(Допущения!$B$95:$B$103,A11,Допущения!$C$95:$C$103) -> 1000000 | AG11: 0 | AH11: =G11+SUM(X11:AG11) -> 5198457.8 | AI11: =W11-AH11 -> -3016193.8 | AJ11: =AJ10+AI11 -> -12925956 | AK11: =O11*Допущения!$D$58*Допущения!$D$59 -> 28200.454 | AL11: =T11*Допущения!$D$72 -> 104732.53 | AM11: =IF(MOD(A11,12)=0,INDEX($F$70:$F$74,B11),0) -> 0 | AN11: =AI11-AM11 -> -3016193.8 | AO11: =1/(1+Допущения!$D$74)^A11 -> 0.90535746 | AP11: =IF(AND(A11>Допущения!$D$19,MIN(AI11:AI$65)>0),A11,"") | AQ11: =IF(MIN(AJ11:AJ$65)>0,A11,"")
A12: 7 | B12: =INT((A12-1)/12)+1 -> 1 | C12: Масштабирование | D12: =(1+Допущения!$D$11)^(B12-1) -> 1 | E12: =(1+Допущения!$D$12)^(B12-1) -> 1 | F12: =Допущения!$D$71*E12 -> 2965.48 | G12: =MIN(G11*(1+Допущения!$D$33),Допущения!$D$34) -> 503884.8 | H12: =MIN(Допущения!$D$30,G12/Допущения!$D$29) -> 300 | I12: =MAX(0,G12-H12*Допущения!$D$29)/Допущения!$D$31 -> 8.9808 | J12: =IF(A12>=Допущения!$D$35,Допущения!$D$36,0) -> 40 | K12: =H12+I12+J12 -> 348.9808 | L12: =(L11-K11)*(1-Допущения!$D$44)+K11*(1-Допущения!$D$43)+K12 -> 1087.142 | M12: =IF(A12>=Допущения!$D$38,Допущения!$D$73/Допущения!$D$42*MIN(Допущения!$D$42,A12-Допущения!$D$38+1),0) -> 20 | N12: =N11*(1-Допущения!$D$45)+M12 -> 20 | O12: =L12+N12 -> 1107.142 | P12: =L12*Допущения!$D$25 -> 271.78551 | Q12: =L12*(1-Допущения!$D$25)+N12 -> 835.35654 | R12: =MAX(Допущения!$D$18,ROUNDUP(Q12/Допущения!$D$68+P12/Допущения!$D$69,0)) -> 12 | S12: =ROUNDUP(R12/Допущения!$D$48,0) -> 1 | T12: =L12*F12/(1+Допущения!$D$6) -> 2642539.3 | U12: =N12*Допущения!$D$28*E12/(1+Допущения!$D$6) -> 32622.951 | V12: =O12*Допущения!$D$26*Допущения!$D$27/(1+Допущения!$D$6) -> 136124.02 | W12: =T12+U12+V12 -> 2811286.3 | X12: =J12*Допущения!$D$37 -> 20000 | Y12: =(R12*Допущения!$D$47+S12*Допущения!$D$49)*D12*Допущения!$D$9 -> 1236900 | Z12: =(MAX(0,R12-R11)+R12*Допущения!$D$50/12)*Допущения!$D$51*D12 -> 161000 | AA12: =O12*(Допущения!$D$53+Допущения!$D$54)+(L12*F12+N12*Допущения!$D$28*E12)*Допущения!$D$13 -> 462853.41 | AB12: =(R12+S12)*Допущения!$D$52 -> 35100 | AC12: =SUMPRODUCT(Допущения!$B$84:$B$91,Допущения!$C$84:$C$91,--(Допущения!$D$84:$D$91<=A12))*D12*Допущения!$D$9 -> 1627500 | AD12: =(AC12+Y12)*Допущения!$D$14 -> 286440 | AE12: =Допущения!$D$55+Допущения!$D$56*O12/1000+Допущения!$D$57 -> 148857.14 | AF12: =SUMIF(Допущения!$B$95:$B$103,A12,Допущения!$C$95:$C$103) -> 500000 | AG12: 0 | AH12: =G12+SUM(X12:AG12) -> 4982535.3 | AI12: =W12-AH12 -> -2171249 | AJ12: =AJ11+AI12 -> -15097205 | AK12: =O12*Допущения!$D$58*Допущения!$D$59 -> 36535.688 | AL12: =T12*Допущения!$D$72 -> 133237.28 | AM12: =IF(MOD(A12,12)=0,INDEX($F$70:$F$74,B12),0) -> 0 | AN12: =AI12-AM12 -> -2171249 | AO12: =1/(1+Допущения!$D$74)^A12 -> 0.89047849 | AP12: =IF(AND(A12>Допущения!$D$19,MIN(AI12:AI$65)>0),A12,"") | AQ12: =IF(MIN(AJ12:AJ$65)>0,A12,"")
A13: 8 | B13: =INT((A13-1)/12)+1 -> 1 | C13: Масштабирование | D13: =(1+Допущения!$D$11)^(B13-1) -> 1 | E13: =(1+Допущения!$D$12)^(B13-1) -> 1 | F13: =Допущения!$D$71*E13 -> 2965.48 | G13: =MIN(G12*(1+Допущения!$D$33),Допущения!$D$34) -> 544195.58 | H13: =MIN(Допущения!$D$30,G13/Допущения!$D$29) -> 300 | I13: =MAX(0,G13-H13*Допущения!$D$29)/Допущения!$D$31 -> 15.699264 | J13: =IF(A13>=Допущения!$D$35,Допущения!$D$36,0) -> 40 | K13: =H13+I13+J13 -> 355.69926 | L13: =(L12-K12)*(1-Допущения!$D$44)+K12*(1-Допущения!$D$43)+K13 -> 1311.3064 | M13: =IF(A13>=Допущения!$D$38,Допущения!$D$73/Допущения!$D$42*MIN(Допущения!$D$42,A13-Допущения!$D$38+1),0) -> 40 | N13: =N12*(1-Допущения!$D$45)+M13 -> 59.6 | O13: =L13+N13 -> 1370.9064 | P13: =L13*Допущения!$D$25 -> 327.82661 | Q13: =L13*(1-Допущения!$D$25)+N13 -> 1043.0798 | R13: =MAX(Допущения!$D$18,ROUNDUP(Q13/Допущения!$D$68+P13/Допущения!$D$69,0)) -> 15 | S13: =ROUNDUP(R13/Допущения!$D$48,0) -> 2 | T13: =L13*F13/(1+Допущения!$D$6) -> 3187420.5 | U13: =N13*Допущения!$D$28*E13/(1+Допущения!$D$6) -> 97216.393 | V13: =O13*Допущения!$D$26*Допущения!$D$27/(1+Допущения!$D$6) -> 168554.07 | W13: =T13+U13+V13 -> 3453191 | X13: =J13*Допущения!$D$37 -> 20000 | Y13: =(R13*Допущения!$D$47+S13*Допущения!$D$49)*D13*Допущения!$D$9 -> 1653540 | Z13: =(MAX(0,R13-R12)+R13*Допущения!$D$50/12)*Допущения!$D$51*D13 -> 236250 | AA13: =O13*(Допущения!$D$53+Допущения!$D$54)+(L13*F13+N13*Допущения!$D$28*E13)*Допущения!$D$13 -> 572511.48 | AB13: =(R13+S13)*Допущения!$D$52 -> 45900 | AC13: =SUMPRODUCT(Допущения!$B$84:$B$91,Допущения!$C$84:$C$91,--(Допущения!$D$84:$D$91<=A13))*D13*Допущения!$D$9 -> 1627500 | AD13: =(AC13+Y13)*Допущения!$D$14 -> 328104 | AE13: =Допущения!$D$55+Допущения!$D$56*O13/1000+Допущения!$D$57 -> 150967.25 | AF13: =SUMIF(Допущения!$B$95:$B$103,A13,Допущения!$C$95:$C$103) -> 500000 | AG13: 0 | AH13: =G13+SUM(X13:AG13) -> 5678968.3 | AI13: =W13-AH13 -> -2225777.3 | AJ13: =AJ12+AI13 -> -17322982 | AK13: =O13*Допущения!$D$58*Допущения!$D$59 -> 45239.912 | AL13: =T13*Допущения!$D$72 -> 160710.28 | AM13: =IF(MOD(A13,12)=0,INDEX($F$70:$F$74,B13),0) -> 0 | AN13: =AI13-AM13 -> -2225777.3 | AO13: =1/(1+Допущения!$D$74)^A13 -> 0.87584404 | AP13: =IF(AND(A13>Допущения!$D$19,MIN(AI13:AI$65)>0),A13,"") | AQ13: =IF(MIN(AJ13:AJ$65)>0,A13,"")
A14: 9 | B14: =INT((A14-1)/12)+1 -> 1 | C14: Масштабирование | D14: =(1+Допущения!$D$11)^(B14-1) -> 1 | E14: =(1+Допущения!$D$12)^(B14-1) -> 1 | F14: =Допущения!$D$71*E14 -> 2965.48 | G14: =MIN(G13*(1+Допущения!$D$33),Допущения!$D$34) -> 587731.23 | H14: =MIN(Допущения!$D$30,G14/Допущения!$D$29) -> 300 | I14: =MAX(0,G14-H14*Допущения!$D$29)/Допущения!$D$31 -> 22.955205 | J14: =IF(A14>=Допущения!$D$35,Допущения!$D$36,0) -> 40 | K14: =H14+I14+J14 -> 362.95521 | L14: =(L13-K13)*(1-Допущения!$D$44)+K13*(1-Допущения!$D$43)+K14 -> 1528.0004 | M14: =IF(A14>=Допущения!$D$38,Допущения!$D$73/Допущения!$D$42*MIN(Допущения!$D$42,A14-Допущения!$D$38+1),0) -> 60 | N14: =N13*(1-Допущения!$D$45)+M14 -> 118.408 | O14: =L14+N14 -> 1646.4084 | P14: =L14*Допущения!$D$25 -> 382.0001 | Q14: =L14*(1-Допущения!$D$25)+N14 -> 1264.4083 | R14: =MAX(Допущения!$D$18,ROUNDUP(Q14/Допущения!$D$68+P14/Допущения!$D$69,0)) -> 18 | S14: =ROUNDUP(R14/Допущения!$D$48,0) -> 2 | T14: =L14*F14/(1+Допущения!$D$6) -> 3714143.1 | U14: =N14*Допущения!$D$28*E14/(1+Допущения!$D$6) -> 193140.92 | V14: =O14*Допущения!$D$26*Допущения!$D$27/(1+Допущения!$D$6) -> 202427.26 | W14: =T14+U14+V14 -> 4109711.3 | X14: =J14*Допущения!$D$37 -> 20000 | Y14: =(R14*Допущения!$D$47+S14*Допущения!$D$49)*D14*Допущения!$D$9 -> 1926960 | Z14: =(MAX(0,R14-R13)+R14*Допущения!$D$50/12)*Допущения!$D$51*D14 -> 241500 | AA14: =O14*(Допущения!$D$53+Допущения!$D$54)+(L14*F14+N14*Допущения!$D$28*E14)*Допущения!$D$13 -> 686743.02 | AB14: =(R14+S14)*Допущения!$D$52 -> 54000 | AC14: =SUMPRODUCT(Допущения!$B$84:$B$91,Допущения!$C$84:$C$91,--(Допущения!$D$84:$D$91<=A14))*D14*Допущения!$D$9 -> 1627500 | AD14: =(AC14+Y14)*Допущения!$D$14 -> 355446 | AE14: =Допущения!$D$55+Допущения!$D$56*O14/1000+Допущения!$D$57 -> 153171.27 | AF14: =SUMIF(Допущения!$B$95:$B$103,A14,Допущения!$C$95:$C$103) -> 500000 | AG14: 0 | AH14: =G14+SUM(X14:AG14) -> 6153051.5 | AI14: =W14-AH14 -> -2043340.2 | AJ14: =AJ13+AI14 -> -19366322 | AK14: =O14*Допущения!$D$58*Допущения!$D$59 -> 54331.477 | AL14: =T14*Допущения!$D$72 -> 187267.72 | AM14: =IF(MOD(A14,12)=0,INDEX($F$70:$F$74,B14),0) -> 0 | AN14: =AI14-AM14 -> -2043340.2 | AO14: =1/(1+Допущения!$D$74)^A14 -> 0.8614501 | AP14: =IF(AND(A14>Допущения!$D$19,MIN(AI14:AI$65)>0),A14,"") | AQ14: =IF(MIN(AJ14:AJ$65)>0,A14,"")
A15: 10 | B15: =INT((A15-1)/12)+1 -> 1 | C15: Масштабирование | D15: =(1+Допущения!$D$11)^(B15-1) -> 1 | E15: =(1+Допущения!$D$12)^(B15-1) -> 1 | F15: =Допущения!$D$71*E15 -> 2965.48 | G15: =MIN(G14*(1+Допущения!$D$33),Допущения!$D$34) -> 634749.73 | H15: =MIN(Допущения!$D$30,G15/Допущения!$D$29) -> 300 | I15: =MAX(0,G15-H15*Допущения!$D$29)/Допущения!$D$31 -> 30.791622 | J15: =IF(A15>=Допущения!$D$35,Допущения!$D$36,0) -> 40 | K15: =H15+I15+J15 -> 370.79162 | L15: =(L14-K14)*(1-Допущения!$D$44)+K14*(1-Допущения!$D$43)+K15 -> 1738.1505 | M15: =IF(A15>=Допущения!$D$38,Допущения!$D$73/Допущения!$D$42*MIN(Допущения!$D$42,A15-Допущения!$D$38+1),0) -> 60 | N15: =N14*(1-Допущения!$D$45)+M15 -> 176.03984 | O15: =L15+N15 -> 1914.1903 | P15: =L15*Допущения!$D$25 -> 434.53763 | Q15: =L15*(1-Допущения!$D$25)+N15 -> 1479.6527 | R15: =MAX(Допущения!$D$18,ROUNDUP(Q15/Допущения!$D$68+P15/Допущения!$D$69,0)) -> 20 | S15: =ROUNDUP(R15/Допущения!$D$48,0) -> 2 | T15: =L15*F15/(1+Допущения!$D$6) -> 4224959.5 | U15: =N15*Допущения!$D$28*E15/(1+Допущения!$D$6) -> 287146.95 | V15: =O15*Допущения!$D$26*Допущения!$D$27/(1+Допущения!$D$6) -> 235351.27 | W15: =T15+U15+V15 -> 4747457.7 | X15: =J15*Допущения!$D$37 -> 20000 | Y15: =(R15*Допущения!$D$47+S15*Допущения!$D$49)*D15*Допущения!$D$9 -> 2109240 | Z15: =(MAX(0,R15-R14)+R15*Допущения!$D$50/12)*Допущения!$D$51*D15 -> 175000 | AA15: =O15*(Допущения!$D$53+Допущения!$D$54)+(L15*F15+N15*Допущения!$D$28*E15)*Допущения!$D$13 -> 797765.33 | AB15: =(R15+S15)*Допущения!$D$52 -> 59400 | AC15: =SUMPRODUCT(Допущения!$B$84:$B$91,Допущения!$C$84:$C$91,--(Допущения!$D$84:$D$91<=A15))*D15*Допущения!$D$9 -> 1966020 | AD15: =(AC15+Y15)*Допущения!$D$14 -> 407526 | AE15: =Допущения!$D$55+Допущения!$D$56*O15/1000+Допущения!$D$57 -> 155313.52 | AF15: =SUMIF(Допущения!$B$95:$B$103,A15,Допущения!$C$95:$C$103) -> 350000 | AG15: 0 | AH15: =G15+SUM(X15:AG15) -> 6675014.6 | AI15: =W15-AH15 -> -1927556.9 | AJ15: =AJ14+AI15 -> -21293879 | AK15: =O15*Допущения!$D$58*Допущения!$D$59 -> 63168.281 | AL15: =T15*Допущения!$D$72 -> 213023.17 | AM15: =IF(MOD(A15,12)=0,INDEX($F$70:$F$74,B15),0) -> 0 | AN15: =AI15-AM15 -> -1927556.9 | AO15: =1/(1+Допущения!$D$74)^A15 -> 0.84729272 | AP15: =IF(AND(A15>Допущения!$D$19,MIN(AI15:AI$65)>0),A15,"") | AQ15: =IF(MIN(AJ15:AJ$65)>0,A15,"")
A16: 11 | B16: =INT((A16-1)/12)+1 -> 1 | C16: Масштабирование | D16: =(1+Допущения!$D$11)^(B16-1) -> 1 | E16: =(1+Допущения!$D$12)^(B16-1) -> 1 | F16: =Допущения!$D$71*E16 -> 2965.48 | G16: =MIN(G15*(1+Допущения!$D$33),Допущения!$D$34) -> 685529.71 | H16: =MIN(Допущения!$D$30,G16/Допущения!$D$29) -> 300 | I16: =MAX(0,G16-H16*Допущения!$D$29)/Допущения!$D$31 -> 39.254951 | J16: =IF(A16>=Допущения!$D$35,Допущения!$D$36,0) -> 40 | K16: =H16+I16+J16 -> 379.25495 | L16: =(L15-K15)*(1-Допущения!$D$44)+K15*(1-Допущения!$D$43)+K16 -> 1942.666 | M16: =IF(A16>=Допущения!$D$38,Допущения!$D$73/Допущения!$D$42*MIN(Допущения!$D$42,A16-Допущения!$D$38+1),0) -> 60 | N16: =N15*(1-Допущения!$D$45)+M16 -> 232.51904 | O16: =L16+N16 -> 2175.1851 | P16: =L16*Допущения!$D$25 -> 485.6665 | Q16: =L16*(1-Допущения!$D$25)+N16 -> 1689.5186 | R16: =MAX(Допущения!$D$18,ROUNDUP(Q16/Допущения!$D$68+P16/Допущения!$D$69,0)) -> 23 | S16: =ROUNDUP(R16/Допущения!$D$48,0) -> 2 | T16: =L16*F16/(1+Допущения!$D$6) -> 4722079.7 | U16: =N16*Допущения!$D$28*E16/(1+Допущения!$D$6) -> 379272.87 | V16: =O16*Допущения!$D$26*Допущения!$D$27/(1+Допущения!$D$6) -> 267440.79 | W16: =T16+U16+V16 -> 5368793.3 | X16: =J16*Допущения!$D$37 -> 20000 | Y16: =(R16*Допущения!$D$47+S16*Допущения!$D$49)*D16*Допущения!$D$9 -> 2382660 | Z16: =(MAX(0,R16-R15)+R16*Допущения!$D$50/12)*Допущения!$D$51*D16 -> 250250 | AA16: =O16*(Допущения!$D$53+Допущения!$D$54)+(L16*F16+N16*Допущения!$D$28*E16)*Допущения!$D$13 -> 905968.25 | AB16: =(R16+S16)*Допущения!$D$52 -> 67500 | AC16: =SUMPRODUCT(Допущения!$B$84:$B$91,Допущения!$C$84:$C$91,--(Допущения!$D$84:$D$91<=A16))*D16*Допущения!$D$9 -> 1966020 | AD16: =(AC16+Y16)*Допущения!$D$14 -> 434868 | AE16: =Допущения!$D$55+Допущения!$D$56*O16/1000+Допущения!$D$57 -> 157401.48 | AF16: =SUMIF(Допущения!$B$95:$B$103,A16,Допущения!$C$95:$C$103) -> 350000 | AG16: 0 | AH16: =G16+SUM(X16:AG16) -> 7220197.4 | AI16: =W16-AH16 -> -1851404.1 | AJ16: =AJ15+AI16 -> -23145283 | AK16: =O16*Допущения!$D$58*Допущения!$D$59 -> 71781.107 | AL16: =T16*Допущения!$D$72 -> 238088.05 | AM16: =IF(MOD(A16,12)=0,INDEX($F$70:$F$74,B16),0) -> 0 | AN16: =AI16-AM16 -> -1851404.1 | AO16: =1/(1+Допущения!$D$74)^A16 -> 0.833368 | AP16: =IF(AND(A16>Допущения!$D$19,MIN(AI16:AI$65)>0),A16,"") | AQ16: =IF(MIN(AJ16:AJ$65)>0,A16,"")
A17: 12 | B17: =INT((A17-1)/12)+1 -> 1 | C17: Масштабирование | D17: =(1+Допущения!$D$11)^(B17-1) -> 1 | E17: =(1+Допущения!$D$12)^(B17-1) -> 1 | F17: =Допущения!$D$71*E17 -> 2965.48 | G17: =MIN(G16*(1+Допущения!$D$33),Допущения!$D$34) -> 740372.08 | H17: =MIN(Допущения!$D$30,G17/Допущения!$D$29) -> 300 | I17: =MAX(0,G17-H17*Допущения!$D$29)/Допущения!$D$31 -> 48.395347 | J17: =IF(A17>=Допущения!$D$35,Допущения!$D$36,0) -> 40 | K17: =H17+I17+J17 -> 388.39535 | L17: =(L16-K16)*(1-Допущения!$D$44)+K16*(1-Допущения!$D$43)+K17 -> 2142.443 | M17: =IF(A17>=Допущения!$D$38,Допущения!$D$73/Допущения!$D$42*MIN(Допущения!$D$42,A17-Допущения!$D$38+1),0) -> 60 | N17: =N16*(1-Допущения!$D$45)+M17 -> 287.86866 | O17: =L17+N17 -> 2430.3116 | P17: =L17*Допущения!$D$25 -> 535.61074 | Q17: =L17*(1-Допущения!$D$25)+N17 -> 1894.7009 | R17: =MAX(Допущения!$D$18,ROUNDUP(Q17/Допущения!$D$68+P17/Допущения!$D$69,0)) -> 26 | S17: =ROUNDUP(R17/Допущения!$D$48,0) -> 3 | T17: =L17*F17/(1+Допущения!$D$6) -> 5207681.8 | U17: =N17*Допущения!$D$28*E17/(1+Допущения!$D$6) -> 469556.26 | V17: =O17*Допущения!$D$26*Допущения!$D$27/(1+Допущения!$D$6) -> 298808.81 | W17: =T17+U17+V17 -> 5976046.8 | X17: =J17*Допущения!$D$37 -> 20000 | Y17: =(R17*Допущения!$D$47+S17*Допущения!$D$49)*D17*Допущения!$D$9 -> 2799300 | Z17: =(MAX(0,R17-R16)+R17*Допущения!$D$50/12)*Допущения!$D$51*D17 -> 255500 | AA17: =O17*(Допущения!$D$53+Допущения!$D$54)+(L17*F17+N17*Допущения!$D$28*E17)*Допущения!$D$13 -> 1011735.9 | AB17: =(R17+S17)*Допущения!$D$52 -> 78300 | AC17: =SUMPRODUCT(Допущения!$B$84:$B$91,Допущения!$C$84:$C$91,--(Допущения!$D$84:$D$91<=A17))*D17*Допущения!$D$9 -> 1966020 | AD17: =(AC17+Y17)*Допущения!$D$14 -> 476532 | AE17: =Допущения!$D$55+Допущения!$D$56*O17/1000+Допущения!$D$57 -> 159442.49 | AF17: =SUMIF(Допущения!$B$95:$B$103,A17,Допущения!$C$95:$C$103) -> 300000 | AG17: 0 | AH17: =G17+SUM(X17:AG17) -> 7807202.5 | AI17: =W17-AH17 -> -1831155.6 | AJ17: =AJ16+AI17 -> -24976439 | AK17: =O17*Допущения!$D$58*Допущения!$D$59 -> 80200.284 | AL17: =T17*Допущения!$D$72 -> 262572.19 | AM17: =IF(MOD(A17,12)=0,INDEX($F$70:$F$74,B17),0) -> 0 | AN17: =AI17-AM17 -> -1831155.6 | AO17: =1/(1+Допущения!$D$74)^A17 -> 0.81967213 | AP17: =IF(AND(A17>Допущения!$D$19,MIN(AI17:AI$65)>0),A17,"") | AQ17: =IF(MIN(AJ17:AJ$65)>0,A17,"")
A18: 13 | B18: =INT((A18-1)/12)+1 -> 2 | C18: Масштабирование | D18: =(1+Допущения!$D$11)^(B18-1) -> 1.08 | E18: =(1+Допущения!$D$12)^(B18-1) -> 1.07 | F18: =Допущения!$D$71*E18 -> 3173.0636 | G18: =MIN(G17*(1+Допущения!$D$33),Допущения!$D$34) -> 799601.85 | H18: =MIN(Допущения!$D$30,G18/Допущения!$D$29) -> 300 | I18: =MAX(0,G18-H18*Допущения!$D$29)/Допущения!$D$31 -> 58.266975 | J18: =IF(A18>=Допущения!$D$35,Допущения!$D$36,0) -> 40 | K18: =H18+I18+J18 -> 398.26698 | L18: =(L17-K17)*(1-Допущения!$D$44)+K17*(1-Допущения!$D$43)+K18 -> 2338.3682 | M18: =IF(A18>=Допущения!$D$38,Допущения!$D$73/Допущения!$D$42*MIN(Допущения!$D$42,A18-Допущения!$D$38+1),0) -> 60 | N18: =N17*(1-Допущения!$D$45)+M18 -> 342.11129 | O18: =L18+N18 -> 2680.4795 | P18: =L18*Допущения!$D$25 -> 584.59206 | Q18: =L18*(1-Допущения!$D$25)+N18 -> 2095.8875 | R18: =MAX(Допущения!$D$18,ROUNDUP(Q18/Допущения!$D$68+P18/Допущения!$D$69,0)) -> 28 | S18: =ROUNDUP(R18/Допущения!$D$48,0) -> 3 | T18: =L18*F18/(1+Допущения!$D$6) -> 6081796 | U18: =N18*Допущения!$D$28*E18/(1+Допущения!$D$6) -> 597096.37 | V18: =O18*Допущения!$D$26*Допущения!$D$27/(1+Допущения!$D$6) -> 329567.16 | W18: =T18+U18+V18 -> 7008459.6 | X18: =J18*Допущения!$D$37 -> 20000 | Y18: =(R18*Допущения!$D$47+S18*Допущения!$D$49)*D18*Допущения!$D$9 -> 3220106.4 | Z18: =(MAX(0,R18-R17)+R18*Допущения!$D$50/12)*Допущения!$D$51*D18 -> 204120 | AA18: =O18*(Допущения!$D$53+Допущения!$D$54)+(L18*F18+N18*Допущения!$D$28*E18)*Допущения!$D$13 -> 1125043.5 | AB18: =(R18+S18)*Допущения!$D$52 -> 83700 | AC18: =SUMPRODUCT(Допущения!$B$84:$B$91,Допущения!$C$84:$C$91,--(Допущения!$D$84:$D$91<=A18))*D18*Допущения!$D$9 -> 2123301.6 | AD18: =(AC18+Y18)*Допущения!$D$14 -> 534340.8 | AE18: =Допущения!$D$55+Допущения!$D$56*O18/1000+Допущения!$D$57 -> 161443.84 | AF18: =SUMIF(Допущения!$B$95:$B$103,A18,Допущения!$C$95:$C$103) -> 0 | AG18: 0 | AH18: =G18+SUM(X18:AG18) -> 8271658 | AI18: =W18-AH18 -> -1263198.4 | AJ18: =AJ17+AI18 -> -26239637 | AK18: =O18*Допущения!$D$58*Допущения!$D$59 -> 88455.825 | AL18: =T18*Допущения!$D$72 -> 306645.18 | AM18: =IF(MOD(A18,12)=0,INDEX($F$70:$F$74,B18),0) -> 0 | AN18: =AI18-AM18 -> -1263198.4 | AO18: =1/(1+Допущения!$D$74)^A18 -> 0.80620134 | AP18: =IF(AND(A18>Допущения!$D$19,MIN(AI18:AI$65)>0),A18,"") | AQ18: =IF(MIN(AJ18:AJ$65)>0,A18,"")
A19: 14 | B19: =INT((A19-1)/12)+1 -> 2 | C19: Масштабирование | D19: =(1+Допущения!$D$11)^(B19-1) -> 1.08 | E19: =(1+Допущения!$D$12)^(B19-1) -> 1.07 | F19: =Допущения!$D$71*E19 -> 3173.0636 | G19: =MIN(G18*(1+Допущения!$D$33),Допущения!$D$34) -> 863570 | H19: =MIN(Допущения!$D$30,G19/Допущения!$D$29) -> 300 | I19: =MAX(0,G19-H19*Допущения!$D$29)/Допущения!$D$31 -> 68.928333 | J19: =IF(A19>=Допущения!$D$35,Допущения!$D$36,0) -> 40 | K19: =H19+I19+J19 -> 408.92833 | L19: =(L18-K18)*(1-Допущения!$D$44)+K18*(1-Допущения!$D$43)+K19 -> 2531.3238 | M19: =IF(A19>=Допущения!$D$38,Допущения!$D$73/Допущения!$D$42*MIN(Допущения!$D$42,A19-Допущения!$D$38+1),0) -> 60 | N19: =N18*(1-Допущения!$D$45)+M19 -> 395.26906 | O19: =L19+N19 -> 2926.5928 | P19: =L19*Допущения!$D$25 -> 632.83094 | Q19: =L19*(1-Допущения!$D$25)+N19 -> 2293.7619 | R19: =MAX(Допущения!$D$18,ROUNDUP(Q19/Допущения!$D$68+P19/Допущения!$D$69,0)) -> 31 | S19: =ROUNDUP(R19/Допущения!$D$48,0) -> 3 | T19: =L19*F19/(1+Допущения!$D$6) -> 6583648.6 | U19: =N19*Допущения!$D$28*E19/(1+Допущения!$D$6) -> 689874.11 | V19: =O19*Допущения!$D$26*Допущения!$D$27/(1+Допущения!$D$6) -> 359826.99 | W19: =T19+U19+V19 -> 7633349.7 | X19: =J19*Допущения!$D$37 -> 20000 | Y19: =(R19*Допущения!$D$47+S19*Допущения!$D$49)*D19*Допущения!$D$9 -> 3515400 | Z19: =(MAX(0,R19-R18)+R19*Допущения!$D$50/12)*Допущения!$D$51*D19 -> 285390 | AA19: =O19*(Допущения!$D$53+Допущения!$D$54)+(L19*F19+N19*Допущения!$D$28*E19)*Допущения!$D$13 -> 1227932.9 | AB19: =(R19+S19)*Допущения!$D$52 -> 91800 | AC19: =SUMPRODUCT(Допущения!$B$84:$B$91,Допущения!$C$84:$C$91,--(Допущения!$D$84:$D$91<=A19))*D19*Допущения!$D$9 -> 2123301.6 | AD19: =(AC19+Y19)*Допущения!$D$14 -> 563870.16 | AE19: =Допущения!$D$55+Допущения!$D$56*O19/1000+Допущения!$D$57 -> 163412.74 | AF19: =SUMIF(Допущения!$B$95:$B$103,A19,Допущения!$C$95:$C$103) -> 0 | AG19: 0 | AH19: =G19+SUM(X19:AG19) -> 8854677.4 | AI19: =W19-AH19 -> -1221327.8 | AJ19: =AJ18+AI19 -> -27460965 | AK19: =O19*Допущения!$D$58*Допущения!$D$59 -> 96577.563 | AL19: =T19*Допущения!$D$72 -> 331948.67 | AM19: =IF(MOD(A19,12)=0,INDEX($F$70:$F$74,B19),0) -> 0 | AN19: =AI19-AM19 -> -1221327.8 | AO19: =1/(1+Допущения!$D$74)^A19 -> 0.79295194 | AP19: =IF(AND(A19>Допущения!$D$19,MIN(AI19:AI$65)>0),A19,"") | AQ19: =IF(MIN(AJ19:AJ$65)>0,A19,"")
A20: 15 | B20: =INT((A20-1)/12)+1 -> 2 | C20: Масштабирование | D20: =(1+Допущения!$D$11)^(B20-1) -> 1.08 | E20: =(1+Допущения!$D$12)^(B20-1) -> 1.07 | F20: =Допущения!$D$71*E20 -> 3173.0636 | G20: =MIN(G19*(1+Допущения!$D$33),Допущения!$D$34) -> 932655.6 | H20: =MIN(Допущения!$D$30,G20/Допущения!$D$29) -> 300 | I20: =MAX(0,G20-H20*Допущения!$D$29)/Допущения!$D$31 -> 80.4426 | J20: =IF(A20>=Допущения!$D$35,Допущения!$D$36,0) -> 40 | K20: =H20+I20+J20 -> 420.4426 | L20: =(L19-K19)*(1-Допущения!$D$44)+K19*(1-Допущения!$D$43)+K20 -> 2722.1905 | M20: =IF(A20>=Допущения!$D$38,Допущения!$D$73/Допущения!$D$42*MIN(Допущения!$D$42,A20-Допущения!$D$38+1),0) -> 60 | N20: =N19*(1-Допущения!$D$45)+M20 -> 447.36368 | O20: =L20+N20 -> 3169.5542 | P20: =L20*Допущения!$D$25 -> 680.54764 | Q20: =L20*(1-Допущения!$D$25)+N20 -> 2489.0066 | R20: =MAX(Допущения!$D$18,ROUNDUP(Q20/Допущения!$D$68+P20/Допущения!$D$69,0)) -> 33 | S20: =ROUNDUP(R20/Допущения!$D$48,0) -> 3 | T20: =L20*F20/(1+Допущения!$D$6) -> 7080068.6 | U20: =N20*Допущения!$D$28*E20/(1+Допущения!$D$6) -> 780796.3 | V20: =O20*Допущения!$D$26*Допущения!$D$27/(1+Допущения!$D$6) -> 389699.29 | W20: =T20+U20+V20 -> 8250564.2 | X20: =J20*Допущения!$D$37 -> 20000 | Y20: =(R20*Допущения!$D$47+S20*Допущения!$D$49)*D20*Допущения!$D$9 -> 3712262.4 | Z20: =(MAX(0,R20-R19)+R20*Допущения!$D$50/12)*Допущения!$D$51*D20 -> 213570 | AA20: =O20*(Допущения!$D$53+Допущения!$D$54)+(L20*F20+N20*Допущения!$D$28*E20)*Допущения!$D$13 -> 1329511.9 | AB20: =(R20+S20)*Допущения!$D$52 -> 97200 | AC20: =SUMPRODUCT(Допущения!$B$84:$B$91,Допущения!$C$84:$C$91,--(Допущения!$D$84:$D$91<=A20))*D20*Допущения!$D$9 -> 2123301.6 | AD20: =(AC20+Y20)*Допущения!$D$14 -> 583556.4 | AE20: =Допущения!$D$55+Допущения!$D$56*O20/1000+Допущения!$D$57 -> 165356.43 | AF20: =SUMIF(Допущения!$B$95:$B$103,A20,Допущения!$C$95:$C$103) -> 0 | AG20: 0 | AH20: =G20+SUM(X20:AG20) -> 9177414.3 | AI20: =W20-AH20 -> -926850.09 | AJ20: =AJ19+AI20 -> -28387815 | AK20: =O20*Допущения!$D$58*Допущения!$D$59 -> 104595.29 | AL20: =T20*Допущения!$D$72 -> 356978.25 | AM20: =IF(MOD(A20,12)=0,INDEX($F$70:$F$74,B20),0) -> 0 | AN20: =AI20-AM20 -> -926850.09 | AO20: =1/(1+Допущения!$D$74)^A20 -> 0.77992028 | AP20: =IF(AND(A20>Допущения!$D$19,MIN(AI20:AI$65)>0),A20,"") | AQ20: =IF(MIN(AJ20:AJ$65)>0,A20,"")
A21: 16 | B21: =INT((A21-1)/12)+1 -> 2 | C21: Масштабирование | D21: =(1+Допущения!$D$11)^(B21-1) -> 1.08 | E21: =(1+Допущения!$D$12)^(B21-1) -> 1.07 | F21: =Допущения!$D$71*E21 -> 3173.0636 | G21: =MIN(G20*(1+Допущения!$D$33),Допущения!$D$34) -> 1007268 | H21: =MIN(Допущения!$D$30,G21/Допущения!$D$29) -> 300 | I21: =MAX(0,G21-H21*Допущения!$D$29)/Допущения!$D$31 -> 92.878008 | J21: =IF(A21>=Допущения!$D$35,Допущения!$D$36,0) -> 40 | K21: =H21+I21+J21 -> 432.87801 | L21: =(L20-K20)*(1-Допущения!$D$44)+K20*(1-Допущения!$D$43)+K21 -> 2911.853 | M21: =IF(A21>=Допущения!$D$38,Допущения!$D$73/Допущения!$D$42*MIN(Допущения!$D$42,A21-Допущения!$D$38+1),0) -> 60 | N21: =N20*(1-Допущения!$D$45)+M21 -> 498.41641 | O21: =L21+N21 -> 3410.2694 | P21: =L21*Допущения!$D$25 -> 727.96326 | Q21: =L21*(1-Допущения!$D$25)+N21 -> 2682.3062 | R21: =MAX(Допущения!$D$18,ROUNDUP(Q21/Допущения!$D$68+P21/Допущения!$D$69,0)) -> 36 | S21: =ROUNDUP(R21/Допущения!$D$48,0) -> 3 | T21: =L21*F21/(1+Допущения!$D$6) -> 7573356.4 | U21: =N21*Допущения!$D$28*E21/(1+Допущения!$D$6) -> 869900.05 | V21: =O21*Допущения!$D$26*Допущения!$D$27/(1+Допущения!$D$6) -> 419295.42 | W21: =T21+U21+V21 -> 8862551.9 | X21: =J21*Допущения!$D$37 -> 20000 | Y21: =(R21*Допущения!$D$47+S21*Допущения!$D$49)*D21*Допущения!$D$9 -> 4007556 | Z21: =(MAX(0,R21-R20)+R21*Допущения!$D$50/12)*Допущения!$D$51*D21 -> 294840 | AA21: =O21*(Допущения!$D$53+Допущения!$D$54)+(L21*F21+N21*Допущения!$D$28*E21)*Допущения!$D$13 -> 1430162.3 | AB21: =(R21+S21)*Допущения!$D$52 -> 105300 | AC21: =SUMPRODUCT(Допущения!$B$84:$B$91,Допущения!$C$84:$C$91,--(Допущения!$D$84:$D$91<=A21))*D21*Допущения!$D$9 -> 2123301.6 | AD21: =(AC21+Y21)*Допущения!$D$14 -> 613085.76 | AE21: =Допущения!$D$55+Допущения!$D$56*O21/1000+Допущения!$D$57 -> 167282.16 | AF21: =SUMIF(Допущения!$B$95:$B$103,A21,Допущения!$C$95:$C$103) -> 0 | AG21: 0 | AH21: =G21+SUM(X21:AG21) -> 9768795.8 | AI21: =W21-AH21 -> -906243.91 | AJ21: =AJ20+AI21 -> -29294059 | AK21: =O21*Допущения!$D$58*Допущения!$D$59 -> 112538.89 | AL21: =T21*Допущения!$D$72 -> 381849.9 | AM21: =IF(MOD(A21,12)=0,INDEX($F$70:$F$74,B21),0) -> 0 | AN21: =AI21-AM21 -> -906243.91 | AO21: =1/(1+Допущения!$D$74)^A21 -> 0.76710278 | AP21: =IF(AND(A21>Допущения!$D$19,MIN(AI21:AI$65)>0),A21,"") | AQ21: =IF(MIN(AJ21:AJ$65)>0,A21,"")
... A65: 60 | B65: =INT((A65-1)/12)+1 -> 5 | C65: Масштабирование | D65: =(1+Допущения!$D$11)^(B65-1) -> 1.360489 | E65: =(1+Допущения!$D$12)^(B65-1) -> 1.310796 | F65: =Допущения!$D$71*E65 -> 3887.1394 | G65: =MIN(G64*(1+Допущения!$D$33),Допущения!$D$34) -> 2500000 | H65: =MIN(Допущения!$D$30,G65/Допущения!$D$29) -> 300 | I65: =MAX(0,G65-H65*Допущения!$D$29)/Допущения!$D$31 -> 341.66667 | J65: =IF(A65>=Допущения!$D$35,Допущения!$D$36,0) -> 40 | K65: =H65+I65+J65 -> 681.66667 | L65: =(L64-K64)*(1-Допущения!$D$44)+K64*(1-Допущения!$D$43)+K65 -> 8682.2156 | M65: =IF(A65>=Допущения!$D$38,Допущения!$D$73/Допущения!$D$42*MIN(Допущения!$D$42,A65-Допущения!$D$38+1),0) -> 60 | N65: =N64*(1-Допущения!$D$45)+M65 -> 1971.5993 | O65: =L65+N65 -> 10653.815 | P65: =L65*Допущения!$D$25 -> 2170.5539 | Q65: =L65*(1-Допущения!$D$25)+N65 -> 8483.2611 | R65: =MAX(Допущения!$D$18,ROUNDUP(Q65/Допущения!$D$68+P65/Допущения!$D$69,0)) -> 109 | S65: =ROUNDUP(R65/Допущения!$D$48,0) -> 10 | T65: =L65*F65/(1+Допущения!$D$6) -> 27663100 | U65: =N65*Допущения!$D$28*E65/(1+Допущения!$D$6) -> 4215479.9 | V65: =O65*Допущения!$D$26*Допущения!$D$27/(1+Допущения!$D$6) -> 1309895.3 | W65: =T65+U65+V65 -> 33188475 | X65: =J65*Допущения!$D$37 -> 20000 | Y65: =(R65*Допущения!$D$47+S65*Допущения!$D$49)*D65*Допущения!$D$9 -> 15463943 | Z65: =(MAX(0,R65-R64)+R65*Допущения!$D$50/12)*Допущения!$D$51*D65 -> 354747.5 | AA65: =O65*(Допущения!$D$53+Допущения!$D$54)+(L65*F65+N65*Допущения!$D$28*E65)*Допущения!$D$13 -> 4588696.1 | AB65: =(R65+S65)*Допущения!$D$52 -> 321300 | AC65: =SUMPRODUCT(Допущения!$B$84:$B$91,Допущения!$C$84:$C$91,--(Допущения!$D$84:$D$91<=A65))*D65*Допущения!$D$9 -> 2674748.5 | AD65: =(AC65+Y65)*Допущения!$D$14 -> 1813869.2 | AE65: =Допущения!$D$55+Допущения!$D$56*O65/1000+Допущения!$D$57 -> 225230.52 | AF65: =SUMIF(Допущения!$B$95:$B$103,A65,Допущения!$C$95:$C$103) -> 0 | AG65: 0 | AH65: =G65+SUM(X65:AG65) -> 27962535 | AI65: =W65-AH65 -> 5225940 | AJ65: =AJ64+AI65 -> 81114294 | AK65: =O65*Допущения!$D$58*Допущения!$D$59 -> 351575.89 | AL65: =T65*Допущения!$D$72 -> 1394778.2 | AM65: =IF(MOD(A65,12)=0,INDEX($F$70:$F$74,B65),0) -> 13697558 | AN65: =AI65-AM65 -> -8471617.5 | AO65: =1/(1+Допущения!$D$74)^A65 -> 0.36999925 | AP65: =IF(AND(A65>Допущения!$D$19,MIN(AI65:AI$65)>0),A65,"") -> 60 | AQ65: =IF(MIN(AJ65:AJ$65)>0,A65,"") -> 60
A68: Годовые итоги и налог на прибыль с переносом убытков
A69: Год | B69: Выручка, руб. | C69: Операционный результат, руб. | D69: Убыток к переносу на начало, руб. | E69: Зачтено убытка, руб. | F69: Налог на прибыль, руб. | G69: Убыток к переносу на конец, руб. | H69: Кросс-продажи, руб.
A70: 1 | B70: =SUMIF($B$6:$B$65,A70,$W$6:$W$65) -> 31496602 | C70: =SUMIF($B$6:$B$65,A70,$AI$6:$AI$65) -> -24976439 | D70: 0 | E70: =IF(C70>0,MIN(D70,C70*Допущения!$D$8),0) -> 0 | F70: =IF(C70>0,(C70-E70)*Допущения!$D$7,0) -> 0 | G70: =D70+IF(C70<0,-C70,0)-E70 -> 24976439 | H70: =SUMIF($B$6:$B$65,A70,$AK$6:$AK$65) -> 412171.64
A71: 2 | B71: =SUMIF($B$6:$B$65,A71,$W$6:$W$65) -> 1.2489503e+08 | C71: =SUMIF($B$6:$B$65,A71,$AI$6:$AI$65) -> -7556528.9 | D71: =G70 -> 24976439 | E71: =IF(C71>0,MIN(D71,C71*Допущения!$D$8),0) -> 0 | F71: =IF(C71>0,(C71-E71)*Допущения!$D$7,0) -> 0 | G71: =D71+IF(C71<0,-C71,0)-E71 -> 32532968 | H71: =SUMIF($B$6:$B$65,A71,$AK$6:$AK$65) -> 1589743.4
A72: 3 | B72: =SUMIF($B$6:$B$65,A72,$W$6:$W$65) -> 2.3287691e+08 | C72: =SUMIF($B$6:$B$65,A72,$AI$6:$AI$65) -> 12184223 | D72: =G71 -> 32532968 | E72: =IF(C72>0,MIN(D72,C72*Допущения!$D$8),0) -> 6092111.7 | F72: =IF(C72>0,(C72-E72)*Допущения!$D$7,0) -> 1523027.9 | G72: =D72+IF(C72<0,-C72,0)-E72 -> 26440856 | H72: =SUMIF($B$6:$B$65,A72,$AK$6:$AK$65) -> 2785470.1
A73: 4 | B73: =SUMIF($B$6:$B$65,A73,$W$6:$W$65) -> 3.2292213e+08 | C73: =SUMIF($B$6:$B$65,A73,$AI$6:$AI$65) -> 40463904 | D73: =G72 -> 26440856 | E73: =IF(C73>0,MIN(D73,C73*Допущения!$D$8),0) -> 20231952 | F73: =IF(C73>0,(C73-E73)*Допущения!$D$7,0) -> 5057988 | G73: =D73+IF(C73<0,-C73,0)-E73 -> 6208904.3 | H73: =SUMIF($B$6:$B$65,A73,$AK$6:$AK$65) -> 3628427.8
A74: 5 | B74: =SUMIF($B$6:$B$65,A74,$W$6:$W$65) -> 3.8586421e+08 | C74: =SUMIF($B$6:$B$65,A74,$AI$6:$AI$65) -> 60999135 | D74: =G73 -> 6208904.3 | E74: =IF(C74>0,MIN(D74,C74*Допущения!$D$8),0) -> 6208904.3 | F74: =IF(C74>0,(C74-E74)*Допущения!$D$7,0) -> 13697558 | G74: =D74+IF(C74<0,-C74,0)-E74 -> 0 | H74: =SUMIF($B$6:$B$65,A74,$AK$6:$AK$65) -> 4079768.4
A75: Итого | B75: =SUM(B70:B74) -> 1.0980549e+09 | C75: =SUM(C70:C74) -> 81114294 | F75: =SUM(F70:F74) -> 20278573 | H75: =SUM(H70:H74) -> 12495581

Sheet Оптимистичный
A1: Помесячный расчет: сценарий «Оптимистичный»
A2: Суммы в рублях без НДС. Месяцы 1-3: MVP. Налог на прибыль начисляется в последнем месяце года.
A5: Месяц | B5: Год | C5: Фаза | D5: Индекс зарплат | E5: Индекс цен | F5: Средний чек B2C с НДС, руб. | G5: Маркетинг, руб. | H5: Новые семьи: внутренние каналы | I5: Новые семьи: внешние каналы | J5: Новые семьи: канал фонда «Защитники Отечества» | K5: Новые семьи B2C | L5: Семьи B2C | M5: Приток B2B2C | N5: Семьи B2B2C | O5: Всего семей | P5: Семьи «Расши-ренный» | Q5: Семьи «Базовый» и B2B2C | R5: Координа-торы, чел. | S5: Супер-визоры, чел. | T5: Выручка: подписка B2C, руб. | U5: Выручка: B2B2C, руб. | V5: Выручка: комиссия партнеров, руб. | W5: Выручка всего, руб. | X5: Партнерский канал фонда, руб. | Y5: ФОТ координаторов и супервизоров, руб. | Z5: Обучение новых координаторов, руб. | AA5: Переменные расходы на семьи, руб. | AB5: Рабочие места, руб. | AC5: Постоянная команда, руб. | AD5: Накладные, руб. | AE5: Размещение и юрлицо, руб. | AF5: Инвестиции, руб. | AG5: Бюджет MVP, руб. | AH5: Расходы всего, руб. | AI5: Операционный результат, руб. | AJ5: Накопленный результат, руб. | AK5: Кросс-продажи (эффект группы), руб. | AL5: Льготы ветеранам: недополученная выручка, руб. | AM5: Налог на прибыль, руб. | AN5: Денежный поток после налога, руб. | AO5: Коэффициент дисконтирования | AP5: Признак безубыточности (месяц) | AQ5: Признак окупаемости (месяц)
A6: 1 | B6: =INT((A6-1)/12)+1 -> 1 | C6: MVP | D6: =(1+Допущения!$E$11)^(B6-1) -> 1 | E6: =(1+Допущения!$E$12)^(B6-1) -> 1 | F6: =Допущения!$E$71*E6 -> 3084.48 | G6: 0 | H6: 0 | I6: 0 | J6: 0 | K6: =Допущения!$B$78-0 -> 0 | L6: =Допущения!$B$78 -> 0 | M6: 0 | N6: 0 | O6: =L6+N6 -> 0 | P6: =L6*Допущения!$E$25 -> 0 | Q6: =L6*(1-Допущения!$E$25)+N6 -> 0 | R6: =IF(A6>1,Допущения!$E$18,0) -> 0 | S6: 0 | T6: =L6*Допущения!$E$60*F6/(1+Допущения!$E$6) -> 0 | U6: =N6*Допущения!$E$28*E6/(1+Допущения!$E$6) -> 0 | V6: =O6*Допущения!$E$26*Допущения!$E$27/(1+Допущения!$E$6) -> 0 | W6: =T6+U6+V6 -> 0 | X6: 0 | Y6: 0 | Z6: 0 | AA6: 0 | AB6: 0 | AC6: 0 | AD6: 0 | AE6: 0 | AF6: 0 | AG6: ='Бюджет MVP'!$G$33/Допущения!$E$19 -> 1624654.7 | AH6: =G6+SUM(X6:AG6) -> 1624654.7 | AI6: =W6-AH6 -> -1624654.7 | AJ6: =AI6 -> -1624654.7 | AK6: 0 | AL6: =T6*Допущения!$E$72 -> 0 | AM6: =IF(MOD(A6,12)=0,INDEX($F$70:$F$74,B6),0) -> 0 | AN6: =AI6-AM6 -> -1624654.7 | AO6: =1/(1+Допущения!$E$74)^A6 -> 0.98356564 | AP6: =IF(AND(A6>Допущения!$E$19,MIN(AI6:AI$65)>0),A6,"") | AQ6: =IF(MIN(AJ6:AJ$65)>0,A6,"")
A7: 2 | B7: =INT((A7-1)/12)+1 -> 1 | C7: MVP | D7: =(1+Допущения!$E$11)^(B7-1) -> 1 | E7: =(1+Допущения!$E$12)^(B7-1) -> 1 | F7: =Допущения!$E$71*E7 -> 3084.48 | G7: 0 | H7: 0 | I7: 0 | J7: 0 | K7: =Допущения!$B$79-Допущения!$B$78 -> 50 | L7: =Допущения!$B$79 -> 50 | M7: 0 | N7: 0 | O7: =L7+N7 -> 50 | P7: =L7*Допущения!$E$25 -> 15 | Q7: =L7*(1-Допущения!$E$25)+N7 -> 35 | R7: =IF(A7>1,Допущения!$E$18,0) -> 3 | S7: 0 | T7: =L7*Допущения!$E$60*F7/(1+Допущения!$E$6) -> 75847.869 | U7: =N7*Допущения!$E$28*E7/(1+Допущения!$E$6) -> 0 | V7: =O7*Допущения!$E$26*Допущения!$E$27/(1+Допущения!$E$6) -> 6147.541 | W7: =T7+U7+V7 -> 81995.41 | X7: 0 | Y7: 0 | Z7: 0 | AA7: 0 | AB7: 0 | AC7: 0 | AD7: 0 | AE7: 0 | AF7: 0 | AG7: ='Бюджет MVP'!$G$33/Допущения!$E$19 -> 1624654.7 | AH7: =G7+SUM(X7:AG7) -> 1624654.7 | AI7: =W7-AH7 -> -1542659.3 | AJ7: =AJ6+AI7 -> -3167313.9 | AK7: 0 | AL7: =T7*Допущения!$E$72 -> 3824.2623 | AM7: =IF(MOD(A7,12)=0,INDEX($F$70:$F$74,B7),0) -> 0 | AN7: =AI7-AM7 -> -1542659.3 | AO7: =1/(1+Допущения!$E$74)^A7 -> 0.96740136 | AP7: =IF(AND(A7>Допущения!$E$19,MIN(AI7:AI$65)>0),A7,"") | AQ7: =IF(MIN(AJ7:AJ$65)>0,A7,"")
A8: 3 | B8: =INT((A8-1)/12)+1 -> 1 | C8: MVP | D8: =(1+Допущения!$E$11)^(B8-1) -> 1 | E8: =(1+Допущения!$E$12)^(B8-1) -> 1 | F8: =Допущения!$E$71*E8 -> 3084.48 | G8: 0 | H8: 0 | I8: 0 | J8: 0 | K8: =Допущения!$B$80-Допущения!$B$79 -> 100 | L8: =Допущения!$B$80 -> 150 | M8: 0 | N8: 0 | O8: =L8+N8 -> 150 | P8: =L8*Допущения!$E$25 -> 45 | Q8: =L8*(1-Допущения!$E$25)+N8 -> 105 | R8: =IF(A8>1,Допущения!$E$18,0) -> 3 | S8: 0 | T8: =L8*Допущения!$E$60*F8/(1+Допущения!$E$6) -> 227543.61 | U8: =N8*Допущения!$E$28*E8/(1+Допущения!$E$6) -> 0 | V8: =O8*Допущения!$E$26*Допущения!$E$27/(1+Допущения!$E$6) -> 18442.623 | W8: =T8+U8+V8 -> 245986.23 | X8: 0 | Y8: 0 | Z8: 0 | AA8: 0 | AB8: 0 | AC8: 0 | AD8: 0 | AE8: 0 | AF8: 0 | AG8: ='Бюджет MVP'!$G$33/Допущения!$E$19 -> 1624654.7 | AH8: =G8+SUM(X8:AG8) -> 1624654.7 | AI8: =W8-AH8 -> -1378668.4 | AJ8: =AJ7+AI8 -> -4545982.4 | AK8: 0 | AL8: =T8*Допущения!$E$72 -> 11472.787 | AM8: =IF(MOD(A8,12)=0,INDEX($F$70:$F$74,B8),0) -> 0 | AN8: =AI8-AM8 -> -1378668.4 | AO8: =1/(1+Допущения!$E$74)^A8 -> 0.95150274 | AP8: =IF(AND(A8>Допущения!$E$19,MIN(AI8:AI$65)>0),A8,"") | AQ8: =IF(MIN(AJ8:AJ$65)>0,A8,"")
A9: 4 | B9: =INT((A9-1)/12)+1 -> 1 | C9: Масштабирование | D9: =(1+Допущения!$E$11)^(B9-1) -> 1 | E9: =(1+Допущения!$E$12)^(B9-1) -> 1 | F9: =Допущения!$E$71*E9 -> 3084.48 | G9: =Допущения!$E$32 -> 400000 | H9: =MIN(Допущения!$E$30,G9/Допущения!$E$29) -> 266.66667 | I9: =MAX(0,G9-H9*Допущения!$E$29)/Допущения!$E$31 -> 0 | J9: =IF(A9>=Допущения!$E$35,Допущения!$E$36,0) -> 0 | K9: =H9+I9+J9 -> 266.66667 | L9: =(L8-K8)*(1-Допущения!$E$44)+K8*(1-Допущения!$E$43)+K9 -> 396.41667 | M9: =IF(A9>=Допущения!$E$38,Допущения!$E$73/Допущения!$E$42*MIN(Допущения!$E$42,A9-Допущения!$E$38+1),0) -> 0 | N9: =N8*(1-Допущения!$E$45)+M9 -> 0 | O9: =L9+N9 -> 396.41667 | P9: =L9*Допущения!$E$25 -> 118.925 | Q9: =L9*(1-Допущения!$E$25)+N9 -> 277.49167 | R9: =MAX(Допущения!$E$18,ROUNDUP(Q9/Допущения!$E$68+P9/Допущения!$E$69,0)) -> 4 | S9: =ROUNDUP(R9/Допущения!$E$48,0) -> 1 | T9: =L9*F9/(1+Допущения!$E$6) -> 1002245.3 | U9: =N9*Допущения!$E$28*E9/(1+Допущения!$E$6) -> 0 | V9: =O9*Допущения!$E$26*Допущения!$E$27/(1+Допущения!$E$6) -> 48739.754 | W9: =T9+U9+V9 -> 1050985.1 | X9: =J9*Допущения!$E$37 -> 0 | Y9: =(R9*Допущения!$E$47+S9*Допущения!$E$49)*D9*Допущения!$E$9 -> 481740 | Z9: =(MAX(0,R9-R8)+R9*Допущения!$E$50/12)*Допущения!$E$51*D9 -> 77000 | AA9: =O9*(Допущения!$E$53+Допущения!$E$54)+(L9*F9+N9*Допущения!$E$28*E9)*Допущения!$E$13 -> 166701.39 | AB9: =(R9+S9)*Допущения!$E$52 -> 13500 | AC9: =SUMPRODUCT(Допущения!$B$84:$B$91,Допущения!$C$84:$C$91,--(Допущения!$D$84:$D$91<=A9))*D9*Допущения!$E$9 -> 1132740 | AD9: =(AC9+Y9)*Допущения!$E$14 -> 161448 | AE9: =Допущения!$E$55+Допущения!$E$56*O9/1000+Допущения!$E$57 -> 143171.33 | AF9: =SUMIF(Допущения!$B$95:$B$103,A9,Допущения!$C$95:$C$103) -> 1000000 | AG9: 0 | AH9: =G9+SUM(X9:AG9) -> 3576300.7 | AI9: =W9-AH9 -> -2525315.7 | AJ9: =AJ8+AI9 -> -7071298 | AK9: =O9*Допущения!$E$58*Допущения!$E$59 -> 19622.625 | AL9: =T9*Допущения!$E$72 -> 50533.377 | AM9: =IF(MOD(A9,12)=0,INDEX($F$70:$F$74,B9),0) -> 0 | AN9: =AI9-AM9 -> -2525315.7 | AO9: =1/(1+Допущения!$E$74)^A9 -> 0.9358654 | AP9: =IF(AND(A9>Допущения!$E$19,MIN(AI9:AI$65)>0),A9,"") | AQ9: =IF(MIN(AJ9:AJ$65)>0,A9,"")
A10: 5 | B10: =INT((A10-1)/12)+1 -> 1 | C10: Масштабирование | D10: =(1+Допущения!$E$11)^(B10-1) -> 1 | E10: =(1+Допущения!$E$12)^(B10-1) -> 1 | F10: =Допущения!$E$71*E10 -> 3084.48 | G10: =MIN(G9*(1+Допущения!$E$33),Допущения!$E$34) -> 432000 | H10: =MIN(Допущения!$E$30,G10/Допущения!$E$29) -> 288 | I10: =MAX(0,G10-H10*Допущения!$E$29)/Допущения!$E$31 -> 0 | J10: =IF(A10>=Допущения!$E$35,Допущения!$E$36,0) -> 0 | K10: =H10+I10+J10 -> 288 | L10: =(L9-K9)*(1-Допущения!$E$44)+K9*(1-Допущения!$E$43)+K10 -> 630.57792 | M10: =IF(A10>=Допущения!$E$38,Допущения!$E$73/Допущения!$E$42*MIN(Допущения!$E$42,A10-Допущения!$E$38+1),0) -> 0 | N10: =N9*(1-Допущения!$E$45)+M10 -> 0 | O10: =L10+N10 -> 630.57792 | P10: =L10*Допущения!$E$25 -> 189.17337 | Q10: =L10*(1-Допущения!$E$25)+N10 -> 441.40454 | R10: =MAX(Допущения!$E$18,ROUNDUP(Q10/Допущения!$E$68+P10/Допущения!$E$69,0)) -> 7 | S10: =ROUNDUP(R10/Допущения!$E$48,0) -> 1 | T10: =L10*F10/(1+Допущения!$E$6) -> 1594266.4 | U10: =N10*Допущения!$E$28*E10/(1+Допущения!$E$6) -> 0 | V10: =O10*Допущения!$E$26*Допущения!$E$27/(1+Допущения!$E$6) -> 77530.072 | W10: =T10+U10+V10 -> 1671796.4 | X10: =J10*Допущения!$E$37 -> 0 | Y10: =(R10*Допущения!$E$47+S10*Допущения!$E$49)*D10*Допущения!$E$9 -> 735630 | Z10: =(MAX(0,R10-R9)+R10*Допущения!$E$50/12)*Допущения!$E$51*D10 -> 222250 | AA10: =O10*(Допущения!$E$53+Допущения!$E$54)+(L10*F10+N10*Допущения!$E$28*E10)*Допущения!$E$13 -> 265171.03 | AB10: =(R10+S10)*Допущения!$E$52 -> 21600 | AC10: =SUMPRODUCT(Допущения!$B$84:$B$91,Допущения!$C$84:$C$91,--(Допущения!$D$84:$D$91<=A10))*D10*Допущения!$E$9 -> 1132740 | AD10: =(AC10+Y10)*Допущения!$E$14 -> 186837 | AE10: =Допущения!$E$55+Допущения!$E$56*O10/1000+Допущения!$E$57 -> 145044.62 | AF10: =SUMIF(Допущения!$B$95:$B$103,A10,Допущения!$C$95:$C$103) -> 1000000 | AG10: 0 | AH10: =G10+SUM(X10:AG10) -> 4141272.7 | AI10: =W10-AH10 -> -2469476.2 | AJ10: =AJ9+AI10 -> -9540774.2 | AK10: =O10*Допущения!$E$58*Допущения!$E$59 -> 31213.607 | AL10: =T10*Допущения!$E$72 -> 80383.178 | AM10: =IF(MOD(A10,12)=0,INDEX($F$70:$F$74,B10),0) -> 0 | AN10: =AI10-AM10 -> -2469476.2 | AO10: =1/(1+Допущения!$E$74)^A10 -> 0.92048505 | AP10: =IF(AND(A10>Допущения!$E$19,MIN(AI10:AI$65)>0),A10,"") | AQ10: =IF(MIN(AJ10:AJ$65)>0,A10,"")
A11: 6 | B11: =INT((A11-1)/12)+1 -> 1 | C11: Масштабирование | D11: =(1+Допущения!$E$11)^(B11-1) -> 1 | E11: =(1+Допущения!$E$12)^(B11-1) -> 1 | F11: =Допущения!$E$71*E11 -> 3084.48 | G11: =MIN(G10*(1+Допущения!$E$33),Допущения!$E$34) -> 466560 | H11: =MIN(Допущения!$E$30,G11/Допущения!$E$29) -> 311.04 | I11: =MAX(0,G11-H11*Допущения!$E$29)/Допущения!$E$31 -> 0 | J11: =IF(A11>=Допущения!$E$35,Допущения!$E$36,0) -> 60 | K11: =H11+I11+J11 -> 371.04 | L11: =(L10-K10)*(1-Допущения!$E$44)+K10*(1-Допущения!$E$43)+K11 -> 934.36191 | M11: =IF(A11>=Допущения!$E$38,Допущения!$E$73/Допущения!$E$42*MIN(Допущения!$E$42,A11-Допущения!$E$38+1),0) -> 0 | N11: =N10*(1-Допущения!$E$45)+M11 -> 0 | O11: =L11+N11 -> 934.36191 | P11: =L11*Допущения!$E$25 -> 280.30857 | Q11: =L11*(1-Допущения!$E$25)+N11 -> 654.05334 | R11: =MAX(Допущения!$E$18,ROUNDUP(Q11/Допущения!$E$68+P11/Допущения!$E$69,0)) -> 9 | S11: =ROUNDUP(R11/Допущения!$E$48,0) -> 1 | T11: =L11*F11/(1+Допущения!$E$6) -> 2362312 | U11: =N11*Допущения!$E$28*E11/(1+Допущения!$E$6) -> 0 | V11: =O11*Допущения!$E$26*Допущения!$E$27/(1+Допущения!$E$6) -> 114880.56 | W11: =T11+U11+V11 -> 2477192.6 | X11: =J11*Допущения!$E$37 -> 30000 | Y11: =(R11*Допущения!$E$47+S11*Допущения!$E$49)*D11*Допущения!$E$9 -> 904890 | Z11: =(MAX(0,R11-R10)+R11*Допущения!$E$50/12)*Допущения!$E$51*D11 -> 155750 | AA11: =O11*(Допущения!$E$53+Допущения!$E$54)+(L11*F11+N11*Допущения!$E$28*E11)*Допущения!$E$13 -> 392918.47 | AB11: =(R11+S11)*Допущения!$E$52 -> 27000 | AC11: =SUMPRODUCT(Допущения!$B$84:$B$91,Допущения!$C$84:$C$91,--(Допущения!$D$84:$D$91<=A11))*D11*Допущения!$E$9 -> 1627500 | AD11: =(AC11+Y11)*Допущения!$E$14 -> 253239 | AE11: =Допущения!$E$55+Допущения!$E$56*O11/1000+Допущения!$E$57 -> 147474.9 | AF11: =SUMIF(Допущения!$B$95:$B$103,A11,Допущения!$C$95:$C$103) -> 1000000 | AG11: 0 | AH11: =G11+SUM(X11:AG11) -> 5005332.4 | AI11: =W11-AH11 -> -2528139.8 | AJ11: =AJ10+AI11 -> -12068914 | AK11: =O11*Допущения!$E$58*Допущения!$E$59 -> 46250.915 | AL11: =T11*Допущения!$E$72 -> 119108.17 | AM11: =IF(MOD(A11,12)=0,INDEX($F$70:$F$74,B11),0) -> 0 | AN11: =AI11-AM11 -> -2528139.8 | AO11: =1/(1+Допущения!$E$74)^A11 -> 0.90535746 | AP11: =IF(AND(A11>Допущения!$E$19,MIN(AI11:AI$65)>0),A11,"") | AQ11: =IF(MIN(AJ11:AJ$65)>0,A11,"")
A12: 7 | B12: =INT((A12-1)/12)+1 -> 1 | C12: Масштабирование | D12: =(1+Допущения!$E$11)^(B12-1) -> 1 | E12: =(1+Допущения!$E$12)^(B12-1) -> 1 | F12: =Допущения!$E$71*E12 -> 3084.48 | G12: =MIN(G11*(1+Допущения!$E$33),Допущения!$E$34) -> 503884.8 | H12: =MIN(Допущения!$E$30,G12/Допущения!$E$29) -> 335.9232 | I12: =MAX(0,G12-H12*Допущения!$E$29)/Допущения!$E$31 -> 0 | J12: =IF(A12>=Допущения!$E$35,Допущения!$E$36,0) -> 60 | K12: =H12+I12+J12 -> 395.9232 | L12: =(L11-K11)*(1-Допущения!$E$44)+K11*(1-Допущения!$E$43)+K12 -> 1238.1484 | M12: =IF(A12>=Допущения!$E$38,Допущения!$E$73/Допущения!$E$42*MIN(Допущения!$E$42,A12-Допущения!$E$38+1),0) -> 40 | N12: =N11*(1-Допущения!$E$45)+M12 -> 40 | O12: =L12+N12 -> 1278.1484 | P12: =L12*Допущения!$E$25 -> 371.44453 | Q12: =L12*(1-Допущения!$E$25)+N12 -> 906.7039 | R12: =MAX(Допущения!$E$18,ROUNDUP(Q12/Допущения!$E$68+P12/Допущения!$E$69,0)) -> 13 | S12: =ROUNDUP(R12/Допущения!$E$48,0) -> 2 | T12: =L12*F12/(1+Допущения!$E$6) -> 3130364 | U12: =N12*Допущения!$E$28*E12/(1+Допущения!$E$6) -> 65245.902 | V12: =O12*Допущения!$E$26*Допущения!$E$27/(1+Допущения!$E$6) -> 157149.4 | W12: =T12+U12+V12 -> 3352759.3 | X12: =J12*Допущения!$E$37 -> 30000 | Y12: =(R12*Допущения!$E$47+S12*Допущения!$E$49)*D12*Допущения!$E$9 -> 1386630 | Z12: =(MAX(0,R12-R11)+R12*Допущения!$E$50/12)*Допущения!$E$51*D12 -> 302750 | AA12: =O12*(Допущения!$E$53+Допущения!$E$54)+(L12*F12+N12*Допущения!$E$28*E12)*Допущения!$E$13 -> 536699.77 | AB12: =(R12+S12)*Допущения!$E$52 -> 40500 | AC12: =SUMPRODUCT(Допущения!$B$84:$B$91,Допущения!$C$84:$C$91,--(Допущения!$D$84:$D$91<=A12))*D12*Допущения!$E$9 -> 1627500 | AD12: =(AC12+Y12)*Допущения!$E$14 -> 301413 | AE12: =Допущения!$E$55+Допущения!$E$56*O12/1000+Допущения!$E$57 -> 150225.19 | AF12: =SUMIF(Допущения!$B$95:$B$103,A12,Допущения!$C$95:$C$103) -> 500000 | AG12: 0 | AH12: =G12+SUM(X12:AG12) -> 5379602.8 | AI12: =W12-AH12 -> -2026843.5 | AJ12: =AJ11+AI12 -> -14095758 | AK12: =O12*Допущения!$E$58*Допущения!$E$59 -> 63268.347 | AL12: =T12*Допущения!$E$72 -> 157833.48 | AM12: =IF(MOD(A12,12)=0,INDEX($F$70:$F$74,B12),0) -> 0 | AN12: =AI12-AM12 -> -2026843.5 | AO12: =1/(1+Допущения!$E$74)^A12 -> 0.89047849 | AP12: =IF(AND(A12>Допущения!$E$19,MIN(AI12:AI$65)>0),A12,"") | AQ12: =IF(MIN(AJ12:AJ$65)>0,A12,"")
A13: 8 | B13: =INT((A13-1)/12)+1 -> 1 | C13: Масштабирование | D13: =(1+Допущения!$E$11)^(B13-1) -> 1 | E13: =(1+Допущения!$E$12)^(B13-1) -> 1 | F13: =Допущения!$E$71*E13 -> 3084.48 | G13: =MIN(G12*(1+Допущения!$E$33),Допущения!$E$34) -> 544195.58 | H13: =MIN(Допущения!$E$30,G13/Допущения!$E$29) -> 362.79706 | I13: =MAX(0,G13-H13*Допущения!$E$29)/Допущения!$E$31 -> 0 | J13: =IF(A13>=Допущения!$E$35,Допущения!$E$36,0) -> 60 | K13: =H13+I13+J13 -> 422.79706 | L13: =(L12-K12)*(1-Допущения!$E$44)+K12*(1-Допущения!$E$43)+K13 -> 1551.7792 | M13: =IF(A13>=Допущения!$E$38,Допущения!$E$73/Допущения!$E$42*MIN(Допущения!$E$42,A13-Допущения!$E$38+1),0) -> 80 | N13: =N12*(1-Допущения!$E$45)+M13 -> 119.2 | O13: =L13+N13 -> 1670.9792 | P13: =L13*Допущения!$E$25 -> 465.53375 | Q13: =L13*(1-Допущения!$E$25)+N13 -> 1205.4454 | R13: =MAX(Допущения!$E$18,ROUNDUP(Q13/Допущения!$E$68+P13/Допущения!$E$69,0)) -> 16 | S13: =ROUNDUP(R13/Допущения!$E$48,0) -> 2 | T13: =L13*F13/(1+Допущения!$E$6) -> 3923304.8 | U13: =N13*Допущения!$E$28*E13/(1+Допущения!$E$6) -> 194432.79 | V13: =O13*Допущения!$E$26*Допущения!$E$27/(1+Допущения!$E$6) -> 205448.26 | W13: =T13+U13+V13 -> 4323185.8 | X13: =J13*Допущения!$E$37 -> 30000 | Y13: =(R13*Допущения!$E$47+S13*Допущения!$E$49)*D13*Допущения!$E$9 -> 1640520 | Z13: =(MAX(0,R13-R12)+R13*Допущения!$E$50/12)*Допущения!$E$51*D13 -> 238000 | AA13: =O13*(Допущения!$E$53+Допущения!$E$54)+(L13*F13+N13*Допущения!$E$28*E13)*Допущения!$E$13 -> 700332.91 | AB13: =(R13+S13)*Допущения!$E$52 -> 48600 | AC13: =SUMPRODUCT(Допущения!$B$84:$B$91,Допущения!$C$84:$C$91,--(Допущения!$D$84:$D$91<=A13))*D13*Допущения!$E$9 -> 1627500 | AD13: =(AC13+Y13)*Допущения!$E$14 -> 326802 | AE13: =Допущения!$E$55+Допущения!$E$56*O13/1000+Допущения!$E$57 -> 153367.83 | AF13: =SUMIF(Допущения!$B$95:$B$103,A13,Допущения!$C$95:$C$103) -> 500000 | AG13: 0 | AH13: =G13+SUM(X13:AG13) -> 5809318.3 | AI13: =W13-AH13 -> -1486132.5 | AJ13: =AJ12+AI13 -> -15581890 | AK13: =O13*Допущения!$E$58*Допущения!$E$59 -> 82713.469 | AL13: =T13*Допущения!$E$72 -> 197813.69 | AM13: =IF(MOD(A13,12)=0,INDEX($F$70:$F$74,B13),0) -> 0 | AN13: =AI13-AM13 -> -1486132.5 | AO13: =1/(1+Допущения!$E$74)^A13 -> 0.87584404 | AP13: =IF(AND(A13>Допущения!$E$19,MIN(AI13:AI$65)>0),A13,"") | AQ13: =IF(MIN(AJ13:AJ$65)>0,A13,"")
A14: 9 | B14: =INT((A14-1)/12)+1 -> 1 | C14: Масштабирование | D14: =(1+Допущения!$E$11)^(B14-1) -> 1 | E14: =(1+Допущения!$E$12)^(B14-1) -> 1 | F14: =Допущения!$E$71*E14 -> 3084.48 | G14: =MIN(G13*(1+Допущения!$E$33),Допущения!$E$34) -> 587731.23 | H14: =MIN(Допущения!$E$30,G14/Допущения!$E$29) -> 391.82082 | I14: =MAX(0,G14-H14*Допущения!$E$29)/Допущения!$E$31 -> 0 | J14: =IF(A14>=Допущения!$E$35,Допущения!$E$36,0) -> 60 | K14: =H14+I14+J14 -> 451.82082 | L14: =(L13-K13)*(1-Допущения!$E$44)+K13*(1-Допущения!$E$43)+K14 -> 1876.6923 | M14: =IF(A14>=Допущения!$E$38,Допущения!$E$73/Допущения!$E$42*MIN(Допущения!$E$42,A14-Допущения!$E$38+1),0) -> 120 | N14: =N13*(1-Допущения!$E$45)+M14 -> 236.816 | O14: =L14+N14 -> 2113.5083 | P14: =L14*Допущения!$E$25 -> 563.0077 | Q14: =L14*(1-Допущения!$E$25)+N14 -> 1550.5006 | R14: =MAX(Допущения!$E$18,ROUNDUP(Q14/Допущения!$E$68+P14/Допущения!$E$69,0)) -> 20 | S14: =ROUNDUP(R14/Допущения!$E$48,0) -> 2 | T14: =L14*F14/(1+Допущения!$E$6) -> 4744770.4 | U14: =N14*Допущения!$E$28*E14/(1+Допущения!$E$6) -> 386281.84 | V14: =O14*Допущения!$E$26*Допущения!$E$27/(1+Допущения!$E$6) -> 259857.58 | W14: =T14+U14+V14 -> 5390909.9 | X14: =J14*Допущения!$E$37 -> 30000 | Y14: =(R14*Допущения!$E$47+S14*Допущения!$E$49)*D14*Допущения!$E$9 -> 1979040 | Z14: =(MAX(0,R14-R13)+R14*Допущения!$E$50/12)*Допущения!$E$51*D14 -> 315000 | AA14: =O14*(Допущения!$E$53+Допущения!$E$54)+(L14*F14+N14*Допущения!$E$28*E14)*Допущения!$E$13 -> 884108.45 | AB14: =(R14+S14)*Допущения!$E$52 -> 59400 | AC14: =SUMPRODUCT(Допущения!$B$84:$B$91,Допущения!$C$84:$C$91,--(Допущения!$D$84:$D$91<=A14))*D14*Допущения!$E$9 -> 1627500 | AD14: =(AC14+Y14)*Допущения!$E$14 -> 360654 | AE14: =Допущения!$E$55+Допущения!$E$56*O14/1000+Допущения!$E$57 -> 156908.07 | AF14: =SUMIF(Допущения!$B$95:$B$103,A14,Допущения!$C$95:$C$103) -> 500000 | AG14: 0 | AH14: =G14+SUM(X14:AG14) -> 6500341.7 | AI14: =W14-AH14 -> -1109431.9 | AJ14: =AJ13+AI14 -> -16691322 | AK14: =O14*Допущения!$E$58*Допущения!$E$59 -> 104618.66 | AL14: =T14*Допущения!$E$72 -> 239232.12 | AM14: =IF(MOD(A14,12)=0,INDEX($F$70:$F$74,B14),0) -> 0 | AN14: =AI14-AM14 -> -1109431.9 | AO14: =1/(1+Допущения!$E$74)^A14 -> 0.8614501 | AP14: =IF(AND(A14>Допущения!$E$19,MIN(AI14:AI$65)>0),A14,"") | AQ14: =IF(MIN(AJ14:AJ$65)>0,A14,"")
A15: 10 | B15: =INT((A15-1)/12)+1 -> 1 | C15: Масштабирование | D15: =(1+Допущения!$E$11)^(B15-1) -> 1 | E15: =(1+Допущения!$E$12)^(B15-1) -> 1 | F15: =Допущения!$E$71*E15 -> 3084.48 | G15: =MIN(G14*(1+Допущения!$E$33),Допущения!$E$34) -> 634749.73 | H15: =MIN(Допущения!$E$30,G15/Допущения!$E$29) -> 400 | I15: =MAX(0,G15-H15*Допущения!$E$29)/Допущения!$E$31 -> 7.722162 | J15: =IF(A15>=Допущения!$E$35,Допущения!$E$36,0) -> 60 | K15: =H15+I15+J15 -> 467.72216 | L15: =(L14-K14)*(1-Допущения!$E$44)+K14*(1-Допущения!$E$43)+K15 -> 2198.9675 | M15: =IF(A15>=Допущения!$E$38,Допущения!$E$73/Допущения!$E$42*MIN(Допущения!$E$42,A15-Допущения!$E$38+1),0) -> 120 | N15: =N14*(1-Допущения!$E$45)+M15 -> 352.07968 | O15: =L15+N15 -> 2551.0472 | P15: =L15*Допущения!$E$25 -> 659.69026 | Q15: =L15*(1-Допущения!$E$25)+N15 -> 1891.3569 | R15: =MAX(Допущения!$E$18,ROUNDUP(Q15/Допущения!$E$68+P15/Допущения!$E$69,0)) -> 24 | S15: =ROUNDUP(R15/Допущения!$E$48,0) -> 2 | T15: =L15*F15/(1+Допущения!$E$6) -> 5559566.7 | U15: =N15*Допущения!$E$28*E15/(1+Допущения!$E$6) -> 574293.9 | V15: =O15*Допущения!$E$26*Допущения!$E$27/(1+Допущения!$E$6) -> 313653.34 | W15: =T15+U15+V15 -> 6447513.9 | X15: =J15*Допущения!$E$37 -> 30000 | Y15: =(R15*Допущения!$E$47+S15*Допущения!$E$49)*D15*Допущения!$E$9 -> 2317560 | Z15: =(MAX(0,R15-R14)+R15*Допущения!$E$50/12)*Допущения!$E$51*D15 -> 322000 | AA15: =O15*(Допущения!$E$53+Допущения!$E$54)+(L15*F15+N15*Допущения!$E$28*E15)*Допущения!$E$13 -> 1065831.8 | AB15: =(R15+S15)*Допущения!$E$52 -> 70200 | AC15: =SUMPRODUCT(Допущения!$B$84:$B$91,Допущения!$C$84:$C$91,--(Допущения!$D$84:$D$91<=A15))*D15*Допущения!$E$9 -> 1966020 | AD15: =(AC15+Y15)*Допущения!$E$14 -> 428358 | AE15: =Допущения!$E$55+Допущения!$E$56*O15/1000+Допущения!$E$57 -> 160408.38 | AF15: =SUMIF(Допущения!$B$95:$B$103,A15,Допущения!$C$95:$C$103) -> 350000 | AG15: 0 | AH15: =G15+SUM(X15:AG15) -> 7345127.9 | AI15: =W15-AH15 -> -897613.99 | AJ15: =AJ14+AI15 -> -17588936 | AK15: =O15*Допущения!$E$58*Допущения!$E$59 -> 126276.84 | AL15: =T15*Допущения!$E$72 -> 280314.29 | AM15: =IF(MOD(A15,12)=0,INDEX($F$70:$F$74,B15),0) -> 0 | AN15: =AI15-AM15 -> -897613.99 | AO15: =1/(1+Допущения!$E$74)^A15 -> 0.84729272 | AP15: =IF(AND(A15>Допущения!$E$19,MIN(AI15:AI$65)>0),A15,"") | AQ15: =IF(MIN(AJ15:AJ$65)>0,A15,"")
A16: 11 | B16: =INT((A16-1)/12)+1 -> 1 | C16: Масштабирование | D16: =(1+Допущения!$E$11)^(B16-1) -> 1 | E16: =(1+Допущения!$E$12)^(B16-1) -> 1 | F16: =Допущения!$E$71*E16 -> 3084.48 | G16: =MIN(G15*(1+Допущения!$E$33),Допущения!$E$34) -> 685529.71 | H16: =MIN(Допущения!$E$30,G16/Допущения!$E$29) -> 400 | I16: =MAX(0,G16-H16*Допущения!$E$29)/Допущения!$E$31 -> 19.006602 | J16: =IF(A16>=Допущения!$E$35,Допущения!$E$36,0) -> 60 | K16: =H16+I16+J16 -> 479.0066 | L16: =(L15-K15)*(1-Допущения!$E$44)+K15*(1-Допущения!$E$43)+K16 -> 2515.8781 | M16: =IF(A16>=Допущения!$E$38,Допущения!$E$73/Допущения!$E$42*MIN(Допущения!$E$42,A16-Допущения!$E$38+1),0) -> 120 | N16: =N15*(1-Допущения!$E$45)+M16 -> 465.03809 | O16: =L16+N16 -> 2980.9162 | P16: =L16*Допущения!$E$25 -> 754.76343 | Q16: =L16*(1-Допущения!$E$25)+N16 -> 2226.1528 | R16: =MAX(Допущения!$E$18,ROUNDUP(Q16/Допущения!$E$68+P16/Допущения!$E$69,0)) -> 28 | S16: =ROUNDUP(R16/Допущения!$E$48,0) -> 3 | T16: =L16*F16/(1+Допущения!$E$6) -> 6360799.7 | U16: =N16*Допущения!$E$28*E16/(1+Допущения!$E$6) -> 758545.73 | V16: =O16*Допущения!$E$26*Допущения!$E$27/(1+Допущения!$E$6) -> 366506.09 | W16: =T16+U16+V16 -> 7485851.5 | X16: =J16*Допущения!$E$37 -> 30000 | Y16: =(R16*Допущения!$E$47+S16*Допущения!$E$49)*D16*Допущения!$E$9 -> 2799300 | Z16: =(MAX(0,R16-R15)+R16*Допущения!$E$50/12)*Допущения!$E$51*D16 -> 329000 | AA16: =O16*(Допущения!$E$53+Допущения!$E$54)+(L16*F16+N16*Допущения!$E$28*E16)*Допущения!$E$13 -> 1244375.2 | AB16: =(R16+S16)*Допущения!$E$52 -> 83700 | AC16: =SUMPRODUCT(Допущения!$B$84:$B$91,Допущения!$C$84:$C$91,--(Допущения!$D$84:$D$91<=A16))*D16*Допущения!$E$9 -> 1966020 | AD16: =(AC16+Y16)*Допущения!$E$14 -> 476532 | AE16: =Допущения!$E$55+Допущения!$E$56*O16/1000+Допущения!$E$57 -> 163847.33 | AF16: =SUMIF(Допущения!$B$95:$B$103,A16,Допущения!$C$95:$C$103) -> 350000 | AG16: 0 | AH16: =G16+SUM(X16:AG16) -> 8128304.3 | AI16: =W16-AH16 -> -642452.73 | AJ16: =AJ15+AI16 -> -18231389 | AK16: =O16*Допущения!$E$58*Допущения!$E$59 -> 147555.35 | AL16: =T16*Допущения!$E$72 -> 320712.59 | AM16: =IF(MOD(A16,12)=0,INDEX($F$70:$F$74,B16),0) -> 0 | AN16: =AI16-AM16 -> -642452.73 | AO16: =1/(1+Допущения!$E$74)^A16 -> 0.833368 | AP16: =IF(AND(A16>Допущения!$E$19,MIN(AI16:AI$65)>0),A16,"") | AQ16: =IF(MIN(AJ16:AJ$65)>0,A16,"")
A17: 12 | B17: =INT((A17-1)/12)+1 -> 1 | C17: Масштабирование | D17: =(1+Допущения!$E$11)^(B17-1) -> 1 | E17: =(1+Допущения!$E$12)^(B17-1) -> 1 | F17: =Допущения!$E$71*E17 -> 3084.48 | G17: =MIN(G16*(1+Допущения!$E$33),Допущения!$E$34) -> 740372.08 | H17: =MIN(Допущения!$E$30,G17/Допущения!$E$29) -> 400 | I17: =MAX(0,G17-H17*Допущения!$E$29)/Допущения!$E$31 -> 31.193796 | J17: =IF(A17>=Допущения!$E$35,Допущения!$E$36,0) -> 60 | K17: =H17+I17+J17 -> 491.1938 | L17: =(L16-K16)*(1-Допущения!$E$44)+K16*(1-Допущения!$E$43)+K17 -> 2829.1915 | M17: =IF(A17>=Допущения!$E$38,Допущения!$E$73/Допущения!$E$42*MIN(Допущения!$E$42,A17-Допущения!$E$38+1),0) -> 120 | N17: =N16*(1-Допущения!$E$45)+M17 -> 575.73732 | O17: =L17+N17 -> 3404.9288 | P17: =L17*Допущения!$E$25 -> 848.75745 | Q17: =L17*(1-Допущения!$E$25)+N17 -> 2556.1714 | R17: =MAX(Допущения!$E$18,ROUNDUP(Q17/Допущения!$E$68+P17/Допущения!$E$69,0)) -> 31 | S17: =ROUNDUP(R17/Допущения!$E$48,0) -> 3 | T17: =L17*F17/(1+Допущения!$E$6) -> 7152938.2 | U17: =N17*Допущения!$E$28*E17/(1+Допущения!$E$6) -> 939112.52 | V17: =O17*Допущения!$E$26*Допущения!$E$27/(1+Допущения!$E$6) -> 418638.79 | W17: =T17+U17+V17 -> 8510689.5 | X17: =J17*Допущения!$E$37 -> 30000 | Y17: =(R17*Допущения!$E$47+S17*Допущения!$E$49)*D17*Допущения!$E$9 -> 3053190 | Z17: =(MAX(0,R17-R16)+R17*Допущения!$E$50/12)*Допущения!$E$51*D17 -> 264250 | AA17: =O17*(Допущения!$E$53+Допущения!$E$54)+(L17*F17+N17*Допущения!$E$28*E17)*Допущения!$E$13 -> 1420500.4 | AB17: =(R17+S17)*Допущения!$E$52 -> 91800 | AC17: =SUMPRODUCT(Допущения!$B$84:$B$91,Допущения!$C$84:$C$91,--(Допущения!$D$84:$D$91<=A17))*D17*Допущения!$E$9 -> 1966020 | AD17: =(AC17+Y17)*Допущения!$E$14 -> 501921 | AE17: =Допущения!$E$55+Допущения!$E$56*O17/1000+Допущения!$E$57 -> 167239.43 | AF17: =SUMIF(Допущения!$B$95:$B$103,A17,Допущения!$C$95:$C$103) -> 300000 | AG17: 0 | AH17: =G17+SUM(X17:AG17) -> 8535293 | AI17: =W17-AH17 -> -24603.499 | AJ17: =AJ16+AI17 -> -18255992 | AK17: =O17*Допущения!$E$58*Допущения!$E$59 -> 168543.98 | AL17: =T17*Допущения!$E$72 -> 360652.34 | AM17: =IF(MOD(A17,12)=0,INDEX($F$70:$F$74,B17),0) -> 0 | AN17: =AI17-AM17 -> -24603.499 | AO17: =1/(1+Допущения!$E$74)^A17 -> 0.81967213 | AP17: =IF(AND(A17>Допущения!$E$19,MIN(AI17:AI$65)>0),A17,"") | AQ17: =IF(MIN(AJ17:AJ$65)>0,A17,"")
A18: 13 | B18: =INT((A18-1)/12)+1 -> 2 | C18: Масштабирование | D18: =(1+Допущения!$E$11)^(B18-1) -> 1.08 | E18: =(1+Допущения!$E$12)^(B18-1) -> 1.07 | F18: =Допущения!$E$71*E18 -> 3300.3936 | G18: =MIN(G17*(1+Допущения!$E$33),Допущения!$E$34) -> 799601.85 | H18: =MIN(Допущения!$E$30,G18/Допущения!$E$29) -> 400 | I18: =MAX(0,G18-H18*Допущения!$E$29)/Допущения!$E$31 -> 44.355967 | J18: =IF(A18>=Допущения!$E$35,Допущения!$E$36,0) -> 60 | K18: =H18+I18+J18 -> 504.35597 | L18: =(L17-K17)*(1-Допущения!$E$44)+K17*(1-Допущения!$E$43)+K18 -> 3139.9227 | M18: =IF(A18>=Допущения!$E$38,Допущения!$E$73/Допущения!$E$42*MIN(Допущения!$E$42,A18-Допущения!$E$38+1),0) -> 120 | N18: =N17*(1-Допущения!$E$45)+M18 -> 684.22258 | O18: =L18+N18 -> 3824.1452 | P18: =L18*Допущения!$E$25 -> 941.9768 | Q18: =L18*(1-Допущения!$E$25)+N18 -> 2882.1684 | R18: =MAX(Допущения!$E$18,ROUNDUP(Q18/Допущения!$E$68+P18/Допущения!$E$69,0)) -> 35 | S18: =ROUNDUP(R18/Допущения!$E$48,0) -> 3 | T18: =L18*F18/(1+Допущения!$E$6) -> 8494246.5 | U18: =N18*Допущения!$E$28*E18/(1+Допущения!$E$6) -> 1194192.7 | V18: =O18*Допущения!$E$26*Допущения!$E$27/(1+Допущения!$E$6) -> 470181.79 | W18: =T18+U18+V18 -> 10158621 | X18: =J18*Допущения!$E$37 -> 30000 | Y18: =(R18*Допущения!$E$47+S18*Допущения!$E$49)*D18*Допущения!$E$9 -> 3663046.8 | Z18: =(MAX(0,R18-R17)+R18*Допущения!$E$50/12)*Допущения!$E$51*D18 -> 368550 | AA18: =O18*(Допущения!$E$53+Допущения!$E$54)+(L18*F18+N18*Допущения!$E$28*E18)*Допущения!$E$13 -> 1608571.1 | AB18: =(R18+S18)*Допущения!$E$52 -> 102600 | AC18: =SUMPRODUCT(Допущения!$B$84:$B$91,Допущения!$C$84:$C$91,--(Допущения!$D$84:$D$91<=A18))*D18*Допущения!$E$9 -> 2123301.6 | AD18: =(AC18+Y18)*Допущения!$E$14 -> 578634.84 | AE18: =Допущения!$E$55+Допущения!$E$56*O18/1000+Допущения!$E$57 -> 170593.16 | AF18: =SUMIF(Допущения!$B$95:$B$103,A18,Допущения!$C$95:$C$103) -> 0 | AG18: 0 | AH18: =G18+SUM(X18:AG18) -> 9444899.4 | AI18: =W18-AH18 -> 713721.6 | AJ18: =AJ17+AI18 -> -17542271 | AK18: =O18*Допущения!$E$58*Допущения!$E$59 -> 189295.19 | AL18: =T18*Допущения!$E$72 -> 428281.33 | AM18: =IF(MOD(A18,12)=0,INDEX($F$70:$F$74,B18),0) -> 0 | AN18: =AI18-AM18 -> 713721.6 | AO18: =1/(1+Допущения!$E$74)^A18 -> 0.80620134 | AP18: =IF(AND(A18>Допущения!$E$19,MIN(AI18:AI$65)>0),A18,"") -> 13 | AQ18: =IF(MIN(AJ18:AJ$65)>0,A18,"")
A19: 14 | B19: =INT((A19-1)/12)+1 -> 2 | C19: Масштабирование | D19: =(1+Допущения!$E$11)^(B19-1) -> 1.08 | E19: =(1+Допущения!$E$12)^(B19-1) -> 1.07 | F19: =Допущения!$E$71*E19 -> 3300.3936 | G19: =MIN(G18*(1+Допущения!$E$33),Допущения!$E$34) -> 863570 | H19: =MIN(Допущения!$E$30,G19/Допущения!$E$29) -> 400 | I19: =MAX(0,G19-H19*Допущения!$E$29)/Допущения!$E$31 -> 58.571111 | J19: =IF(A19>=Допущения!$E$35,Допущения!$E$36,0) -> 60 | K19: =H19+I19+J19 -> 518.57111 | L19: =(L18-K18)*(1-Допущения!$E$44)+K18*(1-Допущения!$E$43)+K19 -> 3449.1092 | M19: =IF(A19>=Допущения!$E$38,Допущения!$E$73/Допущения!$E$42*MIN(Допущения!$E$42,A19-Допущения!$E$38+1),0) -> 120 | N19: =N18*(1-Допущения!$E$45)+M19 -> 790.53813 | O19: =L19+N19 -> 4239.6473 | P19: =L19*Допущения!$E$25 -> 1034.7328 | Q19: =L19*(1-Допущения!$E$25)+N19 -> 3204.9146 | R19: =MAX(Допущения!$E$18,ROUNDUP(Q19/Допущения!$E$68+P19/Допущения!$E$69,0)) -> 39 | S19: =ROUNDUP(R19/Допущения!$E$48,0) -> 4 | T19: =L19*F19/(1+Допущения!$E$6) -> 9330670.5 | U19: =N19*Допущения!$E$28*E19/(1+Допущения!$E$6) -> 1379748.2 | V19: =O19*Допущения!$E$26*Допущения!$E$27/(1+Допущения!$E$6) -> 521268.11 | W19: =T19+U19+V19 -> 11231687 | X19: =J19*Допущения!$E$37 -> 30000 | Y19: =(R19*Допущения!$E$47+S19*Допущения!$E$49)*D19*Допущения!$E$9 -> 4183326 | Z19: =(MAX(0,R19-R18)+R19*Допущения!$E$50/12)*Допущения!$E$51*D19 -> 376110 | AA19: =O19*(Допущения!$E$53+Допущения!$E$54)+(L19*F19+N19*Допущения!$E$28*E19)*Допущения!$E$13 -> 1782672.1 | AB19: =(R19+S19)*Допущения!$E$52 -> 116100 | AC19: =SUMPRODUCT(Допущения!$B$84:$B$91,Допущения!$C$84:$C$91,--(Допущения!$D$84:$D$91<=A19))*D19*Допущения!$E$9 -> 2123301.6 | AD19: =(AC19+Y19)*Допущения!$E$14 -> 630662.76 | AE19: =Допущения!$E$55+Допущения!$E$56*O19/1000+Допущения!$E$57 -> 173917.18 | AF19: =SUMIF(Допущения!$B$95:$B$103,A19,Допущения!$C$95:$C$103) -> 0 | AG19: 0 | AH19: =G19+SUM(X19:AG19) -> 10279660 | AI19: =W19-AH19 -> 952027.18 | AJ19: =AJ18+AI19 -> -16590243 | AK19: =O19*Допущения!$E$58*Допущения!$E$59 -> 209862.54 | AL19: =T19*Допущения!$E$72 -> 470453.97 | AM19: =IF(MOD(A19,12)=0,INDEX($F$70:$F$74,B19),0) -> 0 | AN19: =AI19-AM19 -> 952027.18 | AO19: =1/(1+Допущения!$E$74)^A19 -> 0.79295194 | AP19: =IF(AND(A19>Допущения!$E$19,MIN(AI19:AI$65)>0),A19,"") -> 14 | AQ19: =IF(MIN(AJ19:AJ$65)>0,A19,"")
A20: 15 | B20: =INT((A20-1)/12)+1 -> 2 | C20: Масштабирование | D20: =(1+Допущения!$E$11)^(B20-1) -> 1.08 | E20: =(1+Допущения!$E$12)^(B20-1) -> 1.07 | F20: =Допущения!$E$71*E20 -> 3300.3936 | G20: =MIN(G19*(1+Допущения!$E$33),Допущения!$E$34) -> 932655.6 | H20: =MIN(Допущения!$E$30,G20/Допущения!$E$29) -> 400 | I20: =MAX(0,G20-H20*Допущения!$E$29)/Допущения!$E$31 -> 73.923466 | J20: =IF(A20>=Допущения!$E$35,Допущения!$E$36,0) -> 60 | K20: =H20+I20+J20 -> 533.92347 | L20: =(L19-K19)*(1-Допущения!$E$44)+K19*(1-Допущения!$E$43)+K20 -> 3757.8157 | M20: =IF(A20>=Допущения!$E$38,Допущения!$E$73/Допущения!$E$42*MIN(Допущения!$E$42,A20-Допущения!$E$38+1),0) -> 120 | N20: =N19*(1-Допущения!$E$45)+M20 -> 894.72736 | O20: =L20+N20 -> 4652.543 | P20: =L20*Допущения!$E$25 -> 1127.3447 | Q20: =L20*(1-Допущения!$E$25)+N20 -> 3525.1983 | R20: =MAX(Допущения!$E$18,ROUNDUP(Q20/Допущения!$E$68+P20/Допущения!$E$69,0)) -> 43 | S20: =ROUNDUP(R20/Допущения!$E$48,0) -> 4 | T20: =L20*F20/(1+Допущения!$E$6) -> 10165796 | U20: =N20*Допущения!$E$28*E20/(1+Допущения!$E$6) -> 1561592.6 | V20: =O20*Допущения!$E$26*Допущения!$E$27/(1+Допущения!$E$6) -> 572033.98 | W20: =T20+U20+V20 -> 12299422 | X20: =J20*Допущения!$E$37 -> 30000 | Y20: =(R20*Допущения!$E$47+S20*Допущения!$E$49)*D20*Допущения!$E$9 -> 4548927.6 | Z20: =(MAX(0,R20-R19)+R20*Допущения!$E$50/12)*Допущения!$E$51*D20 -> 383670 | AA20: =O20*(Допущения!$E$53+Допущения!$E$54)+(L20*F20+N20*Допущения!$E$28*E20)*Допущения!$E$13 -> 1955711.7 | AB20: =(R20+S20)*Допущения!$E$52 -> 126900 | AC20: =SUMPRODUCT(Допущения!$B$84:$B$91,Допущения!$C$84:$C$91,--(Допущения!$D$84:$D$91<=A20))*D20*Допущения!$E$9 -> 2123301.6 | AD20: =(AC20+Y20)*Допущения!$E$14 -> 667222.92 | AE20: =Допущения!$E$55+Допущения!$E$56*O20/1000+Допущения!$E$57 -> 177220.34 | AF20: =SUMIF(Допущения!$B$95:$B$103,A20,Допущения!$C$95:$C$103) -> 0 | AG20: 0 | AH20: =G20+SUM(X20:AG20) -> 10945610 | AI20: =W20-AH20 -> 1353812.6 | AJ20: =AJ19+AI20 -> -15236431 | AK20: =O20*Допущения!$E$58*Допущения!$E$59 -> 230300.88 | AL20: =T20*Допущения!$E$72 -> 512561.13 | AM20: =IF(MOD(A20,12)=0,INDEX($F$70:$F$74,B20),0) -> 0 | AN20: =AI20-AM20 -> 1353812.6 | AO20: =1/(1+Допущения!$E$74)^A20 -> 0.77992028 | AP20: =IF(AND(A20>Допущения!$E$19,MIN(AI20:AI$65)>0),A20,"") -> 15 | AQ20: =IF(MIN(AJ20:AJ$65)>0,A20,"")
A21: 16 | B21: =INT((A21-1)/12)+1 -> 2 | C21: Масштабирование | D21: =(1+Допущения!$E$11)^(B21-1) -> 1.08 | E21: =(1+Допущения!$E$12)^(B21-1) -> 1.07 | F21: =Допущения!$E$71*E21 -> 3300.3936 | G21: =MIN(G20*(1+Допущения!$E$33),Допущения!$E$34) -> 1007268 | H21: =MIN(Допущения!$E$30,G21/Допущения!$E$29) -> 400 | I21: =MAX(0,G21-H21*Допущения!$E$29)/Допущения!$E$31 -> 90.50401 | J21: =IF(A21>=Допущения!$E$35,Допущения!$E$36,0) -> 60 | K21: =H21+I21+J21 -> 550.50401 | L21: =(L20-K20)*(1-Допущения!$E$44)+K20*(1-Допущения!$E$43)+K21 -> 4067.1383 | M21: =IF(A21>=Допущения!$E$38,Допущения!$E$73/Допущения!$E$42*MIN(Допущения!$E$42,A21-Допущения!$E$38+1),0) -> 120 | N21: =N20*(1-Допущения!$E$45)+M21 -> 996.83282 | O21: =L21+N21 -> 5063.9711 | P21: =L21*Допущения!$E$25 -> 1220.1415 | Q21: =L21*(1-Допущения!$E$25)+N21 -> 3843.8296 | R21: =MAX(Допущения!$E$18,ROUNDUP(Q21/Допущения!$E$68+P21/Допущения!$E$69,0)) -> 46 | S21: =ROUNDUP(R21/Допущения!$E$48,0) -> 4 | T21: =L21*F21/(1+Допущения!$E$6) -> 11002588 | U21: =N21*Допущения!$E$28*E21/(1+Допущения!$E$6) -> 1739800.1 | V21: =O21*Допущения!$E$26*Допущения!$E$27/(1+Допущения!$E$6) -> 622619.4 | W21: =T21+U21+V21 -> 13365007 | X21: =J21*Допущения!$E$37 -> 30000 | Y21: =(R21*Допущения!$E$47+S21*Допущения!$E$49)*D21*Допущения!$E$9 -> 4823128.8 | Z21: =(MAX(0,R21-R20)+R21*Допущения!$E$50/12)*Допущения!$E$51*D21 -> 313740 | AA21: =O21*(Допущения!$E$53+Допущения!$E$54)+(L21*F21+N21*Допущения!$E$28*E21)*Допущения!$E$13 -> 2128172.3 | AB21: =(R21+S21)*Допущения!$E$52 -> 135000 | AC21: =SUMPRODUCT(Допущения!$B$84:$B$91,Допущения!$C$84:$C$91,--(Допущения!$D$84:$D$91<=A21))*D21*Допущения!$E$9 -> 2123301.6 | AD21: =(AC21+Y21)*Допущения!$E$14 -> 694643.04 | AE21: =Допущения!$E$55+Допущения!$E$56*O21/1000+Допущения!$E$57 -> 180511.77 | AF21: =SUMIF(Допущения!$B$95:$B$103,A21,Допущения!$C$95:$C$103) -> 0 | AG21: 0 | AH21: =G21+SUM(X21:AG21) -> 11435766 | AI21: =W21-AH21 -> 1929241.8 | AJ21: =AJ20+AI21 -> -13307189 | AK21: =O21*Допущения!$E$58*Допущения!$E$59 -> 250666.57 | AL21: =T21*Допущения!$E$72 -> 554752.33 | AM21: =IF(MOD(A21,12)=0,INDEX($F$70:$F$74,B21),0) -> 0 | AN21: =AI21-AM21 -> 1929241.8 | AO21: =1/(1+Допущения!$E$74)^A21 -> 0.76710278 | AP21: =IF(AND(A21>Допущения!$E$19,MIN(AI21:AI$65)>0),A21,"") -> 16 | AQ21: =IF(MIN(AJ21:AJ$65)>0,A21,"")
... A65: 60 | B65: =INT((A65-1)/12)+1 -> 5 | C65: Масштабирование | D65: =(1+Допущения!$E$11)^(B65-1) -> 1.360489 | E65: =(1+Допущения!$E$12)^(B65-1) -> 1.310796 | F65: =Допущения!$E$71*E65 -> 4043.1241 | G65: =MIN(G64*(1+Допущения!$E$33),Допущения!$E$34) -> 2500000 | H65: =MIN(Допущения!$E$30,G65/Допущения!$E$29) -> 400 | I65: =MAX(0,G65-H65*Допущения!$E$29)/Допущения!$E$31 -> 422.22222 | J65: =IF(A65>=Допущения!$E$35,Допущения!$E$36,0) -> 60 | K65: =H65+I65+J65 -> 882.22222 | L65: =(L64-K64)*(1-Допущения!$E$44)+K64*(1-Допущения!$E$43)+K65 -> 14970.963 | M65: =IF(A65>=Допущения!$E$38,Допущения!$E$73/Допущения!$E$42*MIN(Допущения!$E$42,A65-Допущения!$E$38+1),0) -> 120 | N65: =N64*(1-Допущения!$E$45)+M65 -> 3943.1987 | O65: =L65+N65 -> 18914.162 | P65: =L65*Допущения!$E$25 -> 4491.2889 | Q65: =L65*(1-Допущения!$E$25)+N65 -> 14422.873 | R65: =MAX(Допущения!$E$18,ROUNDUP(Q65/Допущения!$E$68+P65/Допущения!$E$69,0)) -> 170 | S65: =ROUNDUP(R65/Допущения!$E$48,0) -> 15 | T65: =L65*F65/(1+Допущения!$E$6) -> 49614313 | U65: =N65*Допущения!$E$28*E65/(1+Допущения!$E$6) -> 8430959.7 | V65: =O65*Допущения!$E$26*Допущения!$E$27/(1+Допущения!$E$6) -> 2325511.7 | W65: =T65+U65+V65 -> 60370784 | X65: =J65*Допущения!$E$37 -> 30000 | Y65: =(R65*Допущения!$E$47+S65*Допущения!$E$49)*D65*Допущения!$E$9 -> 22496229 | Z65: =(MAX(0,R65-R64)+R65*Допущения!$E$50/12)*Допущения!$E$51*D65 -> 499979.69 | AA65: =O65*(Допущения!$E$53+Допущения!$E$54)+(L65*F65+N65*Допущения!$E$28*E65)*Допущения!$E$13 -> 8178343.2 | AB65: =(R65+S65)*Допущения!$E$52 -> 499500 | AC65: =SUMPRODUCT(Допущения!$B$84:$B$91,Допущения!$C$84:$C$91,--(Допущения!$D$84:$D$91<=A65))*D65*Допущения!$E$9 -> 2674748.5 | AD65: =(AC65+Y65)*Допущения!$E$14 -> 2517097.8 | AE65: =Допущения!$E$55+Допущения!$E$56*O65/1000+Допущения!$E$57 -> 291313.29 | AF65: =SUMIF(Допущения!$B$95:$B$103,A65,Допущения!$C$95:$C$103) -> 0 | AG65: 0 | AH65: =G65+SUM(X65:AG65) -> 39687212 | AI65: =W65-AH65 -> 20683572 | AJ65: =AJ64+AI65 -> 5.2413048e+08 | AK65: =O65*Допущения!$E$58*Допущения!$E$59 -> 936251.01 | AL65: =T65*Допущения!$E$72 -> 2501562 | AM65: =IF(MOD(A65,12)=0,INDEX($F$70:$F$74,B65),0) -> 58585336 | AN65: =AI65-AM65 -> -37901764 | AO65: =1/(1+Допущения!$E$74)^A65 -> 0.36999925 | AP65: =IF(AND(A65>Допущения!$E$19,MIN(AI65:AI$65)>0),A65,"") -> 60 | AQ65: =IF(MIN(AJ65:AJ$65)>0,A65,"") -> 60
A68: Годовые итоги и налог на прибыль с переносом убытков
A69: Год | B69: Выручка, руб. | C69: Операционный результат, руб. | D69: Убыток к переносу на начало, руб. | E69: Зачтено убытка, руб. | F69: Налог на прибыль, руб. | G69: Убыток к переносу на конец, руб. | H69: Кросс-продажи, руб.
A70: 1 | B70: =SUMIF($B$6:$B$65,A70,$W$6:$W$65) -> 41038866 | C70: =SUMIF($B$6:$B$65,A70,$AI$6:$AI$65) -> -18255992 | D70: 0 | E70: =IF(C70>0,MIN(D70,C70*Допущения!$E$8),0) -> 0 | F70: =IF(C70>0,(C70-E70)*Допущения!$E$7,0) -> 0 | G70: =D70+IF(C70<0,-C70,0)-E70 -> 18255992 | H70: =SUMIF($B$6:$B$65,A70,$AK$6:$AK$65) -> 790063.79
A71: 2 | B71: =SUMIF($B$6:$B$65,A71,$W$6:$W$65) -> 1.9322244e+08 | C71: =SUMIF($B$6:$B$65,A71,$AI$6:$AI$65) -> 32437821 | D71: =G70 -> 18255992 | E71: =IF(C71>0,MIN(D71,C71*Допущения!$E$8),0) -> 16218910 | F71: =IF(C71>0,(C71-E71)*Допущения!$E$7,0) -> 4054727.6 | G71: =D71+IF(C71<0,-C71,0)-E71 -> 2037081.8 | H71: =SUMIF($B$6:$B$65,A71,$AK$6:$AK$65) -> 3630163.4
A72: 3 | B72: =SUMIF($B$6:$B$65,A72,$W$6:$W$65) -> 3.8485219e+08 | C72: =SUMIF($B$6:$B$65,A72,$AI$6:$AI$65) -> 1.0003577e+08 | D72: =G71 -> 2037081.8 | E72: =IF(C72>0,MIN(D72,C72*Допущения!$E$8),0) -> 2037081.8 | F72: =IF(C72>0,(C72-E72)*Допущения!$E$7,0) -> 24499672 | G72: =D72+IF(C72<0,-C72,0)-E72 -> 0 | H72: =SUMIF($B$6:$B$65,A72,$AK$6:$AK$65) -> 6769686.5
A73: 4 | B73: =SUMIF($B$6:$B$65,A73,$W$6:$W$65) -> 5.5921336e+08 | C73: =SUMIF($B$6:$B$65,A73,$AI$6:$AI$65) -> 1.7557154e+08 | D73: =G72 -> 0 | E73: =IF(C73>0,MIN(D73,C73*Допущения!$E$8),0) -> 0 | F73: =IF(C73>0,(C73-E73)*Допущения!$E$7,0) -> 43892884 | G73: =D73+IF(C73<0,-C73,0)-E73 -> 0 | H73: =SUMIF($B$6:$B$65,A73,$AK$6:$AK$65) -> 9217218.1
A74: 5 | B74: =SUMIF($B$6:$B$65,A74,$W$6:$W$65) -> 6.9277866e+08 | C74: =SUMIF($B$6:$B$65,A74,$AI$6:$AI$65) -> 2.3434135e+08 | D74: =G73 -> 0 | E74: =IF(C74>0,MIN(D74,C74*Допущения!$E$8),0) -> 0 | F74: =IF(C74>0,(C74-E74)*Допущения!$E$7,0) -> 58585336 | G74: =D74+IF(C74<0,-C74,0)-E74 -> 0 | H74: =SUMIF($B$6:$B$65,A74,$AK$6:$AK$65) -> 10728623
A75: Итого | B75: =SUM(B70:B74) -> 1.8711055e+09 | C75: =SUM(C70:C74) -> 5.2413048e+08 | F75: =SUM(F70:F74) -> 1.3103262e+08 | H75: =SUM(H70:H74) -> 31135755

Sheet Версия 1
A1: Помесячный расчет: сценарий «Версия 1 без триажа»
A2: Суммы в рублях без НДС. Месяцы 1-3: MVP. Налог на прибыль начисляется в последнем месяце года.
A5: Месяц | B5: Год | C5: Фаза | D5: Индекс зарплат | E5: Индекс цен | F5: Средний чек B2C с НДС, руб. | G5: Маркетинг, руб. | H5: Новые семьи: внутренние каналы | I5: Новые семьи: внешние каналы | J5: Новые семьи: канал фонда «Защитники Отечества» | K5: Новые семьи B2C | L5: Семьи B2C | M5: Приток B2B2C | N5: Семьи B2B2C | O5: Всего семей | P5: Семьи «Расши-ренный» | Q5: Семьи «Базовый» и B2B2C | R5: Координа-торы, чел. | S5: Супер-визоры, чел. | T5: Выручка: подписка B2C, руб. | U5: Выручка: B2B2C, руб. | V5: Выручка: комиссия партнеров, руб. | W5: Выручка всего, руб. | X5: Партнерский канал фонда, руб. | Y5: ФОТ координаторов и супервизоров, руб. | Z5: Обучение новых координаторов, руб. | AA5: Переменные расходы на семьи, руб. | AB5: Рабочие места, руб. | AC5: Постоянная команда, руб. | AD5: Накладные, руб. | AE5: Размещение и юрлицо, руб. | AF5: Инвестиции, руб. | AG5: Бюджет MVP, руб. | AH5: Расходы всего, руб. | AI5: Операционный результат, руб. | AJ5: Накопленный результат, руб. | AK5: Кросс-продажи (эффект группы), руб. | AL5: Льготы ветеранам: недополученная выручка, руб. | AM5: Налог на прибыль, руб. | AN5: Денежный поток после налога, руб. | AO5: Коэффициент дисконтирования | AP5: Признак безубыточности (месяц) | AQ5: Признак окупаемости (месяц)
A6: 1 | B6: =INT((A6-1)/12)+1 -> 1 | C6: MVP | D6: =(1+Допущения!$F$11)^(B6-1) -> 1 | E6: =(1+Допущения!$F$12)^(B6-1) -> 1 | F6: =Допущения!$F$71*E6 -> 2465.68 | G6: 0 | H6: 0 | I6: 0 | J6: 0 | K6: =Допущения!$B$78-0 -> 0 | L6: =Допущения!$B$78 -> 0 | M6: 0 | N6: 0 | O6: =L6+N6 -> 0 | P6: =L6*Допущения!$F$25 -> 0 | Q6: =L6*(1-Допущения!$F$25)+N6 -> 0 | R6: =IF(A6>1,Допущения!$F$18,0) -> 0 | S6: 0 | T6: =L6*Допущения!$F$60*F6/(1+Допущения!$F$6) -> 0 | U6: =N6*Допущения!$F$28*E6/(1+Допущения!$F$6) -> 0 | V6: =O6*Допущения!$F$26*Допущения!$F$27/(1+Допущения!$F$6) -> 0 | W6: =T6+U6+V6 -> 0 | X6: 0 | Y6: 0 | Z6: 0 | AA6: 0 | AB6: 0 | AC6: 0 | AD6: 0 | AE6: 0 | AF6: 0 | AG6: ='Бюджет MVP'!$G$33/Допущения!$F$19 -> 1624654.7 | AH6: =G6+SUM(X6:AG6) -> 1624654.7 | AI6: =W6-AH6 -> -1624654.7 | AJ6: =AI6 -> -1624654.7 | AK6: 0 | AL6: =T6*Допущения!$F$72 -> 0 | AM6: =IF(MOD(A6,12)=0,INDEX($F$70:$F$74,B6),0) -> 0 | AN6: =AI6-AM6 -> -1624654.7 | AO6: =1/(1+Допущения!$F$74)^A6 -> 0.98356564 | AP6: =IF(AND(A6>Допущения!$F$19,MIN(AI6:AI$65)>0),A6,"") | AQ6: =IF(MIN(AJ6:AJ$65)>0,A6,"")
A7: 2 | B7: =INT((A7-1)/12)+1 -> 1 | C7: MVP | D7: =(1+Допущения!$F$11)^(B7-1) -> 1 | E7: =(1+Допущения!$F$12)^(B7-1) -> 1 | F7: =Допущения!$F$71*E7 -> 2465.68 | G7: 0 | H7: 0 | I7: 0 | J7: 0 | K7: =Допущения!$B$79-Допущения!$B$78 -> 50 | L7: =Допущения!$B$79 -> 50 | M7: 0 | N7: 0 | O7: =L7+N7 -> 50 | P7: =L7*Допущения!$F$25 -> 15 | Q7: =L7*(1-Допущения!$F$25)+N7 -> 35 | R7: =IF(A7>1,Допущения!$F$18,0) -> 3 | S7: 0 | T7: =L7*Допущения!$F$60*F7/(1+Допущения!$F$6) -> 60631.475 | U7: =N7*Допущения!$F$28*E7/(1+Допущения!$F$6) -> 0 | V7: =O7*Допущения!$F$26*Допущения!$F$27/(1+Допущения!$F$6) -> 6147.541 | W7: =T7+U7+V7 -> 66779.016 | X7: 0 | Y7: 0 | Z7: 0 | AA7: 0 | AB7: 0 | AC7: 0 | AD7: 0 | AE7: 0 | AF7: 0 | AG7: ='Бюджет MVP'!$G$33/Допущения!$F$19 -> 1624654.7 | AH7: =G7+SUM(X7:AG7) -> 1624654.7 | AI7: =W7-AH7 -> -1557875.7 | AJ7: =AJ6+AI7 -> -3182530.3 | AK7: 0 | AL7: =T7*Допущения!$F$72 -> 3057.0492 | AM7: =IF(MOD(A7,12)=0,INDEX($F$70:$F$74,B7),0) -> 0 | AN7: =AI7-AM7 -> -1557875.7 | AO7: =1/(1+Допущения!$F$74)^A7 -> 0.96740136 | AP7: =IF(AND(A7>Допущения!$F$19,MIN(AI7:AI$65)>0),A7,"") | AQ7: =IF(MIN(AJ7:AJ$65)>0,A7,"")
A8: 3 | B8: =INT((A8-1)/12)+1 -> 1 | C8: MVP | D8: =(1+Допущения!$F$11)^(B8-1) -> 1 | E8: =(1+Допущения!$F$12)^(B8-1) -> 1 | F8: =Допущения!$F$71*E8 -> 2465.68 | G8: 0 | H8: 0 | I8: 0 | J8: 0 | K8: =Допущения!$B$80-Допущения!$B$79 -> 100 | L8: =Допущения!$B$80 -> 150 | M8: 0 | N8: 0 | O8: =L8+N8 -> 150 | P8: =L8*Допущения!$F$25 -> 45 | Q8: =L8*(1-Допущения!$F$25)+N8 -> 105 | R8: =IF(A8>1,Допущения!$F$18,0) -> 3 | S8: 0 | T8: =L8*Допущения!$F$60*F8/(1+Допущения!$F$6) -> 181894.43 | U8: =N8*Допущения!$F$28*E8/(1+Допущения!$F$6) -> 0 | V8: =O8*Допущения!$F$26*Допущения!$F$27/(1+Допущения!$F$6) -> 18442.623 | W8: =T8+U8+V8 -> 200337.05 | X8: 0 | Y8: 0 | Z8: 0 | AA8: 0 | AB8: 0 | AC8: 0 | AD8: 0 | AE8: 0 | AF8: 0 | AG8: ='Бюджет MVP'!$G$33/Допущения!$F$19 -> 1624654.7 | AH8: =G8+SUM(X8:AG8) -> 1624654.7 | AI8: =W8-AH8 -> -1424317.6 | AJ8: =AJ7+AI8 -> -4606847.9 | AK8: 0 | AL8: =T8*Допущения!$F$72 -> 9171.1475 | AM8: =IF(MOD(A8,12)=0,INDEX($F$70:$F$74,B8),0) -> 0 | AN8: =AI8-AM8 -> -1424317.6 | AO8: =1/(1+Допущения!$F$74)^A8 -> 0.95150274 | AP8: =IF(AND(A8>Допущения!$F$19,MIN(AI8:AI$65)>0),A8,"") | AQ8: =IF(MIN(AJ8:AJ$65)>0,A8,"")
A9: 4 | B9: =INT((A9-1)/12)+1 -> 1 | C9: Масштабирование | D9: =(1+Допущения!$F$11)^(B9-1) -> 1 | E9: =(1+Допущения!$F$12)^(B9-1) -> 1 | F9: =Допущения!$F$71*E9 -> 2465.68 | G9: =Допущения!$F$32 -> 400000 | H9: =MIN(Допущения!$F$30,G9/Допущения!$F$29) -> 266.66667 | I9: =MAX(0,G9-H9*Допущения!$F$29)/Допущения!$F$31 -> 0 | J9: =IF(A9>=Допущения!$F$35,Допущения!$F$36,0) -> 0 | K9: =H9+I9+J9 -> 266.66667 | L9: =(L8-K8)*(1-Допущения!$F$44)+K8*(1-Допущения!$F$43)+K9 -> 388.66667 | M9: =IF(A9>=Допущения!$F$38,Допущения!$F$73/Допущения!$F$42*MIN(Допущения!$F$42,A9-Допущения!$F$38+1),0) -> 0 | N9: =N8*(1-Допущения!$F$45)+M9 -> 0 | O9: =L9+N9 -> 388.66667 | P9: =L9*Допущения!$F$25 -> 116.6 | Q9: =L9*(1-Допущения!$F$25)+N9 -> 272.06667 | R9: =MAX(Допущения!$F$18,ROUNDUP(Q9/Допущения!$F$68+P9/Допущения!$F$69,0)) -> 6 | S9: =ROUNDUP(R9/Допущения!$F$48,0) -> 1 | T9: =L9*F9/(1+Допущения!$F$6) -> 785514.45 | U9: =N9*Допущения!$F$28*E9/(1+Допущения!$F$6) -> 0 | V9: =O9*Допущения!$F$26*Допущения!$F$27/(1+Допущения!$F$6) -> 47786.885 | W9: =T9+U9+V9 -> 833301.33 | X9: =J9*Допущения!$F$37 -> 0 | Y9: =(R9*Допущения!$F$47+S9*Допущения!$F$49)*D9*Допущения!$F$9 -> 833280 | Z9: =(MAX(0,R9-R8)+R9*Допущения!$F$50/12)*Допущения!$F$51*D9 -> 244125 | AA9: =O9*(Допущения!$F$53+Допущения!$F$54)+(L9*F9+N9*Допущения!$F$28*E9)*Допущения!$F$13 -> 190206.56 | AB9: =(R9+S9)*Допущения!$F$52 -> 18900 | AC9: =SUMPRODUCT(Допущения!$B$84:$B$91,Допущения!$C$84:$C$91,--(Допущения!$D$84:$D$91<=A9))*D9*Допущения!$F$9 -> 1132740 | AD9: =(AC9+Y9)*Допущения!$F$14 -> 196602 | AE9: =Допущения!$F$55+Допущения!$F$56*O9/1000+Допущения!$F$57 -> 143109.33 | AF9: =SUMIF(Допущения!$B$95:$B$103,A9,Допущения!$C$95:$C$103) -> 1000000 | AG9: 0 | AH9: =G9+SUM(X9:AG9) -> 4158962.9 | AI9: =W9-AH9 -> -3325661.6 | AJ9: =AJ8+AI9 -> -7932509.5 | AK9: =O9*Допущения!$F$58*Допущения!$F$59 -> 12826 | AL9: =T9*Допущения!$F$72 -> 39605.77 | AM9: =IF(MOD(A9,12)=0,INDEX($F$70:$F$74,B9),0) -> 0 | AN9: =AI9-AM9 -> -3325661.6 | AO9: =1/(1+Допущения!$F$74)^A9 -> 0.9358654 | AP9: =IF(AND(A9>Допущения!$F$19,MIN(AI9:AI$65)>0),A9,"") | AQ9: =IF(MIN(AJ9:AJ$65)>0,A9,"")
A10: 5 | B10: =INT((A10-1)/12)+1 -> 1 | C10: Масштабирование | D10: =(1+Допущения!$F$11)^(B10-1) -> 1 | E10: =(1+Допущения!$F$12)^(B10-1) -> 1 | F10: =Допущения!$F$71*E10 -> 2465.68 | G10: =MIN(G9*(1+Допущения!$F$33),Допущения!$F$34) -> 432000 | H10: =MIN(Допущения!$F$30,G10/Допущения!$F$29) -> 288 | I10: =MAX(0,G10-H10*Допущения!$F$29)/Допущения!$F$31 -> 0 | J10: =IF(A10>=Допущения!$F$35,Допущения!$F$36,0) -> 0 | K10: =H10+I10+J10 -> 288 | L10: =(L9-K9)*(1-Допущения!$F$44)+K9*(1-Допущения!$F$43)+K10 -> 602.68 | M10: =IF(A10>=Допущения!$F$38,Допущения!$F$73/Допущения!$F$42*MIN(Допущения!$F$42,A10-Допущения!$F$38+1),0) -> 0 | N10: =N9*(1-Допущения!$F$45)+M10 -> 0 | O10: =L10+N10 -> 602.68 | P10: =L10*Допущения!$F$25 -> 180.804 | Q10: =L10*(1-Допущения!$F$25)+N10 -> 421.876 | R10: =MAX(Допущения!$F$18,ROUNDUP(Q10/Допущения!$F$68+P10/Допущения!$F$69,0)) -> 9 | S10: =ROUNDUP(R10/Допущения!$F$48,0) -> 1 | T10: =L10*F10/(1+Допущения!$F$6) -> 1218045.9 | U10: =N10*Допущения!$F$28*E10/(1+Допущения!$F$6) -> 0 | V10: =O10*Допущения!$F$26*Допущения!$F$27/(1+Допущения!$F$6) -> 74100 | W10: =T10+U10+V10 -> 1292145.9 | X10: =J10*Допущения!$F$37 -> 0 | Y10: =(R10*Допущения!$F$47+S10*Допущения!$F$49)*D10*Допущения!$F$9 -> 1165290 | Z10: =(MAX(0,R10-R9)+R10*Допущения!$F$50/12)*Допущения!$F$51*D10 -> 249937.5 | AA10: =O10*(Допущения!$F$53+Допущения!$F$54)+(L10*F10+N10*Допущения!$F$28*E10)*Допущения!$F$13 -> 294940.89 | AB10: =(R10+S10)*Допущения!$F$52 -> 27000 | AC10: =SUMPRODUCT(Допущения!$B$84:$B$91,Допущения!$C$84:$C$91,--(Допущения!$D$84:$D$91<=A10))*D10*Допущения!$F$9 -> 1132740 | AD10: =(AC10+Y10)*Допущения!$F$14 -> 229803 | AE10: =Допущения!$F$55+Допущения!$F$56*O10/1000+Допущения!$F$57 -> 144821.44 | AF10: =SUMIF(Допущения!$B$95:$B$103,A10,Допущения!$C$95:$C$103) -> 1000000 | AG10: 0 | AH10: =G10+SUM(X10:AG10) -> 4676532.8 | AI10: =W10-AH10 -> -3384386.9 | AJ10: =AJ9+AI10 -> -11316896 | AK10: =O10*Допущения!$F$58*Допущения!$F$59 -> 19888.44 | AL10: =T10*Допущения!$F$72 -> 61414.08 | AM10: =IF(MOD(A10,12)=0,INDEX($F$70:$F$74,B10),0) -> 0 | AN10: =AI10-AM10 -> -3384386.9 | AO10: =1/(1+Допущения!$F$74)^A10 -> 0.92048505 | AP10: =IF(AND(A10>Допущения!$F$19,MIN(AI10:AI$65)>0),A10,"") | AQ10: =IF(MIN(AJ10:AJ$65)>0,A10,"")
A11: 6 | B11: =INT((A11-1)/12)+1 -> 1 | C11: Масштабирование | D11: =(1+Допущения!$F$11)^(B11-1) -> 1 | E11: =(1+Допущения!$F$12)^(B11-1) -> 1 | F11: =Допущения!$F$71*E11 -> 2465.68 | G11: =MIN(G10*(1+Допущения!$F$33),Допущения!$F$34) -> 466560 | H11: =MIN(Допущения!$F$30,G11/Допущения!$F$29) -> 300 | I11: =MAX(0,G11-H11*Допущения!$F$29)/Допущения!$F$31 -> 2.76 | J11: =IF(A11>=Допущения!$F$35,Допущения!$F$36,0) -> 40 | K11: =H11+I11+J11 -> 342.76 | L11: =(L10-K10)*(1-Допущения!$F$44)+K10*(1-Допущения!$F$43)+K11 -> 854.5592 | M11: =IF(A11>=Допущения!$F$38,Допущения!$F$73/Допущения!$F$42*MIN(Допущения!$F$42,A11-Допущения!$F$38+1),0) -> 0 | N11: =N10*(1-Допущения!$F$45)+M11 -> 0 | O11: =L11+N11 -> 854.5592 | P11: =L11*Допущения!$F$25 -> 256.36776 | Q11: =L11*(1-Допущения!$F$25)+N11 -> 598.19144 | R11: =MAX(Допущения!$F$18,ROUNDUP(Q11/Допущения!$F$68+P11/Допущения!$F$69,0)) -> 13 | S11: =ROUNDUP(R11/Допущения!$F$48,0) -> 2 | T11: =L11*F11/(1+Допущения!$F$6) -> 1727106.2 | U11: =N11*Допущения!$F$28*E11/(1+Допущения!$F$6) -> 0 | V11: =O11*Допущения!$F$26*Допущения!$F$27/(1+Допущения!$F$6) -> 105068.75 | W11: =T11+U11+V11 -> 1832174.9 | X11: =J11*Допущения!$F$37 -> 20000 | Y11: =(R11*Допущения!$F$47+S11*Допущения!$F$49)*D11*Допущения!$F$9 -> 1777230 | Z11: =(MAX(0,R11-R10)+R11*Допущения!$F$50/12)*Допущения!$F$51*D11 -> 335187.5 | AA11: =O11*(Допущения!$F$53+Допущения!$F$54)+(L11*F11+N11*Допущения!$F$28*E11)*Допущения!$F$13 -> 418206.1 | AB11: =(R11+S11)*Допущения!$F$52 -> 40500 | AC11: =SUMPRODUCT(Допущения!$B$84:$B$91,Допущения!$C$84:$C$91,--(Допущения!$D$84:$D$91<=A11))*D11*Допущения!$F$9 -> 1627500 | AD11: =(AC11+Y11)*Допущения!$F$14 -> 340473 | AE11: =Допущения!$F$55+Допущения!$F$56*O11/1000+Допущения!$F$57 -> 146836.47 | AF11: =SUMIF(Допущения!$B$95:$B$103,A11,Допущения!$C$95:$C$103) -> 1000000 | AG11: 0 | AH11: =G11+SUM(X11:AG11) -> 6172493.1 | AI11: =W11-AH11 -> -4340318.1 | AJ11: =AJ10+AI11 -> -15657215 | AK11: =O11*Допущения!$F$58*Допущения!$F$59 -> 28200.454 | AL11: =T11*Допущения!$F$72 -> 87080.983 | AM11: =IF(MOD(A11,12)=0,INDEX($F$70:$F$74,B11),0) -> 0 | AN11: =AI11-AM11 -> -4340318.1 | AO11: =1/(1+Допущения!$F$74)^A11 -> 0.90535746 | AP11: =IF(AND(A11>Допущения!$F$19,MIN(AI11:AI$65)>0),A11,"") | AQ11: =IF(MIN(AJ11:AJ$65)>0,A11,"")
A12: 7 | B12: =INT((A12-1)/12)+1 -> 1 | C12: Масштабирование | D12: =(1+Допущения!$F$11)^(B12-1) -> 1 | E12: =(1+Допущения!$F$12)^(B12-1) -> 1 | F12: =Допущения!$F$71*E12 -> 2465.68 | G12: =MIN(G11*(1+Допущения!$F$33),Допущения!$F$34) -> 503884.8 | H12: =MIN(Допущения!$F$30,G12/Допущения!$F$29) -> 300 | I12: =MAX(0,G12-H12*Допущения!$F$29)/Допущения!$F$31 -> 8.9808 | J12: =IF(A12>=Допущения!$F$35,Допущения!$F$36,0) -> 40 | K12: =H12+I12+J12 -> 348.9808 | L12: =(L11-K11)*(1-Допущения!$F$44)+K11*(1-Допущения!$F$43)+K12 -> 1087.142 | M12: =IF(A12>=Допущения!$F$38,Допущения!$F$73/Допущения!$F$42*MIN(Допущения!$F$42,A12-Допущения!$F$38+1),0) -> 20 | N12: =N11*(1-Допущения!$F$45)+M12 -> 20 | O12: =L12+N12 -> 1107.142 | P12: =L12*Допущения!$F$25 -> 326.14261 | Q12: =L12*(1-Допущения!$F$25)+N12 -> 780.99943 | R12: =MAX(Допущения!$F$18,ROUNDUP(Q12/Допущения!$F$68+P12/Допущения!$F$69,0)) -> 17 | S12: =ROUNDUP(R12/Допущения!$F$48,0) -> 2 | T12: =L12*F12/(1+Допущения!$F$6) -> 2197167.5 | U12: =N12*Допущения!$F$28*E12/(1+Допущения!$F$6) -> 24590.164 | V12: =O12*Допущения!$F$26*Допущения!$F$27/(1+Допущения!$F$6) -> 136124.02 | W12: =T12+U12+V12 -> 2357881.7 | X12: =J12*Допущения!$F$37 -> 20000 | Y12: =(R12*Допущения!$F$47+S12*Допущения!$F$49)*D12*Допущения!$F$9 -> 2219910 | Z12: =(MAX(0,R12-R11)+R12*Допущения!$F$50/12)*Допущения!$F$51*D12 -> 342937.5 | AA12: =O12*(Допущения!$F$53+Допущения!$F$54)+(L12*F12+N12*Допущения!$F$28*E12)*Допущения!$F$13 -> 541468.01 | AB12: =(R12+S12)*Допущения!$F$52 -> 51300 | AC12: =SUMPRODUCT(Допущения!$B$84:$B$91,Допущения!$C$84:$C$91,--(Допущения!$D$84:$D$91<=A12))*D12*Допущения!$F$9 -> 1627500 | AD12: =(AC12+Y12)*Допущения!$F$14 -> 384741 | AE12: =Допущения!$F$55+Допущения!$F$56*O12/1000+Допущения!$F$57 -> 148857.14 | AF12: =SUMIF(Допущения!$B$95:$B$103,A12,Допущения!$C$95:$C$103) -> 500000 | AG12: 0 | AH12: =G12+SUM(X12:AG12) -> 6340598.4 | AI12: =W12-AH12 -> -3982716.7 | AJ12: =AJ11+AI12 -> -19639931 | AK12: =O12*Допущения!$F$58*Допущения!$F$59 -> 36535.688 | AL12: =T12*Допущения!$F$72 -> 110781.56 | AM12: =IF(MOD(A12,12)=0,INDEX($F$70:$F$74,B12),0) -> 0 | AN12: =AI12-AM12 -> -3982716.7 | AO12: =1/(1+Допущения!$F$74)^A12 -> 0.89047849 | AP12: =IF(AND(A12>Допущения!$F$19,MIN(AI12:AI$65)>0),A12,"") | AQ12: =IF(MIN(AJ12:AJ$65)>0,A12,"")
A13: 8 | B13: =INT((A13-1)/12)+1 -> 1 | C13: Масштабирование | D13: =(1+Допущения!$F$11)^(B13-1) -> 1 | E13: =(1+Допущения!$F$12)^(B13-1) -> 1 | F13: =Допущения!$F$71*E13 -> 2465.68 | G13: =MIN(G12*(1+Допущения!$F$33),Допущения!$F$34) -> 544195.58 | H13: =MIN(Допущения!$F$30,G13/Допущения!$F$29) -> 300 | I13: =MAX(0,G13-H13*Допущения!$F$29)/Допущения!$F$31 -> 15.699264 | J13: =IF(A13>=Допущения!$F$35,Допущения!$F$36,0) -> 40 | K13: =H13+I13+J13 -> 355.69926 | L13: =(L12-K12)*(1-Допущения!$F$44)+K12*(1-Допущения!$F$43)+K13 -> 1311.3064 | M13: =IF(A13>=Допущения!$F$38,Допущения!$F$73/Допущения!$F$42*MIN(Допущения!$F$42,A13-Допущения!$F$38+1),0) -> 40 | N13: =N12*(1-Допущения!$F$45)+M13 -> 59.6 | O13: =L13+N13 -> 1370.9064 | P13: =L13*Допущения!$F$25 -> 393.39193 | Q13: =L13*(1-Допущения!$F$25)+N13 -> 977.51451 | R13: =MAX(Допущения!$F$18,ROUNDUP(Q13/Допущения!$F$68+P13/Допущения!$F$69,0)) -> 21 | S13: =ROUNDUP(R13/Допущения!$F$48,0) -> 3 | T13: =L13*F13/(1+Допущения!$F$6) -> 2650214.8 | U13: =N13*Допущения!$F$28*E13/(1+Допущения!$F$6) -> 73278.689 | V13: =O13*Допущения!$F$26*Допущения!$F$27/(1+Допущения!$F$6) -> 168554.07 | W13: =T13+U13+V13 -> 2892047.6 | X13: =J13*Допущения!$F$37 -> 20000 | Y13: =(R13*Допущения!$F$47+S13*Допущения!$F$49)*D13*Допущения!$F$9 -> 2831850 | Z13: =(MAX(0,R13-R12)+R13*Допущения!$F$50/12)*Допущения!$F$51*D13 -> 350687.5 | AA13: =O13*(Допущения!$F$53+Допущения!$F$54)+(L13*F13+N13*Допущения!$F$28*E13)*Допущения!$F$13 -> 669861.28 | AB13: =(R13+S13)*Допущения!$F$52 -> 64800 | AC13: =SUMPRODUCT(Допущения!$B$84:$B$91,Допущения!$C$84:$C$91,--(Допущения!$D$84:$D$91<=A13))*D13*Допущения!$F$9 -> 1627500 | AD13: =(AC13+Y13)*Допущения!$F$14 -> 445935 | AE13: =Допущения!$F$55+Допущения!$F$56*O13/1000+Допущения!$F$57 -> 150967.25 | AF13: =SUMIF(Допущения!$B$95:$B$103,A13,Допущения!$C$95:$C$103) -> 500000 | AG13: 0 | AH13: =G13+SUM(X13:AG13) -> 7205796.6 | AI13: =W13-AH13 -> -4313749.1 | AJ13: =AJ12+AI13 -> -23953680 | AK13: =O13*Допущения!$F$58*Допущения!$F$59 -> 45239.912 | AL13: =T13*Допущения!$F$72 -> 133624.28 | AM13: =IF(MOD(A13,12)=0,INDEX($F$70:$F$74,B13),0) -> 0 | AN13: =AI13-AM13 -> -4313749.1 | AO13: =1/(1+Допущения!$F$74)^A13 -> 0.87584404 | AP13: =IF(AND(A13>Допущения!$F$19,MIN(AI13:AI$65)>0),A13,"") | AQ13: =IF(MIN(AJ13:AJ$65)>0,A13,"")
A14: 9 | B14: =INT((A14-1)/12)+1 -> 1 | C14: Масштабирование | D14: =(1+Допущения!$F$11)^(B14-1) -> 1 | E14: =(1+Допущения!$F$12)^(B14-1) -> 1 | F14: =Допущения!$F$71*E14 -> 2465.68 | G14: =MIN(G13*(1+Допущения!$F$33),Допущения!$F$34) -> 587731.23 | H14: =MIN(Допущения!$F$30,G14/Допущения!$F$29) -> 300 | I14: =MAX(0,G14-H14*Допущения!$F$29)/Допущения!$F$31 -> 22.955205 | J14: =IF(A14>=Допущения!$F$35,Допущения!$F$36,0) -> 40 | K14: =H14+I14+J14 -> 362.95521 | L14: =(L13-K13)*(1-Допущения!$F$44)+K13*(1-Допущения!$F$43)+K14 -> 1528.0004 | M14: =IF(A14>=Допущения!$F$38,Допущения!$F$73/Допущения!$F$42*MIN(Допущения!$F$42,A14-Допущения!$F$38+1),0) -> 60 | N14: =N13*(1-Допущения!$F$45)+M14 -> 118.408 | O14: =L14+N14 -> 1646.4084 | P14: =L14*Допущения!$F$25 -> 458.40012 | Q14: =L14*(1-Допущения!$F$25)+N14 -> 1188.0083 | R14: =MAX(Допущения!$F$18,ROUNDUP(Q14/Допущения!$F$68+P14/Допущения!$F$69,0)) -> 25 | S14: =ROUNDUP(R14/Допущения!$F$48,0) -> 3 | T14: =L14*F14/(1+Допущения!$F$6) -> 3088163.9 | U14: =N14*Допущения!$F$28*E14/(1+Допущения!$F$6) -> 145583.61 | V14: =O14*Допущения!$F$26*Допущения!$F$27/(1+Допущения!$F$6) -> 202427.26 | W14: =T14+U14+V14 -> 3436174.8 | X14: =J14*Допущения!$F$37 -> 20000 | Y14: =(R14*Допущения!$F$47+S14*Допущения!$F$49)*D14*Допущения!$F$9 -> 3274530 | Z14: =(MAX(0,R14-R13)+R14*Допущения!$F$50/12)*Допущения!$F$51*D14 -> 358437.5 | AA14: =O14*(Допущения!$F$53+Допущения!$F$54)+(L14*F14+N14*Допущения!$F$28*E14)*Допущения!$F$13 -> 803664.83 | AB14: =(R14+S14)*Допущения!$F$52 -> 75600 | AC14: =SUMPRODUCT(Допущения!$B$84:$B$91,Допущения!$C$84:$C$91,--(Допущения!$D$84:$D$91<=A14))*D14*Допущения!$F$9 -> 1627500 | AD14: =(AC14+Y14)*Допущения!$F$14 -> 490203 | AE14: =Допущения!$F$55+Допущения!$F$56*O14/1000+Допущения!$F$57 -> 153171.27 | AF14: =SUMIF(Допущения!$B$95:$B$103,A14,Допущения!$C$95:$C$103) -> 500000 | AG14: 0 | AH14: =G14+SUM(X14:AG14) -> 7890837.8 | AI14: =W14-AH14 -> -4454663 | AJ14: =AJ13+AI14 -> -28408343 | AK14: =O14*Допущения!$F$58*Допущения!$F$59 -> 54331.477 | AL14: =T14*Допущения!$F$72 -> 155705.75 | AM14: =IF(MOD(A14,12)=0,INDEX($F$70:$F$74,B14),0) -> 0 | AN14: =AI14-AM14 -> -4454663 | AO14: =1/(1+Допущения!$F$74)^A14 -> 0.8614501 | AP14: =IF(AND(A14>Допущения!$F$19,MIN(AI14:AI$65)>0),A14,"") | AQ14: =IF(MIN(AJ14:AJ$65)>0,A14,"")
A15: 10 | B15: =INT((A15-1)/12)+1 -> 1 | C15: Масштабирование | D15: =(1+Допущения!$F$11)^(B15-1) -> 1 | E15: =(1+Допущения!$F$12)^(B15-1) -> 1 | F15: =Допущения!$F$71*E15 -> 2465.68 | G15: =MIN(G14*(1+Допущения!$F$33),Допущения!$F$34) -> 634749.73 | H15: =MIN(Допущения!$F$30,G15/Допущения!$F$29) -> 300 | I15: =MAX(0,G15-H15*Допущения!$F$29)/Допущения!$F$31 -> 30.791622 | J15: =IF(A15>=Допущения!$F$35,Допущения!$F$36,0) -> 40 | K15: =H15+I15+J15 -> 370.79162 | L15: =(L14-K14)*(1-Допущения!$F$44)+K14*(1-Допущения!$F$43)+K15 -> 1738.1505 | M15: =IF(A15>=Допущения!$F$38,Допущения!$F$73/Допущения!$F$42*MIN(Допущения!$F$42,A15-Допущения!$F$38+1),0) -> 60 | N15: =N14*(1-Допущения!$F$45)+M15 -> 176.03984 | O15: =L15+N15 -> 1914.1903 | P15: =L15*Допущения!$F$25 -> 521.44515 | Q15: =L15*(1-Допущения!$F$25)+N15 -> 1392.7452 | R15: =MAX(Допущения!$F$18,ROUNDUP(Q15/Допущения!$F$68+P15/Допущения!$F$69,0)) -> 28 | S15: =ROUNDUP(R15/Допущения!$F$48,0) -> 3 | T15: =L15*F15/(1+Допущения!$F$6) -> 3512887.7 | U15: =N15*Допущения!$F$28*E15/(1+Допущения!$F$6) -> 216442.43 | V15: =O15*Допущения!$F$26*Допущения!$F$27/(1+Допущения!$F$6) -> 235351.27 | W15: =T15+U15+V15 -> 3964681.4 | X15: =J15*Допущения!$F$37 -> 20000 | Y15: =(R15*Допущения!$F$47+S15*Допущения!$F$49)*D15*Допущения!$F$9 -> 3606540 | Z15: =(MAX(0,R15-R14)+R15*Допущения!$F$50/12)*Допущения!$F$51*D15 -> 286750 | AA15: =O15*(Допущения!$F$53+Допущения!$F$54)+(L15*F15+N15*Допущения!$F$28*E15)*Допущения!$F$13 -> 933710.79 | AB15: =(R15+S15)*Допущения!$F$52 -> 83700 | AC15: =SUMPRODUCT(Допущения!$B$84:$B$91,Допущения!$C$84:$C$91,--(Допущения!$D$84:$D$91<=A15))*D15*Допущения!$F$9 -> 1966020 | AD15: =(AC15+Y15)*Допущения!$F$14 -> 557256 | AE15: =Допущения!$F$55+Допущения!$F$56*O15/1000+Допущения!$F$57 -> 155313.52 | AF15: =SUMIF(Допущения!$B$95:$B$103,A15,Допущения!$C$95:$C$103) -> 350000 | AG15: 0 | AH15: =G15+SUM(X15:AG15) -> 8594040 | AI15: =W15-AH15 -> -4629358.7 | AJ15: =AJ14+AI15 -> -33037702 | AK15: =O15*Допущения!$F$58*Допущения!$F$59 -> 63168.281 | AL15: =T15*Допущения!$F$72 -> 177120.39 | AM15: =IF(MOD(A15,12)=0,INDEX($F$70:$F$74,B15),0) -> 0 | AN15: =AI15-AM15 -> -4629358.7 | AO15: =1/(1+Допущения!$F$74)^A15 -> 0.84729272 | AP15: =IF(AND(A15>Допущения!$F$19,MIN(AI15:AI$65)>0),A15,"") | AQ15: =IF(MIN(AJ15:AJ$65)>0,A15,"")
A16: 11 | B16: =INT((A16-1)/12)+1 -> 1 | C16: Масштабирование | D16: =(1+Допущения!$F$11)^(B16-1) -> 1 | E16: =(1+Допущения!$F$12)^(B16-1) -> 1 | F16: =Допущения!$F$71*E16 -> 2465.68 | G16: =MIN(G15*(1+Допущения!$F$33),Допущения!$F$34) -> 685529.71 | H16: =MIN(Допущения!$F$30,G16/Допущения!$F$29) -> 300 | I16: =MAX(0,G16-H16*Допущения!$F$29)/Допущения!$F$31 -> 39.254951 | J16: =IF(A16>=Допущения!$F$35,Допущения!$F$36,0) -> 40 | K16: =H16+I16+J16 -> 379.25495 | L16: =(L15-K15)*(1-Допущения!$F$44)+K15*(1-Допущения!$F$43)+K16 -> 1942.666 | M16: =IF(A16>=Допущения!$F$38,Допущения!$F$73/Допущения!$F$42*MIN(Допущения!$F$42,A16-Допущения!$F$38+1),0) -> 60 | N16: =N15*(1-Допущения!$F$45)+M16 -> 232.51904 | O16: =L16+N16 -> 2175.1851 | P16: =L16*Допущения!$F$25 -> 582.79981 | Q16: =L16*(1-Допущения!$F$25)+N16 -> 1592.3853 | R16: =MAX(Допущения!$F$18,ROUNDUP(Q16/Допущения!$F$68+P16/Допущения!$F$69,0)) -> 32 | S16: =ROUNDUP(R16/Допущения!$F$48,0) -> 4 | T16: =L16*F16/(1+Допущения!$F$6) -> 3926223.6 | U16: =N16*Допущения!$F$28*E16/(1+Допущения!$F$6) -> 285884.07 | V16: =O16*Допущения!$F$26*Допущения!$F$27/(1+Допущения!$F$6) -> 267440.79 | W16: =T16+U16+V16 -> 4479548.4 | X16: =J16*Допущения!$F$37 -> 20000 | Y16: =(R16*Допущения!$F$47+S16*Допущения!$F$49)*D16*Допущения!$F$9 -> 4218480 | Z16: =(MAX(0,R16-R15)+R16*Допущения!$F$50/12)*Допущения!$F$51*D16 -> 372000 | AA16: =O16*(Допущения!$F$53+Допущения!$F$54)+(L16*F16+N16*Допущения!$F$28*E16)*Допущения!$F$13 -> 1060455.2 | AB16: =(R16+S16)*Допущения!$F$52 -> 97200 | AC16: =SUMPRODUCT(Допущения!$B$84:$B$91,Допущения!$C$84:$C$91,--(Допущения!$D$84:$D$91<=A16))*D16*Допущения!$F$9 -> 1966020 | AD16: =(AC16+Y16)*Допущения!$F$14 -> 618450 | AE16: =Допущения!$F$55+Допущения!$F$56*O16/1000+Допущения!$F$57 -> 157401.48 | AF16: =SUMIF(Допущения!$B$95:$B$103,A16,Допущения!$C$95:$C$103) -> 350000 | AG16: 0 | AH16: =G16+SUM(X16:AG16) -> 9545536.4 | AI16: =W16-AH16 -> -5065988 | AJ16: =AJ15+AI16 -> -38103690 | AK16: =O16*Допущения!$F$58*Допущения!$F$59 -> 71781.107 | AL16: =T16*Допущения!$F$72 -> 197960.85 | AM16: =IF(MOD(A16,12)=0,INDEX($F$70:$F$74,B16),0) -> 0 | AN16: =AI16-AM16 -> -5065988 | AO16: =1/(1+Допущения!$F$74)^A16 -> 0.833368 | AP16: =IF(AND(A16>Допущения!$F$19,MIN(AI16:AI$65)>0),A16,"") | AQ16: =IF(MIN(AJ16:AJ$65)>0,A16,"")
A17: 12 | B17: =INT((A17-1)/12)+1 -> 1 | C17: Масштабирование | D17: =(1+Допущения!$F$11)^(B17-1) -> 1 | E17: =(1+Допущения!$F$12)^(B17-1) -> 1 | F17: =Допущения!$F$71*E17 -> 2465.68 | G17: =MIN(G16*(1+Допущения!$F$33),Допущения!$F$34) -> 740372.08 | H17: =MIN(Допущения!$F$30,G17/Допущения!$F$29) -> 300 | I17: =MAX(0,G17-H17*Допущения!$F$29)/Допущения!$F$31 -> 48.395347 | J17: =IF(A17>=Допущения!$F$35,Допущения!$F$36,0) -> 40 | K17: =H17+I17+J17 -> 388.39535 | L17: =(L16-K16)*(1-Допущения!$F$44)+K16*(1-Допущения!$F$43)+K17 -> 2142.443 | M17: =IF(A17>=Допущения!$F$38,Допущения!$F$73/Допущения!$F$42*MIN(Допущения!$F$42,A17-Допущения!$F$38+1),0) -> 60 | N17: =N16*(1-Допущения!$F$45)+M17 -> 287.86866 | O17: =L17+N17 -> 2430.3116 | P17: =L17*Допущения!$F$25 -> 642.73289 | Q17: =L17*(1-Допущения!$F$25)+N17 -> 1787.5787 | R17: =MAX(Допущения!$F$18,ROUNDUP(Q17/Допущения!$F$68+P17/Допущения!$F$69,0)) -> 36 | S17: =ROUNDUP(R17/Допущения!$F$48,0) -> 4 | T17: =L17*F17/(1+Допущения!$F$6) -> 4329982.6 | U17: =N17*Допущения!$F$28*E17/(1+Допущения!$F$6) -> 353936.88 | V17: =O17*Допущения!$F$26*Допущения!$F$27/(1+Допущения!$F$6) -> 298808.81 | W17: =T17+U17+V17 -> 4982728.3 | X17: =J17*Допущения!$F$37 -> 20000 | Y17: =(R17*Допущения!$F$47+S17*Допущения!$F$49)*D17*Допущения!$F$9 -> 4661160 | Z17: =(MAX(0,R17-R16)+R17*Допущения!$F$50/12)*Допущения!$F$51*D17 -> 379750 | AA17: =O17*(Допущения!$F$53+Допущения!$F$54)+(L17*F17+N17*Допущения!$F$28*E17)*Допущения!$F$13 -> 1184347.5 | AB17: =(R17+S17)*Допущения!$F$52 -> 108000 | AC17: =SUMPRODUCT(Допущения!$B$84:$B$91,Допущения!$C$84:$C$91,--(Допущения!$D$84:$D$91<=A17))*D17*Допущения!$F$9 -> 1966020 | AD17: =(AC17+Y17)*Допущения!$F$14 -> 662718 | AE17: =Допущения!$F$55+Допущения!$F$56*O17/1000+Допущения!$F$57 -> 159442.49 | AF17: =SUMIF(Допущения!$B$95:$B$103,A17,Допущения!$C$95:$C$103) -> 300000 | AG17: 0 | AH17: =G17+SUM(X17:AG17) -> 10181810 | AI17: =W17-AH17 -> -5199081.8 | AJ17: =AJ16+AI17 -> -43302772 | AK17: =O17*Допущения!$F$58*Допущения!$F$59 -> 80200.284 | AL17: =T17*Допущения!$F$72 -> 218318.45 | AM17: =IF(MOD(A17,12)=0,INDEX($F$70:$F$74,B17),0) -> 0 | AN17: =AI17-AM17 -> -5199081.8 | AO17: =1/(1+Допущения!$F$74)^A17 -> 0.81967213 | AP17: =IF(AND(A17>Допущения!$F$19,MIN(AI17:AI$65)>0),A17,"") | AQ17: =IF(MIN(AJ17:AJ$65)>0,A17,"")
A18: 13 | B18: =INT((A18-1)/12)+1 -> 2 | C18: Масштабирование | D18: =(1+Допущения!$F$11)^(B18-1) -> 1.08 | E18: =(1+Допущения!$F$12)^(B18-1) -> 1.07 | F18: =Допущения!$F$71*E18 -> 2638.2776 | G18: =MIN(G17*(1+Допущения!$F$33),Допущения!$F$34) -> 799601.85 | H18: =MIN(Допущения!$F$30,G18/Допущения!$F$29) -> 300 | I18: =MAX(0,G18-H18*Допущения!$F$29)/Допущения!$F$31 -> 58.266975 | J18: =IF(A18>=Допущения!$F$35,Допущения!$F$36,0) -> 40 | K18: =H18+I18+J18 -> 398.26698 | L18: =(L17-K17)*(1-Допущения!$F$44)+K17*(1-Допущения!$F$43)+K18 -> 2338.3682 | M18: =IF(A18>=Допущения!$F$38,Допущения!$F$73/Допущения!$F$42*MIN(Допущения!$F$42,A18-Допущения!$F$38+1),0) -> 60 | N18: =N17*(1-Допущения!$F$45)+M18 -> 342.11129 | O18: =L18+N18 -> 2680.4795 | P18: =L18*Допущения!$F$25 -> 701.51047 | Q18: =L18*(1-Допущения!$F$25)+N18 -> 1978.9691 | R18: =MAX(Допущения!$F$18,ROUNDUP(Q18/Допущения!$F$68+P18/Допущения!$F$69,0)) -> 39 | S18: =ROUNDUP(R18/Допущения!$F$48,0) -> 4 | T18: =L18*F18/(1+Допущения!$F$6) -> 5056774.2 | U18: =N18*Допущения!$F$28*E18/(1+Допущения!$F$6) -> 450072.64 | V18: =O18*Допущения!$F$26*Допущения!$F$27/(1+Допущения!$F$6) -> 329567.16 | W18: =T18+U18+V18 -> 5836414 | X18: =J18*Допущения!$F$37 -> 20000 | Y18: =(R18*Допущения!$F$47+S18*Допущения!$F$49)*D18*Допущения!$F$9 -> 5392623.6 | Z18: =(MAX(0,R18-R17)+R18*Допущения!$F$50/12)*Допущения!$F$51*D18 -> 332707.5 | AA18: =O18*(Допущения!$F$53+Допущения!$F$54)+(L18*F18+N18*Допущения!$F$28*E18)*Допущения!$F$13 -> 1313743.7 | AB18: =(R18+S18)*Допущения!$F$52 -> 116100 | AC18: =SUMPRODUCT(Допущения!$B$84:$B$91,Допущения!$C$84:$C$91,--(Допущения!$D$84:$D$91<=A18))*D18*Допущения!$F$9 -> 2123301.6 | AD18: =(AC18+Y18)*Допущения!$F$14 -> 751592.52 | AE18: =Допущения!$F$55+Допущения!$F$56*O18/1000+Допущения!$F$57 -> 161443.84 | AF18: =SUMIF(Допущения!$B$95:$B$103,A18,Допущения!$C$95:$C$103) -> 0 | AG18: 0 | AH18: =G18+SUM(X18:AG18) -> 11011115 | AI18: =W18-AH18 -> -5174700.6 | AJ18: =AJ17+AI18 -> -48477473 | AK18: =O18*Допущения!$F$58*Допущения!$F$59 -> 88455.825 | AL18: =T18*Допущения!$F$72 -> 254963.41 | AM18: =IF(MOD(A18,12)=0,INDEX($F$70:$F$74,B18),0) -> 0 | AN18: =AI18-AM18 -> -5174700.6 | AO18: =1/(1+Допущения!$F$74)^A18 -> 0.80620134 | AP18: =IF(AND(A18>Допущения!$F$19,MIN(AI18:AI$65)>0),A18,"") | AQ18: =IF(MIN(AJ18:AJ$65)>0,A18,"")
A19: 14 | B19: =INT((A19-1)/12)+1 -> 2 | C19: Масштабирование | D19: =(1+Допущения!$F$11)^(B19-1) -> 1.08 | E19: =(1+Допущения!$F$12)^(B19-1) -> 1.07 | F19: =Допущения!$F$71*E19 -> 2638.2776 | G19: =MIN(G18*(1+Допущения!$F$33),Допущения!$F$34) -> 863570 | H19: =MIN(Допущения!$F$30,G19/Допущения!$F$29) -> 300 | I19: =MAX(0,G19-H19*Допущения!$F$29)/Допущения!$F$31 -> 68.928333 | J19: =IF(A19>=Допущения!$F$35,Допущения!$F$36,0) -> 40 | K19: =H19+I19+J19 -> 408.92833 | L19: =(L18-K18)*(1-Допущения!$F$44)+K18*(1-Допущения!$F$43)+K19 -> 2531.3238 | M19: =IF(A19>=Допущения!$F$38,Допущения!$F$73/Допущения!$F$42*MIN(Допущения!$F$42,A19-Допущения!$F$38+1),0) -> 60 | N19: =N18*(1-Допущения!$F$45)+M19 -> 395.26906 | O19: =L19+N19 -> 2926.5928 | P19: =L19*Допущения!$F$25 -> 759.39713 | Q19: =L19*(1-Допущения!$F$25)+N19 -> 2167.1957 | R19: =MAX(Допущения!$F$18,ROUNDUP(Q19/Допущения!$F$68+P19/Допущения!$F$69,0)) -> 43 | S19: =ROUNDUP(R19/Допущения!$F$48,0) -> 5 | T19: =L19*F19/(1+Допущения!$F$6) -> 5474044.9 | U19: =N19*Допущения!$F$28*E19/(1+Допущения!$F$6) -> 520005.61 | V19: =O19*Допущения!$F$26*Допущения!$F$27/(1+Допущения!$F$6) -> 359826.99 | W19: =T19+U19+V19 -> 6353877.5 | X19: =J19*Допущения!$F$37 -> 20000 | Y19: =(R19*Допущения!$F$47+S19*Допущения!$F$49)*D19*Допущения!$F$9 -> 6053518.8 | Z19: =(MAX(0,R19-R18)+R19*Допущения!$F$50/12)*Допущения!$F$51*D19 -> 424777.5 | AA19: =O19*(Допущения!$F$53+Допущения!$F$54)+(L19*F19+N19*Допущения!$F$28*E19)*Допущения!$F$13 -> 1433963.2 | AB19: =(R19+S19)*Допущения!$F$52 -> 129600 | AC19: =SUMPRODUCT(Допущения!$B$84:$B$91,Допущения!$C$84:$C$91,--(Допущения!$D$84:$D$91<=A19))*D19*Допущения!$F$9 -> 2123301.6 | AD19: =(AC19+Y19)*Допущения!$F$14 -> 817682.04 | AE19: =Допущения!$F$55+Допущения!$F$56*O19/1000+Допущения!$F$57 -> 163412.74 | AF19: =SUMIF(Допущения!$B$95:$B$103,A19,Допущения!$C$95:$C$103) -> 0 | AG19: 0 | AH19: =G19+SUM(X19:AG19) -> 12029826 | AI19: =W19-AH19 -> -5675948.3 | AJ19: =AJ18+AI19 -> -54153421 | AK19: =O19*Допущения!$F$58*Допущения!$F$59 -> 96577.563 | AL19: =T19*Допущения!$F$72 -> 276002.26 | AM19: =IF(MOD(A19,12)=0,INDEX($F$70:$F$74,B19),0) -> 0 | AN19: =AI19-AM19 -> -5675948.3 | AO19: =1/(1+Допущения!$F$74)^A19 -> 0.79295194 | AP19: =IF(AND(A19>Допущения!$F$19,MIN(AI19:AI$65)>0),A19,"") | AQ19: =IF(MIN(AJ19:AJ$65)>0,A19,"")
A20: 15 | B20: =INT((A20-1)/12)+1 -> 2 | C20: Масштабирование | D20: =(1+Допущения!$F$11)^(B20-1) -> 1.08 | E20: =(1+Допущения!$F$12)^(B20-1) -> 1.07 | F20: =Допущения!$F$71*E20 -> 2638.2776 | G20: =MIN(G19*(1+Допущения!$F$33),Допущения!$F$34) -> 932655.6 | H20: =MIN(Допущения!$F$30,G20/Допущения!$F$29) -> 300 | I20: =MAX(0,G20-H20*Допущения!$F$29)/Допущения!$F$31 -> 80.4426 | J20: =IF(A20>=Допущения!$F$35,Допущения!$F$36,0) -> 40 | K20: =H20+I20+J20 -> 420.4426 | L20: =(L19-K19)*(1-Допущения!$F$44)+K19*(1-Допущения!$F$43)+K20 -> 2722.1905 | M20: =IF(A20>=Допущения!$F$38,Допущения!$F$73/Допущения!$F$42*MIN(Допущения!$F$42,A20-Допущения!$F$38+1),0) -> 60 | N20: =N19*(1-Допущения!$F$45)+M20 -> 447.36368 | O20: =L20+N20 -> 3169.5542 | P20: =L20*Допущения!$F$25 -> 816.65716 | Q20: =L20*(1-Допущения!$F$25)+N20 -> 2352.8971 | R20: =MAX(Допущения!$F$18,ROUNDUP(Q20/Допущения!$F$68+P20/Допущения!$F$69,0)) -> 46 | S20: =ROUNDUP(R20/Допущения!$F$48,0) -> 5 | T20: =L20*F20/(1+Допущения!$F$6) -> 5886798.6 | U20: =N20*Допущения!$F$28*E20/(1+Допущения!$F$6) -> 588539.93 | V20: =O20*Допущения!$F$26*Допущения!$F$27/(1+Допущения!$F$6) -> 389699.29 | W20: =T20+U20+V20 -> 6865037.9 | X20: =J20*Допущения!$F$37 -> 20000 | Y20: =(R20*Допущения!$F$47+S20*Допущения!$F$49)*D20*Допущения!$F$9 -> 6412089.6 | Z20: =(MAX(0,R20-R19)+R20*Допущения!$F$50/12)*Допущения!$F$51*D20 -> 347355 | AA20: =O20*(Допущения!$F$53+Допущения!$F$54)+(L20*F20+N20*Допущения!$F$28*E20)*Допущения!$F$13 -> 1552650.1 | AB20: =(R20+S20)*Допущения!$F$52 -> 137700 | AC20: =SUMPRODUCT(Допущения!$B$84:$B$91,Допущения!$C$84:$C$91,--(Допущения!$D$84:$D$91<=A20))*D20*Допущения!$F$9 -> 2123301.6 | AD20: =(AC20+Y20)*Допущения!$F$14 -> 853539.12 | AE20: =Допущения!$F$55+Допущения!$F$56*O20/1000+Допущения!$F$57 -> 165356.43 | AF20: =SUMIF(Допущения!$B$95:$B$103,A20,Допущения!$C$95:$C$103) -> 0 | AG20: 0 | AH20: =G20+SUM(X20:AG20) -> 12544647 | AI20: =W20-AH20 -> -5679609.6 | AJ20: =AJ19+AI20 -> -59833030 | AK20: =O20*Допущения!$F$58*Допущения!$F$59 -> 104595.29 | AL20: =T20*Допущения!$F$72 -> 296813.38 | AM20: =IF(MOD(A20,12)=0,INDEX($F$70:$F$74,B20),0) -> 0 | AN20: =AI20-AM20 -> -5679609.6 | AO20: =1/(1+Допущения!$F$74)^A20 -> 0.77992028 | AP20: =IF(AND(A20>Допущения!$F$19,MIN(AI20:AI$65)>0),A20,"") | AQ20: =IF(MIN(AJ20:AJ$65)>0,A20,"")
A21: 16 | B21: =INT((A21-1)/12)+1 -> 2 | C21: Масштабирование | D21: =(1+Допущения!$F$11)^(B21-1) -> 1.08 | E21: =(1+Допущения!$F$12)^(B21-1) -> 1.07 | F21: =Допущения!$F$71*E21 -> 2638.2776 | G21: =MIN(G20*(1+Допущения!$F$33),Допущения!$F$34) -> 1007268 | H21: =MIN(Допущения!$F$30,G21/Допущения!$F$29) -> 300 | I21: =MAX(0,G21-H21*Допущения!$F$29)/Допущения!$F$31 -> 92.878008 | J21: =IF(A21>=Допущения!$F$35,Допущения!$F$36,0) -> 40 | K21: =H21+I21+J21 -> 432.87801 | L21: =(L20-K20)*(1-Допущения!$F$44)+K20*(1-Допущения!$F$43)+K21 -> 2911.853 | M21: =IF(A21>=Допущения!$F$38,Допущения!$F$73/Допущения!$F$42*MIN(Допущения!$F$42,A21-Допущения!$F$38+1),0) -> 60 | N21: =N20*(1-Допущения!$F$45)+M21 -> 498.41641 | O21: =L21+N21 -> 3410.2694 | P21: =L21*Допущения!$F$25 -> 873.55591 | Q21: =L21*(1-Допущения!$F$25)+N21 -> 2536.7135 | R21: =MAX(Допущения!$F$18,ROUNDUP(Q21/Допущения!$F$68+P21/Допущения!$F$69,0)) -> 50 | S21: =ROUNDUP(R21/Допущения!$F$48,0) -> 5 | T21: =L21*F21/(1+Допущения!$F$6) -> 6296948.1 | U21: =N21*Допущения!$F$28*E21/(1+Допущения!$F$6) -> 655703.55 | V21: =O21*Допущения!$F$26*Допущения!$F$27/(1+Допущения!$F$6) -> 419295.42 | W21: =T21+U21+V21 -> 7371947 | X21: =J21*Допущения!$F$37 -> 20000 | Y21: =(R21*Допущения!$F$47+S21*Допущения!$F$49)*D21*Допущения!$F$9 -> 6890184 | Z21: =(MAX(0,R21-R20)+R21*Допущения!$F$50/12)*Допущения!$F$51*D21 -> 439425 | AA21: =O21*(Допущения!$F$53+Допущения!$F$54)+(L21*F21+N21*Допущения!$F$28*E21)*Допущения!$F$13 -> 1670250.1 | AB21: =(R21+S21)*Допущения!$F$52 -> 148500 | AC21: =SUMPRODUCT(Допущения!$B$84:$B$91,Допущения!$C$84:$C$91,--(Допущения!$D$84:$D$91<=A21))*D21*Допущения!$F$9 -> 2123301.6 | AD21: =(AC21+Y21)*Допущения!$F$14 -> 901348.56 | AE21: =Допущения!$F$55+Допущения!$F$56*O21/1000+Допущения!$F$57 -> 167282.16 | AF21: =SUMIF(Допущения!$B$95:$B$103,A21,Допущения!$C$95:$C$103) -> 0 | AG21: 0 | AH21: =G21+SUM(X21:AG21) -> 13367559 | AI21: =W21-AH21 -> -5995612.5 | AJ21: =AJ20+AI21 -> -65828643 | AK21: =O21*Допущения!$F$58*Допущения!$F$59 -> 112538.89 | AL21: =T21*Допущения!$F$72 -> 317493.18 | AM21: =IF(MOD(A21,12)=0,INDEX($F$70:$F$74,B21),0) -> 0 | AN21: =AI21-AM21 -> -5995612.5 | AO21: =1/(1+Допущения!$F$74)^A21 -> 0.76710278 | AP21: =IF(AND(A21>Допущения!$F$19,MIN(AI21:AI$65)>0),A21,"") | AQ21: =IF(MIN(AJ21:AJ$65)>0,A21,"")
... A65: 60 | B65: =INT((A65-1)/12)+1 -> 5 | C65: Масштабирование | D65: =(1+Допущения!$F$11)^(B65-1) -> 1.360489 | E65: =(1+Допущения!$F$12)^(B65-1) -> 1.310796 | F65: =Допущения!$F$71*E65 -> 3232.0035 | G65: =MIN(G64*(1+Допущения!$F$33),Допущения!$F$34) -> 2500000 | H65: =MIN(Допущения!$F$30,G65/Допущения!$F$29) -> 300 | I65: =MAX(0,G65-H65*Допущения!$F$29)/Допущения!$F$31 -> 341.66667 | J65: =IF(A65>=Допущения!$F$35,Допущения!$F$36,0) -> 40 | K65: =H65+I65+J65 -> 681.66667 | L65: =(L64-K64)*(1-Допущения!$F$44)+K64*(1-Допущения!$F$43)+K65 -> 8682.2156 | M65: =IF(A65>=Допущения!$F$38,Допущения!$F$73/Допущения!$F$42*MIN(Допущения!$F$42,A65-Допущения!$F$38+1),0) -> 60 | N65: =N64*(1-Допущения!$F$45)+M65 -> 1971.5993 | O65: =L65+N65 -> 10653.815 | P65: =L65*Допущения!$F$25 -> 2604.6647 | Q65: =L65*(1-Допущения!$F$25)+N65 -> 8049.1503 | R65: =MAX(Допущения!$F$18,ROUNDUP(Q65/Допущения!$F$68+P65/Допущения!$F$69,0)) -> 153 | S65: =ROUNDUP(R65/Допущения!$F$48,0) -> 16 | T65: =L65*F65/(1+Допущения!$F$6) -> 23000780 | U65: =N65*Допущения!$F$28*E65/(1+Допущения!$F$6) -> 3177497.4 | V65: =O65*Допущения!$F$26*Допущения!$F$27/(1+Допущения!$F$6) -> 1309895.3 | W65: =T65+U65+V65 -> 27488172 | X65: =J65*Допущения!$F$37 -> 20000 | Y65: =(R65*Допущения!$F$47+S65*Допущения!$F$49)*D65*Допущения!$F$9 -> 26720915 | Z65: =(MAX(0,R65-R64)+R65*Допущения!$F$50/12)*Допущения!$F$51*D65 -> 403299.95 | AA65: =O65*(Допущения!$F$53+Допущения!$F$54)+(L65*F65+N65*Допущения!$F$28*E65)*Допущения!$F$13 -> 5315822.6 | AB65: =(R65+S65)*Допущения!$F$52 -> 456300 | AC65: =SUMPRODUCT(Допущения!$B$84:$B$91,Допущения!$C$84:$C$91,--(Допущения!$D$84:$D$91<=A65))*D65*Допущения!$F$9 -> 2674748.5 | AD65: =(AC65+Y65)*Допущения!$F$14 -> 2939566.3 | AE65: =Допущения!$F$55+Допущения!$F$56*O65/1000+Допущения!$F$57 -> 225230.52 | AF65: =SUMIF(Допущения!$B$95:$B$103,A65,Допущения!$C$95:$C$103) -> 0 | AG65: 0 | AH65: =G65+SUM(X65:AG65) -> 41255883 | AI65: =W65-AH65 -> -13767710 | AJ65: =AJ64+AI65 -> -5.5299689e+08 | AK65: =O65*Допущения!$F$58*Допущения!$F$59 -> 351575.89 | AL65: =T65*Допущения!$F$72 -> 1159703.2 | AM65: =IF(MOD(A65,12)=0,INDEX($F$70:$F$74,B65),0) -> 0 | AN65: =AI65-AM65 -> -13767710 | AO65: =1/(1+Допущения!$F$74)^A65 -> 0.36999925 | AP65: =IF(AND(A65>Допущения!$F$19,MIN(AI65:AI$65)>0),A65,"") | AQ65: =IF(MIN(AJ65:AJ$65)>0,A65,"")
A68: Годовые итоги и налог на прибыль с переносом убытков
A69: Год | B69: Выручка, руб. | C69: Операционный результат, руб. | D69: Убыток к переносу на начало, руб. | E69: Зачтено убытка, руб. | F69: Налог на прибыль, руб. | G69: Убыток к переносу на конец, руб. | H69: Кросс-продажи, руб.
A70: 1 | B70: =SUMIF($B$6:$B$65,A70,$W$6:$W$65) -> 26337800 | C70: =SUMIF($B$6:$B$65,A70,$AI$6:$AI$65) -> -43302772 | D70: 0 | E70: =IF(C70>0,MIN(D70,C70*Допущения!$F$8),0) -> 0 | F70: =IF(C70>0,(C70-E70)*Допущения!$F$7,0) -> 0 | G70: =D70+IF(C70<0,-C70,0)-E70 -> 43302772 | H70: =SUMIF($B$6:$B$65,A70,$AK$6:$AK$65) -> 412171.64
A71: 2 | B71: =SUMIF($B$6:$B$65,A71,$W$6:$W$65) -> 1.038415e+08 | C71: =SUMIF($B$6:$B$65,A71,$AI$6:$AI$65) -> -79712783 | D71: =G70 -> 43302772 | E71: =IF(C71>0,MIN(D71,C71*Допущения!$F$8),0) -> 0 | F71: =IF(C71>0,(C71-E71)*Допущения!$F$7,0) -> 0 | G71: =D71+IF(C71<0,-C71,0)-E71 -> 1.2301556e+08 | H71: =SUMIF($B$6:$B$65,A71,$AK$6:$AK$65) -> 1589743.4
A72: 3 | B72: =SUMIF($B$6:$B$65,A72,$W$6:$W$65) -> 1.9341124e+08 | C72: =SUMIF($B$6:$B$65,A72,$AI$6:$AI$65) -> -1.2193943e+08 | D72: =G71 -> 1.2301556e+08 | E72: =IF(C72>0,MIN(D72,C72*Допущения!$F$8),0) -> 0 | F72: =IF(C72>0,(C72-E72)*Допущения!$F$7,0) -> 0 | G72: =D72+IF(C72<0,-C72,0)-E72 -> 2.4495498e+08 | H72: =SUMIF($B$6:$B$65,A72,$AK$6:$AK$65) -> 2785470.1
A73: 4 | B73: =SUMIF($B$6:$B$65,A73,$W$6:$W$65) -> 2.6792167e+08 | C73: =SUMIF($B$6:$B$65,A73,$AI$6:$AI$65) -> -1.4498746e+08 | D73: =G72 -> 2.4495498e+08 | E73: =IF(C73>0,MIN(D73,C73*Допущения!$F$8),0) -> 0 | F73: =IF(C73>0,(C73-E73)*Допущения!$F$7,0) -> 0 | G73: =D73+IF(C73<0,-C73,0)-E73 -> 3.8994245e+08 | H73: =SUMIF($B$6:$B$65,A73,$AK$6:$AK$65) -> 3628427.8
A74: 5 | B74: =SUMIF($B$6:$B$65,A74,$W$6:$W$65) -> 3.1970916e+08 | C74: =SUMIF($B$6:$B$65,A74,$AI$6:$AI$65) -> -1.6305444e+08 | D74: =G73 -> 3.8994245e+08 | E74: =IF(C74>0,MIN(D74,C74*Допущения!$F$8),0) -> 0 | F74: =IF(C74>0,(C74-E74)*Допущения!$F$7,0) -> 0 | G74: =D74+IF(C74<0,-C74,0)-E74 -> 5.5299689e+08 | H74: =SUMIF($B$6:$B$65,A74,$AK$6:$AK$65) -> 4079768.4
A75: Итого | B75: =SUM(B70:B74) -> 9.1122138e+08 | C75: =SUM(C70:C74) -> -5.5299689e+08 | F75: =SUM(F70:F74) -> 0 | H75: =SUM(H70:H74) -> 12495581

Sheet Чувствительность
A1: Чувствительность NPV до налога за 60 мес. к параметрам (базовый сценарий)
A2: Результаты получены многократным прогоном модели в model.py (каждая строка требует отдельного пересчета всех 60 месяцев), поэтому перенесены значениями. Пересчет: python model.py.
A4: NPV базового сценария, руб. | B4: 23483259
A6: Параметр | B6: NPV при -25%, руб. | C6: NPV при +25%, руб. | D6: Размах, руб. | E6: Ранг
A7: Цены тарифов | B7: -110775180 | C7: 157741699 | D7: =ABS(C7-B7) -> 268516879 | E7: 1
A8: Минуты координатора на семью | B8: 98617809 | C8: -51480353 | D8: =ABS(C8-B8) -> 150098162 | E8: 2
A9: Зарплата координатора | B9: 86719051 | C9: -39752532 | D9: =ABS(C9-B9) -> 126471583 | E9: 3
A10: Отток B2C | B10: 48549307 | C10: 4109792 | D10: =ABS(C10-B10) -> 44439515 | E10: 4
A11: CAC внешних каналов | B11: 44225724 | C11: 10795056 | D11: =ABS(C11-B11) -> 33430668 | E11: 5
A12: Емкость внутренних каналов | B12: 5843012 | C12: 38665797 | D12: =ABS(C12-B12) -> 32822785 | E12: 6
A13: Отток первого месяца | B13: 35948446 | C13: 10576321 | D13: =ABS(C13-B13) -> 25372125 | E13: 7
A14: Доля Расширенного | B14: 17293108 | C14: 29093310 | D14: =ABS(C14-B14) -> 11800202 | E14: 8
A15: Активация B2B2C | B15: 19123484 | C15: 27188703 | D15: =ABS(C15-B15) -> 8065219 | E15: 9
A17: Для параметра «Цены тарифов» одновременно меняются цены обоих тарифов и опции B2B2C.

Sheet Монте-Карло
A1: Анализ рисков методом Монте-Карло
A2: Результаты получены многократным прогоном модели в model.py (каждая строка требует отдельного пересчета всех 60 месяцев), поэтому перенесены значениями. Пересчет: python model.py.
A4: Треугольные распределения параметров
A5: Параметр | B5: Минимум | C5: Наиболее вероятное | D5: Максимум
A6: CAC во внешних каналах, руб. | B6: 4000 | C6: 6000 | D6: 8000
A7: Емкость внутренних каналов, семей/мес. | B7: 150 | C7: 300 | D7: 450
A8: Отток после первого месяца | B8: 0.15 | C8: 0.25 | D8: 0.35
A9: Отток B2C в месяц | B9: 0.04 | C9: 0.06 | D9: 0.08
A10: Множитель минут координатора | B10: 0.75 | C10: 1 | D10: 1.25
A11: Доля тарифа «Расширенный» | B11: 0.15 | C11: 0.25 | D11: 0.35
A12: Зарплата координатора, руб. | B12: 60000 | C12: 70000 | D12: 80000
A13: Активация B2B2C | B13: 0.01 | C13: 0.03 | D13: 0.05
A14: Новых корпоративных клиентов в месяц | B14: 0.4 | C14: 1 | D14: 1.6
A15: Покупки услуг партнеров, руб./мес. | B15: 500 | C15: 1500 | D15: 2500
A17: Результаты
A18: Показатель | B18: Значение
A19: Прогонов | B19: 5000
A20: Вероятность NPV(36 мес) > 0 | B20: 0.127
A21: Вероятность NPV(60 мес) > 0 | B21: 0.708
A22: NPV(60) P5, руб. | B22: -39827636
A23: NPV(60) P50, руб. | B23: 22762478
A24: NPV(60) P95, руб. | B24: 94371491
A25: Пиковая потребность P50, руб. | B25: 33506084
A26: Пиковая потребность P95, руб. | B26: 63297524
A27: Доля прогонов с окупаемостью за 60 мес | B27: 0.843
A28: Медианный месяц окупаемости (среди окупившихся) | B28: 41

Sheet Риски модели
A1: Подводные камни и их учет в модели
A3: Риск | B3: Суть | C3: Как учтено | D3: Влияние
A4: Подписку, вероятно, нельзя продавать от имени страховщика | B4: Ст. 6 закона 4015-1 ограничивает страховщика страховой деятельностью | C4: Оператор сервиса: сервисная компания группы; заключение юриста 200 тыс. в MVP и 100 тыс. в месяц после | D4: Высокое
A5: Запрет иностранных мессенджеров для финорганизаций | B5: 41-ФЗ от 01.04.2025, с 01.06.2025; плюс трансграничная передача медданных | C5: В MVP только MAX, СМС и звонки; Telegram исключен | D5: Высокое
A6: Медданные родителя это спецкатегория ПДн (152-ФЗ ст. 10) | B6: Нужно согласие самого родителя, а не ребенка | C6: Размещение в существующем контуре ИСПДн группы, доработка модели угроз 350 тыс. | D6: Высокое
A7: НДС 22% на подписку (425-ФЗ от 28.11.2025) | B7: Координация не медицинская услуга, льгота ст. 149 не применяется; 18% цены уходит в НДС | C7: Выручка в модели без НДС | D7: Высокое
A8: Нагрузка координатора ограничена временем | B8: Каждый живой звонок стоит минут; при еженедельных звонках всем экономика не сходится | C8: Нагрузка считается от бюджета минут; Базовый тариф с одним плановым звонком в месяц | D8: Высокое
A9: Отпуска, больничные, работа без выходных | B9: Робот звонит каждый день, флаги бывают в выходные | C9: Множитель покрытия 1,2 к числу координаторов | D9: Среднее
A10: Высокий отток в первый месяц | B10: Часть семей пробует и уходит | C10: Отдельный отток первого месяца 25% (порог H5) | D10: Среднее
A11: Рост CAC после исчерпания внутренних каналов | B11: Внутренние каналы дают ограниченный поток | C11: Два канала: внутренний до 300 семей в месяц по 1 500 руб., остальное по 6 000 руб. | D11: Высокое
